{
  "Zimbabwe": {
    "id": "ZWEFCMTVGGDPPT",
    "realtime_start": "2022-03-23",
    "realtime_end": "2022-03-23",
    "title": "Use of Financial Services: Key Indicators, Value of Mobile Money Transactions During the Reference Year for Zimbabwe",
    "observation_start": "2009-01-01",
    "observation_end": "2020-01-01",
    "frequency": "Annual",
    "frequency_short": "A",
    "units": "Percent of GDP",
    "units_short": "% of GDP",
    "seasonal_adjustment": "Not Seasonally Adjusted",
    "seasonal_adjustment_short": "NSA",
    "last_updated": "2021-09-01 10:03:26-05",
    "popularity": 1,
    "group_popularity": 1,
    "notes": "Copyright \u00a9 2016, International Monetary Fund. Reprinted with permission. Complete terms of use and contact details are available at http://www.imf.org/external/terms.htm."
  },
  "Afghanistan": {
    "id": "AFGFCMTVGGDPPT",
    "realtime_start": "2022-03-23",
    "realtime_end": "2022-03-23",
    "title": "Use of Financial Services: Key Indicators, Value of Mobile Money Transactions During the Reference Year for Afghanistan",
    "observation_start": "2012-01-01",
    "observation_end": "2019-01-01",
    "frequency": "Annual",
    "frequency_short": "A",
    "units": "Percent of GDP",
    "units_short": "% of GDP",
    "seasonal_adjustment": "Not Seasonally Adjusted",
    "seasonal_adjustment_short": "NSA",
    "last_updated": "2022-01-03 13:53:08-06",
    "popularity": 1,
    "group_popularity": 1,
    "notes": "Copyright \u00a9 2016, International Monetary Fund. Reprinted with permission. Complete terms of use and contact details are available at http://www.imf.org/external/terms.htm."
  },
  "Armenia": {
    "id": "ARMFCMTVGGDPPT",
    "realtime_start": "2022-03-23",
    "realtime_end": "2022-03-23",
    "title": "Use of Financial Services: Key Indicators, Value of Mobile Money Transactions During the Reference Year for Armenia",
    "observation_start": "2012-01-01",
    "observation_end": "2020-01-01",
    "frequency": "Annual",
    "frequency_short": "A",
    "units": "Percent of GDP",
    "units_short": "% of GDP",
    "seasonal_adjustment": "Not Seasonally Adjusted",
    "seasonal_adjustment_short": "NSA",
    "last_updated": "2021-08-02 13:30:42-05",
    "popularity": 1,
    "group_popularity": 1,
    "notes": "Copyright \u00a9 2016, International Monetary Fund. Reprinted with permission. Complete terms of use and contact details are available at http://www.imf.org/external/terms.htm."
  },
  "Austria": {
    "id": "AUTFCMTVGGDPPT",
    "realtime_start": "2022-03-23",
    "realtime_end": "2022-03-23",
    "title": "Use of Financial Services: Key Indicators, Value of Mobile Money Transactions During the Reference Year for Austria",
    "observation_start": "2004-01-01",
    "observation_end": "2015-01-01",
    "frequency": "Annual",
    "frequency_short": "A",
    "units": "Percent of GDP",
    "units_short": "% of GDP",
    "seasonal_adjustment": "Not Seasonally Adjusted",
    "seasonal_adjustment_short": "NSA",
    "last_updated": "2016-11-10 15:25:49-06",
    "popularity": 1,
    "group_popularity": 1,
    "notes": "Copyright \u00a9 2016, International Monetary Fund. Reprinted with permission. Complete terms of use and contact details are available at http://www.imf.org/external/terms.htm."
  },
  "Bangladesh": {
    "id": "BGDFCMTVGGDPPT",
    "realtime_start": "2022-03-23",
    "realtime_end": "2022-03-23",
    "title": "Use of Financial Services: Key Indicators, Value of Mobile Money Transactions During the Reference Year for Bangladesh",
    "observation_start": "2011-01-01",
    "observation_end": "2020-01-01",
    "frequency": "Annual",
    "frequency_short": "A",
    "units": "Percent of GDP",
    "units_short": "% of GDP",
    "seasonal_adjustment": "Not Seasonally Adjusted",
    "seasonal_adjustment_short": "NSA",
    "last_updated": "2021-08-02 13:29:59-05",
    "popularity": 1,
    "group_popularity": 1,
    "notes": "Copyright \u00a9 2016, International Monetary Fund. Reprinted with permission. Complete terms of use and contact details are available at http://www.imf.org/external/terms.htm."
  },
  "Benin": {
    "id": "BENFCMTVGGDPPT",
    "realtime_start": "2022-03-23",
    "realtime_end": "2022-03-23",
    "title": "Use of Financial Services: Key Indicators, Value of Mobile Money Transactions During the Reference Year for Benin",
    "observation_start": "2014-01-01",
    "observation_end": "2019-01-01",
    "frequency": "Annual",
    "frequency_short": "A",
    "units": "Percent of GDP",
    "units_short": "% of GDP",
    "seasonal_adjustment": "Not Seasonally Adjusted",
    "seasonal_adjustment_short": "NSA",
    "last_updated": "2021-09-01 10:05:47-05",
    "popularity": 1,
    "group_popularity": 1,
    "notes": "Copyright \u00a9 2016, International Monetary Fund. Reprinted with permission. Complete terms of use and contact details are available at http://www.imf.org/external/terms.htm."
  },
  "Botswana": {
    "id": "BWAFCMTVGGDPPT",
    "realtime_start": "2022-03-23",
    "realtime_end": "2022-03-23",
    "title": "Use of Financial Services: Key Indicators, Value of Mobile Money Transactions During the Reference Year for Botswana",
    "observation_start": "2010-01-01",
    "observation_end": "2020-01-01",
    "frequency": "Annual",
    "frequency_short": "A",
    "units": "Percent of GDP",
    "units_short": "% of GDP",
    "seasonal_adjustment": "Not Seasonally Adjusted",
    "seasonal_adjustment_short": "NSA",
    "last_updated": "2021-08-02 13:29:38-05",
    "popularity": 1,
    "group_popularity": 1,
    "notes": "Copyright \u00a9 2016, International Monetary Fund. Reprinted with permission. Complete terms of use and contact details are available at http://www.imf.org/external/terms.htm."
  },
  "Cameroon": {
    "id": "CMRFCMTVGGDPPT",
    "realtime_start": "2022-03-23",
    "realtime_end": "2022-03-23",
    "title": "Use of Financial Services: Key Indicators, Value of Mobile Money Transactions During the Reference Year for Cameroon",
    "observation_start": "2010-01-01",
    "observation_end": "2020-01-01",
    "frequency": "Annual",
    "frequency_short": "A",
    "units": "Percent of GDP",
    "units_short": "% of GDP",
    "seasonal_adjustment": "Not Seasonally Adjusted",
    "seasonal_adjustment_short": "NSA",
    "last_updated": "2022-01-03 13:53:03-06",
    "popularity": 1,
    "group_popularity": 1,
    "notes": "Copyright \u00a9 2016, International Monetary Fund. Reprinted with permission. Complete terms of use and contact details are available at http://www.imf.org/external/terms.htm."
  },
  "Chad": {
    "id": "TCDFCMTVGGDPPT",
    "realtime_start": "2022-03-23",
    "realtime_end": "2022-03-23",
    "title": "Use of Financial Services: Key Indicators, Value of Mobile Money Transactions During the Reference Year for Chad",
    "observation_start": "2014-01-01",
    "observation_end": "2017-01-01",
    "frequency": "Annual",
    "frequency_short": "A",
    "units": "Percent of GDP",
    "units_short": "% of GDP",
    "seasonal_adjustment": "Not Seasonally Adjusted",
    "seasonal_adjustment_short": "NSA",
    "last_updated": "2021-08-02 13:24:11-05",
    "popularity": 1,
    "group_popularity": 1,
    "notes": "Copyright \u00a9 2016, International Monetary Fund. Reprinted with permission. Complete terms of use and contact details are available at http://www.imf.org/external/terms.htm."
  },
  "Fiji": {
    "id": "FJIFCMTVGGDPPT",
    "realtime_start": "2022-03-23",
    "realtime_end": "2022-03-23",
    "title": "Use of Financial Services: Key Indicators, Value of Mobile Money Transactions During the Reference Year for Fiji",
    "observation_start": "2011-01-01",
    "observation_end": "2020-01-01",
    "frequency": "Annual",
    "frequency_short": "A",
    "units": "Percent of GDP",
    "units_short": "% of GDP",
    "seasonal_adjustment": "Not Seasonally Adjusted",
    "seasonal_adjustment_short": "NSA",
    "last_updated": "2021-08-02 13:33:08-05",
    "popularity": 1,
    "group_popularity": 1,
    "notes": "Copyright \u00a9 2016, International Monetary Fund. Reprinted with permission. Complete terms of use and contact details are available at http://www.imf.org/external/terms.htm."
  },
  "Ghana": {
    "id": "GHAFCMTVGGDPPT",
    "realtime_start": "2022-03-23",
    "realtime_end": "2022-03-23",
    "title": "Use of Financial Services: Key Indicators, Value of Mobile Money Transactions During the Reference Year for Ghana",
    "observation_start": "2012-01-01",
    "observation_end": "2018-01-01",
    "frequency": "Annual",
    "frequency_short": "A",
    "units": "Percent of GDP",
    "units_short": "% of GDP",
    "seasonal_adjustment": "Not Seasonally Adjusted",
    "seasonal_adjustment_short": "NSA",
    "last_updated": "2021-08-02 13:28:19-05",
    "popularity": 1,
    "group_popularity": 1,
    "notes": "Copyright \u00a9 2016, International Monetary Fund. Reprinted with permission. Complete terms of use and contact details are available at http://www.imf.org/external/terms.htm."
  },
  "Guinea": {
    "id": "GINFCMTVGGDPPT",
    "realtime_start": "2022-03-23",
    "realtime_end": "2022-03-23",
    "title": "Use of Financial Services: Key Indicators, Value of Mobile Money Transactions During the Reference Year for Guinea",
    "observation_start": "2013-01-01",
    "observation_end": "2020-01-01",
    "frequency": "Annual",
    "frequency_short": "A",
    "units": "Percent of GDP",
    "units_short": "% of GDP",
    "seasonal_adjustment": "Not Seasonally Adjusted",
    "seasonal_adjustment_short": "NSA",
    "last_updated": "2021-08-02 13:27:23-05",
    "popularity": 1,
    "group_popularity": 1,
    "notes": "Copyright \u00a9 2016, International Monetary Fund. Reprinted with permission. Complete terms of use and contact details are available at http://www.imf.org/external/terms.htm."
  },
  "Guyana": {
    "id": "GUYFCMTVGGDPPT",
    "realtime_start": "2022-03-23",
    "realtime_end": "2022-03-23",
    "title": "Use of Financial Services: Key Indicators, Value of Mobile Money Transactions During the Reference Year for Guyana",
    "observation_start": "2013-01-01",
    "observation_end": "2020-01-01",
    "frequency": "Annual",
    "frequency_short": "A",
    "units": "Percent of GDP",
    "units_short": "% of GDP",
    "seasonal_adjustment": "Not Seasonally Adjusted",
    "seasonal_adjustment_short": "NSA",
    "last_updated": "2021-08-02 13:27:53-05",
    "popularity": 1,
    "group_popularity": 1,
    "notes": "Copyright \u00a9 2016, International Monetary Fund. Reprinted with permission. Complete terms of use and contact details are available at http://www.imf.org/external/terms.htm."
  },
  "Haiti": {
    "id": "HTIFCMTVGGDPPT",
    "realtime_start": "2022-03-23",
    "realtime_end": "2022-03-23",
    "title": "Use of Financial Services: Key Indicators, Value of Mobile Money Transactions During the Reference Year for Haiti",
    "observation_start": "2014-01-01",
    "observation_end": "2015-01-01",
    "frequency": "Annual",
    "frequency_short": "A",
    "units": "Percent of GDP",
    "units_short": "% of GDP",
    "seasonal_adjustment": "Not Seasonally Adjusted",
    "seasonal_adjustment_short": "NSA",
    "last_updated": "2021-08-02 13:27:05-05",
    "popularity": 1,
    "group_popularity": 1,
    "notes": "Copyright \u00a9 2016, International Monetary Fund. Reprinted with permission. Complete terms of use and contact details are available at http://www.imf.org/external/terms.htm."
  },
  "Indonesia": {
    "id": "IDNFCMTVGGDPPT",
    "realtime_start": "2022-03-23",
    "realtime_end": "2022-03-23",
    "title": "Use of Financial Services: Key Indicators, Value of Mobile Money Transactions During the Reference Year for Indonesia",
    "observation_start": "2007-01-01",
    "observation_end": "2020-01-01",
    "frequency": "Annual",
    "frequency_short": "A",
    "units": "Percent of GDP",
    "units_short": "% of GDP",
    "seasonal_adjustment": "Not Seasonally Adjusted",
    "seasonal_adjustment_short": "NSA",
    "last_updated": "2021-08-02 13:26:57-05",
    "popularity": 1,
    "group_popularity": 1,
    "notes": "Copyright \u00a9 2016, International Monetary Fund. Reprinted with permission. Complete terms of use and contact details are available at http://www.imf.org/external/terms.htm."
  },
  "Jordan": {
    "id": "JORFCMTVGGDPPT",
    "realtime_start": "2022-03-23",
    "realtime_end": "2022-03-23",
    "title": "Use of Financial Services: Key Indicators, Value of Mobile Money Transactions During the Reference Year for Jordan",
    "observation_start": "2015-01-01",
    "observation_end": "2020-01-01",
    "frequency": "Annual",
    "frequency_short": "A",
    "units": "Percent of GDP",
    "units_short": "% of GDP",
    "seasonal_adjustment": "Not Seasonally Adjusted",
    "seasonal_adjustment_short": "NSA",
    "last_updated": "2021-08-02 13:26:20-05",
    "popularity": 1,
    "group_popularity": 1,
    "notes": "Copyright \u00a9 2016, International Monetary Fund. Reprinted with permission. Complete terms of use and contact details are available at http://www.imf.org/external/terms.htm."
  },
  "Kazakhstan": {
    "id": "KAZFCMTVGGDPPT",
    "realtime_start": "2022-03-23",
    "realtime_end": "2022-03-23",
    "title": "Use of Financial Services: Key Indicators, Value of Mobile Money Transactions During the Reference Year for Kazakhstan",
    "observation_start": "2013-01-01",
    "observation_end": "2013-01-01",
    "frequency": "Annual",
    "frequency_short": "A",
    "units": "Percent of GDP",
    "units_short": "% of GDP",
    "seasonal_adjustment": "Not Seasonally Adjusted",
    "seasonal_adjustment_short": "NSA",
    "last_updated": "2015-12-15 15:48:55-06",
    "popularity": 0,
    "group_popularity": 0,
    "notes": "Copyright \u00a9 2016, International Monetary Fund. Reprinted with permission. Complete terms of use and contact details are available at http://www.imf.org/external/terms.htm."
  },
  "Kenya": {
    "id": "KENFCMTVGGDPPT",
    "realtime_start": "2022-03-23",
    "realtime_end": "2022-03-23",
    "title": "Use of Financial Services: Key Indicators, Value of Mobile Money Transactions During the Reference Year for Kenya",
    "observation_start": "2007-01-01",
    "observation_end": "2020-01-01",
    "frequency": "Annual",
    "frequency_short": "A",
    "units": "Percent of GDP",
    "units_short": "% of GDP",
    "seasonal_adjustment": "Not Seasonally Adjusted",
    "seasonal_adjustment_short": "NSA",
    "last_updated": "2021-08-02 13:26:08-05",
    "popularity": 1,
    "group_popularity": 1,
    "notes": "Copyright \u00a9 2016, International Monetary Fund. Reprinted with permission. Complete terms of use and contact details are available at http://www.imf.org/external/terms.htm."
  },
  "Lesotho": {
    "id": "LSOFCMTVGGDPPT",
    "realtime_start": "2022-03-23",
    "realtime_end": "2022-03-23",
    "title": "Use of Financial Services: Key Indicators, Value of Mobile Money Transactions During the Reference Year for Lesotho",
    "observation_start": "2013-01-01",
    "observation_end": "2020-01-01",
    "frequency": "Annual",
    "frequency_short": "A",
    "units": "Percent of GDP",
    "units_short": "% of GDP",
    "seasonal_adjustment": "Not Seasonally Adjusted",
    "seasonal_adjustment_short": "NSA",
    "last_updated": "2022-01-03 13:52:34-06",
    "popularity": 1,
    "group_popularity": 1,
    "notes": "Copyright \u00a9 2016, International Monetary Fund. Reprinted with permission. Complete terms of use and contact details are available at http://www.imf.org/external/terms.htm."
  },
  "Liberia": {
    "id": "LBRFCMTVGGDPPT",
    "realtime_start": "2022-03-23",
    "realtime_end": "2022-03-23",
    "title": "Use of Financial Services: Key Indicators, Value of Mobile Money Transactions During the Reference Year for Liberia",
    "observation_start": "2017-01-01",
    "observation_end": "2019-01-01",
    "frequency": "Annual",
    "frequency_short": "A",
    "units": "Percent of GDP",
    "units_short": "% of GDP",
    "seasonal_adjustment": "Not Seasonally Adjusted",
    "seasonal_adjustment_short": "NSA",
    "last_updated": "2020-11-09 13:32:25-06",
    "popularity": 1,
    "group_popularity": 1,
    "notes": "Copyright \u00a9 2016, International Monetary Fund. Reprinted with permission. Complete terms of use and contact details are available at http://www.imf.org/external/terms.htm."
  },
  "Madagascar": {
    "id": "MDGFCMTVGGDPPT",
    "realtime_start": "2022-03-23",
    "realtime_end": "2022-03-23",
    "title": "Use of Financial Services: Key Indicators, Value of Mobile Money Transactions During the Reference Year for Madagascar",
    "observation_start": "2010-01-01",
    "observation_end": "2020-01-01",
    "frequency": "Annual",
    "frequency_short": "A",
    "units": "Percent of GDP",
    "units_short": "% of GDP",
    "seasonal_adjustment": "Not Seasonally Adjusted",
    "seasonal_adjustment_short": "NSA",
    "last_updated": "2022-01-03 13:52:18-06",
    "popularity": 1,
    "group_popularity": 1,
    "notes": "Copyright \u00a9 2016, International Monetary Fund. Reprinted with permission. Complete terms of use and contact details are available at http://www.imf.org/external/terms.htm."
  },
  "Malawi": {
    "id": "MWIFCMTVGGDPPT",
    "realtime_start": "2022-03-23",
    "realtime_end": "2022-03-23",
    "title": "Use of Financial Services: Key Indicators, Value of Mobile Money Transactions During the Reference Year for Malawi",
    "observation_start": "2012-01-01",
    "observation_end": "2019-01-01",
    "frequency": "Annual",
    "frequency_short": "A",
    "units": "Percent of GDP",
    "units_short": "% of GDP",
    "seasonal_adjustment": "Not Seasonally Adjusted",
    "seasonal_adjustment_short": "NSA",
    "last_updated": "2021-10-07 09:34:36-05",
    "popularity": 1,
    "group_popularity": 1,
    "notes": "Copyright \u00a9 2016, International Monetary Fund. Reprinted with permission. Complete terms of use and contact details are available at http://www.imf.org/external/terms.htm."
  },
  "Mauritius": {
    "id": "MUSFCMTVGGDPPT",
    "realtime_start": "2022-03-23",
    "realtime_end": "2022-03-23",
    "title": "Use of Financial Services: Key Indicators, Value of Mobile Money Transactions During the Reference Year for Mauritius",
    "observation_start": "2016-01-01",
    "observation_end": "2020-01-01",
    "frequency": "Annual",
    "frequency_short": "A",
    "units": "Percent of GDP",
    "units_short": "% of GDP",
    "seasonal_adjustment": "Not Seasonally Adjusted",
    "seasonal_adjustment_short": "NSA",
    "last_updated": "2021-08-02 13:25:03-05",
    "popularity": 1,
    "group_popularity": 1,
    "notes": "Copyright \u00a9 2016, International Monetary Fund. Reprinted with permission. Complete terms of use and contact details are available at http://www.imf.org/external/terms.htm."
  },
  "Morocco": {
    "id": "MARFCMTVGGDPPT",
    "realtime_start": "2022-03-23",
    "realtime_end": "2022-03-23",
    "title": "Use of Financial Services: Key Indicators, Value of Mobile Money Transactions During the Reference Year for Morocco",
    "observation_start": "2012-01-01",
    "observation_end": "2013-01-01",
    "frequency": "Annual",
    "frequency_short": "A",
    "units": "Percent of GDP",
    "units_short": "% of GDP",
    "seasonal_adjustment": "Not Seasonally Adjusted",
    "seasonal_adjustment_short": "NSA",
    "last_updated": "2016-09-01 08:43:27-05",
    "popularity": 1,
    "group_popularity": 1,
    "notes": "Copyright \u00a9 2016, International Monetary Fund. Reprinted with permission. Complete terms of use and contact details are available at http://www.imf.org/external/terms.htm."
  },
  "Mozambique": {
    "id": "MOZFCMTVGGDPPT",
    "realtime_start": "2022-03-23",
    "realtime_end": "2022-03-23",
    "title": "Use of Financial Services: Key Indicators, Value of Mobile Money Transactions During the Reference Year for Mozambique",
    "observation_start": "2014-01-01",
    "observation_end": "2020-01-01",
    "frequency": "Annual",
    "frequency_short": "A",
    "units": "Percent of GDP",
    "units_short": "% of GDP",
    "seasonal_adjustment": "Not Seasonally Adjusted",
    "seasonal_adjustment_short": "NSA",
    "last_updated": "2021-08-02 13:25:08-05",
    "popularity": 1,
    "group_popularity": 1,
    "notes": "Copyright \u00a9 2016, International Monetary Fund. Reprinted with permission. Complete terms of use and contact details are available at http://www.imf.org/external/terms.htm."
  },
  "Myanmar": {
    "id": "MMRFCMTVGGDPPT",
    "realtime_start": "2022-03-23",
    "realtime_end": "2022-03-23",
    "title": "Use of Financial Services: Key Indicators, Value of Mobile Money Transactions During the Reference Year for Myanmar",
    "observation_start": "2014-01-01",
    "observation_end": "2019-01-01",
    "frequency": "Annual",
    "frequency_short": "A",
    "units": "Percent of GDP",
    "units_short": "% of GDP",
    "seasonal_adjustment": "Not Seasonally Adjusted",
    "seasonal_adjustment_short": "NSA",
    "last_updated": "2021-08-02 13:25:26-05",
    "popularity": 1,
    "group_popularity": 1,
    "notes": "Copyright \u00a9 2016, International Monetary Fund. Reprinted with permission. Complete terms of use and contact details are available at http://www.imf.org/external/terms.htm."
  },
  "Namibia": {
    "id": "NAMFCMTVGGDPPT",
    "realtime_start": "2022-03-23",
    "realtime_end": "2022-03-23",
    "title": "Use of Financial Services: Key Indicators, Value of Mobile Money Transactions During the Reference Year for Namibia",
    "observation_start": "2010-01-01",
    "observation_end": "2019-01-01",
    "frequency": "Annual",
    "frequency_short": "A",
    "units": "Percent of GDP",
    "units_short": "% of GDP",
    "seasonal_adjustment": "Not Seasonally Adjusted",
    "seasonal_adjustment_short": "NSA",
    "last_updated": "2020-11-09 13:31:54-06",
    "popularity": 1,
    "group_popularity": 1,
    "notes": "Copyright \u00a9 2016, International Monetary Fund. Reprinted with permission. Complete terms of use and contact details are available at http://www.imf.org/external/terms.htm."
  },
  "Nigeria": {
    "id": "NGAFCMTVGGDPPT",
    "realtime_start": "2022-03-23",
    "realtime_end": "2022-03-23",
    "title": "Use of Financial Services: Key Indicators, Value of Mobile Money Transactions During the Reference Year for Nigeria",
    "observation_start": "2012-01-01",
    "observation_end": "2020-01-01",
    "frequency": "Annual",
    "frequency_short": "A",
    "units": "Percent of GDP",
    "units_short": "% of GDP",
    "seasonal_adjustment": "Not Seasonally Adjusted",
    "seasonal_adjustment_short": "NSA",
    "last_updated": "2021-09-01 10:05:28-05",
    "popularity": 1,
    "group_popularity": 1,
    "notes": "Copyright \u00a9 2016, International Monetary Fund. Reprinted with permission. Complete terms of use and contact details are available at http://www.imf.org/external/terms.htm."
  },
  "Pakistan": {
    "id": "PAKFCMTVGGDPPT",
    "realtime_start": "2022-03-23",
    "realtime_end": "2022-03-23",
    "title": "Use of Financial Services: Key Indicators, Value of Mobile Money Transactions During the Reference Year for Pakistan",
    "observation_start": "2011-01-01",
    "observation_end": "2020-01-01",
    "frequency": "Annual",
    "frequency_short": "A",
    "units": "Percent of GDP",
    "units_short": "% of GDP",
    "seasonal_adjustment": "Not Seasonally Adjusted",
    "seasonal_adjustment_short": "NSA",
    "last_updated": "2021-09-01 10:05:18-05",
    "popularity": 1,
    "group_popularity": 1,
    "notes": "Copyright \u00a9 2016, International Monetary Fund. Reprinted with permission. Complete terms of use and contact details are available at http://www.imf.org/external/terms.htm."
  },
  "Philippines": {
    "id": "PHLFCMTVGGDPPT",
    "realtime_start": "2022-03-23",
    "realtime_end": "2022-03-23",
    "title": "Use of Financial Services: Key Indicators, Value of Mobile Money Transactions During the Reference Year for Philippines",
    "observation_start": "2010-01-01",
    "observation_end": "2019-01-01",
    "frequency": "Annual",
    "frequency_short": "A",
    "units": "Percent of GDP",
    "units_short": "% of GDP",
    "seasonal_adjustment": "Not Seasonally Adjusted",
    "seasonal_adjustment_short": "NSA",
    "last_updated": "2021-08-02 13:24:15-05",
    "popularity": 1,
    "group_popularity": 1,
    "notes": "Copyright \u00a9 2016, International Monetary Fund. Reprinted with permission. Complete terms of use and contact details are available at http://www.imf.org/external/terms.htm."
  },
  "Qatar": {
    "id": "QATFCMTVGGDPPT",
    "realtime_start": "2022-03-23",
    "realtime_end": "2022-03-23",
    "title": "Use of Financial Services: Key Indicators, Value of Mobile Money Transactions During the Reference Year for Qatar",
    "observation_start": "2011-01-01",
    "observation_end": "2019-01-01",
    "frequency": "Annual",
    "frequency_short": "A",
    "units": "Percent of GDP",
    "units_short": "% of GDP",
    "seasonal_adjustment": "Not Seasonally Adjusted",
    "seasonal_adjustment_short": "NSA",
    "last_updated": "2021-08-02 13:23:57-05",
    "popularity": 1,
    "group_popularity": 1,
    "notes": "Copyright \u00a9 2016, International Monetary Fund. Reprinted with permission. Complete terms of use and contact details are available at http://www.imf.org/external/terms.htm."
  },
  "Rwanda": {
    "id": "RWAFCMTVGGDPPT",
    "realtime_start": "2022-03-23",
    "realtime_end": "2022-03-23",
    "title": "Use of Financial Services: Key Indicators, Value of Mobile Money Transactions During the Reference Year for Rwanda",
    "observation_start": "2011-01-01",
    "observation_end": "2020-01-01",
    "frequency": "Annual",
    "frequency_short": "A",
    "units": "Percent of GDP",
    "units_short": "% of GDP",
    "seasonal_adjustment": "Not Seasonally Adjusted",
    "seasonal_adjustment_short": "NSA",
    "last_updated": "2021-08-02 13:24:44-05",
    "popularity": 1,
    "group_popularity": 1,
    "notes": "Copyright \u00a9 2016, International Monetary Fund. Reprinted with permission. Complete terms of use and contact details are available at http://www.imf.org/external/terms.htm."
  },
  "Samoa": {
    "id": "WSMFCMTVGGDPPT",
    "realtime_start": "2022-03-23",
    "realtime_end": "2022-03-23",
    "title": "Use of Financial Services: Key Indicators, Value of Mobile Money Transactions During the Reference Year for Samoa",
    "observation_start": "2013-01-01",
    "observation_end": "2020-01-01",
    "frequency": "Annual",
    "frequency_short": "A",
    "units": "Percent of GDP",
    "units_short": "% of GDP",
    "seasonal_adjustment": "Not Seasonally Adjusted",
    "seasonal_adjustment_short": "NSA",
    "last_updated": "2021-09-01 10:04:03-05",
    "popularity": 1,
    "group_popularity": 1,
    "notes": "Copyright \u00a9 2016, International Monetary Fund. Reprinted with permission. Complete terms of use and contact details are available at http://www.imf.org/external/terms.htm."
  },
  "Solomon Islands": {
    "id": "SLBFCMTVGGDPPT",
    "realtime_start": "2022-03-23",
    "realtime_end": "2022-03-23",
    "title": "Use of Financial Services: Key Indicators, Value of Mobile Money Transactions During the Reference Year for Solomon Islands",
    "observation_start": "2013-01-01",
    "observation_end": "2020-01-01",
    "frequency": "Annual",
    "frequency_short": "A",
    "units": "Percent of GDP",
    "units_short": "% of GDP",
    "seasonal_adjustment": "Not Seasonally Adjusted",
    "seasonal_adjustment_short": "NSA",
    "last_updated": "2021-08-02 13:31:43-05",
    "popularity": 1,
    "group_popularity": 1,
    "notes": "Copyright \u00a9 2016, International Monetary Fund. Reprinted with permission. Complete terms of use and contact details are available at http://www.imf.org/external/terms.htm."
  },
  "Swaziland": {
    "id": "SWZFCMTVGGDPPT",
    "realtime_start": "2022-03-23",
    "realtime_end": "2022-03-23",
    "title": "Use of Financial Services: Key Indicators, Value of Mobile Money Transactions During the Reference Year for Swaziland",
    "observation_start": "2011-01-01",
    "observation_end": "2020-01-01",
    "frequency": "Annual",
    "frequency_short": "A",
    "units": "Percent of GDP",
    "units_short": "% of GDP",
    "seasonal_adjustment": "Not Seasonally Adjusted",
    "seasonal_adjustment_short": "NSA",
    "last_updated": "2021-10-07 09:35:03-05",
    "popularity": 1,
    "group_popularity": 1,
    "notes": "Copyright \u00a9 2016, International Monetary Fund. Reprinted with permission. Complete terms of use and contact details are available at http://www.imf.org/external/terms.htm."
  },
  "Tonga": {
    "id": "TONFCMTVGGDPPT",
    "realtime_start": "2022-03-23",
    "realtime_end": "2022-03-23",
    "title": "Use of Financial Services: Key Indicators, Value of Mobile Money Transactions During the Reference Year for Tonga",
    "observation_start": "2011-01-01",
    "observation_end": "2018-01-01",
    "frequency": "Annual",
    "frequency_short": "A",
    "units": "Percent of GDP",
    "units_short": "% of GDP",
    "seasonal_adjustment": "Not Seasonally Adjusted",
    "seasonal_adjustment_short": "NSA",
    "last_updated": "2021-09-01 10:06:22-05",
    "popularity": 1,
    "group_popularity": 1,
    "notes": "Copyright \u00a9 2016, International Monetary Fund. Reprinted with permission. Complete terms of use and contact details are available at http://www.imf.org/external/terms.htm."
  },
  "Uganda": {
    "id": "UGAFCMTVGGDPPT",
    "realtime_start": "2022-03-23",
    "realtime_end": "2022-03-23",
    "title": "Use of Financial Services: Key Indicators, Value of Mobile Money Transactions During the Reference Year for Uganda",
    "observation_start": "2009-01-01",
    "observation_end": "2020-01-01",
    "frequency": "Annual",
    "frequency_short": "A",
    "units": "Percent of GDP",
    "units_short": "% of GDP",
    "seasonal_adjustment": "Not Seasonally Adjusted",
    "seasonal_adjustment_short": "NSA",
    "last_updated": "2021-09-01 10:04:23-05",
    "popularity": 1,
    "group_popularity": 1,
    "notes": "Copyright \u00a9 2016, International Monetary Fund. Reprinted with permission. Complete terms of use and contact details are available at http://www.imf.org/external/terms.htm."
  },
  "Zambia": {
    "id": "ZMBFCMTVGGDPPT",
    "realtime_start": "2022-03-23",
    "realtime_end": "2022-03-23",
    "title": "Use of Financial Services: Key Indicators, Value of Mobile Money Transactions During the Reference Year for Zambia",
    "observation_start": "2011-01-01",
    "observation_end": "2020-01-01",
    "frequency": "Annual",
    "frequency_short": "A",
    "units": "Percent of GDP",
    "units_short": "% of GDP",
    "seasonal_adjustment": "Not Seasonally Adjusted",
    "seasonal_adjustment_short": "NSA",
    "last_updated": "2021-08-02 13:21:25-05",
    "popularity": 1,
    "group_popularity": 1,
    "notes": "Copyright \u00a9 2016, International Monetary Fund. Reprinted with permission. Complete terms of use and contact details are available at http://www.imf.org/external/terms.htm."
  }
}