{
  "EVZCLS": {
    "id": "EVZCLS",
    "realtime_start": "2022-04-06",
    "realtime_end": "2022-04-06",
    "title": "CBOE EuroCurrency ETF Volatility Index",
    "observation_start": "2007-11-01",
    "observation_end": "2022-04-04",
    "frequency": "Daily, Close",
    "frequency_short": "D",
    "units": "Index",
    "units_short": "Index",
    "seasonal_adjustment": "Not Seasonally Adjusted",
    "seasonal_adjustment_short": "NSA",
    "last_updated": "2022-04-05 08:37:02-05",
    "popularity": 26,
    "group_popularity": 26,
    "notes": "Exchange Traded Funds (ETFs) are shares of trusts that hold portfolios of stocks designed to closely track the price performance and yield of specific indices. Copyright, 2016, Chicago Board Options Exchange, Inc. Reprinted with permission.",
    "path": "../Database/Money, Banking, & Finance/Financial Indicators/Volatility Indexes"
  },
  "GVZCLS": {
    "id": "GVZCLS",
    "realtime_start": "2022-04-06",
    "realtime_end": "2022-04-06",
    "title": "CBOE Gold ETF Volatility Index",
    "observation_start": "2008-06-03",
    "observation_end": "2022-04-04",
    "frequency": "Daily, Close",
    "frequency_short": "D",
    "units": "Index",
    "units_short": "Index",
    "seasonal_adjustment": "Not Seasonally Adjusted",
    "seasonal_adjustment_short": "NSA",
    "last_updated": "2022-04-05 08:36:03-05",
    "popularity": 56,
    "group_popularity": 56,
    "notes": "Exchange Traded Funds (ETFs) are shares of trusts that hold portfolios of stocks designed to closely track the price performance and yield of specific indices. Copyright, 2016, Chicago Board Options Exchange, Inc. Reprinted with permission.",
    "path": "../Database/Money, Banking, & Finance/Financial Indicators/Volatility Indexes"
  },
  "OVXCLS": {
    "id": "OVXCLS",
    "realtime_start": "2022-04-06",
    "realtime_end": "2022-04-06",
    "title": "CBOE Crude Oil ETF Volatility Index",
    "observation_start": "2007-05-10",
    "observation_end": "2022-04-04",
    "frequency": "Daily, Close",
    "frequency_short": "D",
    "units": "Index",
    "units_short": "Index",
    "seasonal_adjustment": "Not Seasonally Adjusted",
    "seasonal_adjustment_short": "NSA",
    "last_updated": "2022-04-05 08:36:04-05",
    "popularity": 46,
    "group_popularity": 46,
    "notes": "Exchange Traded Funds (ETFs) are shares of trusts that hold portfolios of stocks designed to closely track the price performance and yield of specific indices. Copyright, 2016, Chicago Board Options Exchange, Inc. Reprinted with permission.",
    "path": "../Database/Money, Banking, & Finance/Financial Indicators/Volatility Indexes"
  },
  "RVXCLS": {
    "id": "RVXCLS",
    "realtime_start": "2022-04-06",
    "realtime_end": "2022-04-06",
    "title": "CBOE Russell 2000 Volatility Index",
    "observation_start": "2004-01-02",
    "observation_end": "2022-04-04",
    "frequency": "Daily, Close",
    "frequency_short": "D",
    "units": "Index",
    "units_short": "Index",
    "seasonal_adjustment": "Not Seasonally Adjusted",
    "seasonal_adjustment_short": "NSA",
    "last_updated": "2022-04-05 08:36:05-05",
    "popularity": 34,
    "group_popularity": 34,
    "notes": "Copyright, 2016, Chicago Board Options Exchange, Inc. Reprinted with permission.",
    "path": "../Database/Money, Banking, & Finance/Financial Indicators/Volatility Indexes"
  },
  "VIXCLS": {
    "id": "VIXCLS",
    "realtime_start": "2022-04-06",
    "realtime_end": "2022-04-06",
    "title": "CBOE Volatility Index: VIX",
    "observation_start": "1990-01-02",
    "observation_end": "2022-04-04",
    "frequency": "Daily, Close",
    "frequency_short": "D",
    "units": "Index",
    "units_short": "Index",
    "seasonal_adjustment": "Not Seasonally Adjusted",
    "seasonal_adjustment_short": "NSA",
    "last_updated": "2022-04-05 08:36:01-05",
    "popularity": 75,
    "group_popularity": 75,
    "notes": "VIX measures market expectation of near term volatility conveyed by stock index option prices. Copyright, 2016, Chicago Board Options Exchange, Inc. Reprinted with permission.",
    "path": "../Database/Money, Banking, & Finance/Financial Indicators/Volatility Indexes"
  },
  "VXAPLCLS": {
    "id": "VXAPLCLS",
    "realtime_start": "2022-04-06",
    "realtime_end": "2022-04-06",
    "title": "CBOE Equity VIX on Apple",
    "observation_start": "2010-06-01",
    "observation_end": "2022-04-04",
    "frequency": "Daily, Close",
    "frequency_short": "D",
    "units": "Index",
    "units_short": "Index",
    "seasonal_adjustment": "Not Seasonally Adjusted",
    "seasonal_adjustment_short": "NSA",
    "last_updated": "2022-04-05 08:36:06-05",
    "popularity": 20,
    "group_popularity": 20,
    "notes": "Copyright, 2016, Chicago Board Options Exchange, Inc. Reprinted with permission.",
    "path": "../Database/Money, Banking, & Finance/Financial Indicators/Volatility Indexes"
  },
  "VXAZNCLS": {
    "id": "VXAZNCLS",
    "realtime_start": "2022-04-06",
    "realtime_end": "2022-04-06",
    "title": "CBOE Equity VIX on Amazon",
    "observation_start": "2010-06-01",
    "observation_end": "2022-04-04",
    "frequency": "Daily, Close",
    "frequency_short": "D",
    "units": "Index",
    "units_short": "Index",
    "seasonal_adjustment": "Not Seasonally Adjusted",
    "seasonal_adjustment_short": "NSA",
    "last_updated": "2022-04-05 08:36:07-05",
    "popularity": 22,
    "group_popularity": 22,
    "notes": "Copyright, 2016, Chicago Board Options Exchange, Inc. Reprinted with permission.",
    "path": "../Database/Money, Banking, & Finance/Financial Indicators/Volatility Indexes"
  },
  "VXDCLS": {
    "id": "VXDCLS",
    "realtime_start": "2022-04-06",
    "realtime_end": "2022-04-06",
    "title": "CBOE DJIA Volatility Index",
    "observation_start": "1997-10-07",
    "observation_end": "2022-04-04",
    "frequency": "Daily, Close",
    "frequency_short": "D",
    "units": "Index",
    "units_short": "Index",
    "seasonal_adjustment": "Not Seasonally Adjusted",
    "seasonal_adjustment_short": "NSA",
    "last_updated": "2022-04-05 08:36:06-05",
    "popularity": 29,
    "group_popularity": 29,
    "notes": "Copyright, 2016, Chicago Board Options Exchange, Inc. Reprinted with permission.",
    "path": "../Database/Money, Banking, & Finance/Financial Indicators/Volatility Indexes"
  },
  "VXEEMCLS": {
    "id": "VXEEMCLS",
    "realtime_start": "2022-04-06",
    "realtime_end": "2022-04-06",
    "title": "CBOE Emerging Markets ETF Volatility Index",
    "observation_start": "2011-03-16",
    "observation_end": "2022-04-04",
    "frequency": "Daily, Close",
    "frequency_short": "D",
    "units": "Index",
    "units_short": "Index",
    "seasonal_adjustment": "Not Seasonally Adjusted",
    "seasonal_adjustment_short": "NSA",
    "last_updated": "2022-04-05 08:36:05-05",
    "popularity": 32,
    "group_popularity": 32,
    "notes": "Exchange Traded Funds (ETFs) are shares of trusts that hold portfolios of stocks designed to closely track the price performance and yield of specific indices. Copyright, 2016, Chicago Board Options Exchange, Inc. Reprinted with permission.",
    "path": "../Database/Money, Banking, & Finance/Financial Indicators/Volatility Indexes"
  },
  "VXEWZCLS": {
    "id": "VXEWZCLS",
    "realtime_start": "2022-04-06",
    "realtime_end": "2022-04-06",
    "title": "CBOE Brazil ETF Volatility Index",
    "observation_start": "2011-03-16",
    "observation_end": "2022-04-04",
    "frequency": "Daily, Close",
    "frequency_short": "D",
    "units": "Index",
    "units_short": "Index",
    "seasonal_adjustment": "Not Seasonally Adjusted",
    "seasonal_adjustment_short": "NSA",
    "last_updated": "2022-04-05 08:36:07-05",
    "popularity": 20,
    "group_popularity": 20,
    "notes": "Exchange Traded Funds (ETFs) are shares of trusts that hold portfolios of stocks designed to closely track the price performance and yield of specific indices. Copyright, 2016, Chicago Board Options Exchange, Inc. Reprinted with permission.",
    "path": "../Database/Money, Banking, & Finance/Financial Indicators/Volatility Indexes"
  },
  "VXFXICLS": {
    "id": "VXFXICLS",
    "realtime_start": "2022-04-06",
    "realtime_end": "2022-04-06",
    "title": "CBOE China ETF Volatility Index (DISCONTINUED)",
    "observation_start": "2011-03-16",
    "observation_end": "2022-02-11",
    "frequency": "Daily, Close",
    "frequency_short": "D",
    "units": "Index",
    "units_short": "Index",
    "seasonal_adjustment": "Not Seasonally Adjusted",
    "seasonal_adjustment_short": "NSA",
    "last_updated": "2022-02-14 08:36:09-06",
    "popularity": 42,
    "group_popularity": 42,
    "notes": "Exchange Traded Funds (ETFs) are shares of trusts that hold portfolios of stocks designed to closely track the price performance and yield of specific indices. Copyright, 2016, Chicago Board Options Exchange, Inc. Reprinted with permission.",
    "path": "../Database/Money, Banking, & Finance/Financial Indicators/Volatility Indexes"
  },
  "VXGDXCLS": {
    "id": "VXGDXCLS",
    "realtime_start": "2022-04-06",
    "realtime_end": "2022-04-06",
    "title": "CBOE Gold Miners ETF Volatility Index (DISCONTINUED)",
    "observation_start": "2011-03-16",
    "observation_end": "2022-02-11",
    "frequency": "Daily, Close",
    "frequency_short": "D",
    "units": "Index",
    "units_short": "Index",
    "seasonal_adjustment": "Not Seasonally Adjusted",
    "seasonal_adjustment_short": "NSA",
    "last_updated": "2022-02-14 08:36:09-06",
    "popularity": 14,
    "group_popularity": 14,
    "notes": "Exchange Traded Funds (ETFs) are shares of trusts that hold portfolios of stocks designed to closely track the price performance and yield of specific indices. Copyright, 2016, Chicago Board Options Exchange, Inc. Reprinted with permission.",
    "path": "../Database/Money, Banking, & Finance/Financial Indicators/Volatility Indexes"
  },
  "VXGOGCLS": {
    "id": "VXGOGCLS",
    "realtime_start": "2022-04-06",
    "realtime_end": "2022-04-06",
    "title": "CBOE Equity VIX on Google",
    "observation_start": "2010-06-01",
    "observation_end": "2022-04-04",
    "frequency": "Daily, Close",
    "frequency_short": "D",
    "units": "Index",
    "units_short": "Index",
    "seasonal_adjustment": "Not Seasonally Adjusted",
    "seasonal_adjustment_short": "NSA",
    "last_updated": "2022-04-05 08:36:07-05",
    "popularity": 16,
    "group_popularity": 16,
    "notes": "Copyright, 2016, Chicago Board Options Exchange, Inc. Reprinted with permission.",
    "path": "../Database/Money, Banking, & Finance/Financial Indicators/Volatility Indexes"
  },
  "VXGSCLS": {
    "id": "VXGSCLS",
    "realtime_start": "2022-04-06",
    "realtime_end": "2022-04-06",
    "title": "CBOE Equity VIX on Goldman Sachs",
    "observation_start": "2010-06-01",
    "observation_end": "2022-04-04",
    "frequency": "Daily, Close",
    "frequency_short": "D",
    "units": "Index",
    "units_short": "Index",
    "seasonal_adjustment": "Not Seasonally Adjusted",
    "seasonal_adjustment_short": "NSA",
    "last_updated": "2022-04-05 08:36:08-05",
    "popularity": 10,
    "group_popularity": 10,
    "notes": "Copyright, 2016, Chicago Board Options Exchange, Inc. Reprinted with permission.",
    "path": "../Database/Money, Banking, & Finance/Financial Indicators/Volatility Indexes"
  },
  "VXIBMCLS": {
    "id": "VXIBMCLS",
    "realtime_start": "2022-04-06",
    "realtime_end": "2022-04-06",
    "title": "CBOE Equity VIX on IBM",
    "observation_start": "2010-06-01",
    "observation_end": "2022-04-04",
    "frequency": "Daily, Close",
    "frequency_short": "D",
    "units": "Index",
    "units_short": "Index",
    "seasonal_adjustment": "Not Seasonally Adjusted",
    "seasonal_adjustment_short": "NSA",
    "last_updated": "2022-04-05 08:36:08-05",
    "popularity": 10,
    "group_popularity": 10,
    "notes": "Copyright, 2016, Chicago Board Options Exchange, Inc. Reprinted with permission.",
    "path": "../Database/Money, Banking, & Finance/Financial Indicators/Volatility Indexes"
  },
  "VXNCLS": {
    "id": "VXNCLS",
    "realtime_start": "2022-04-06",
    "realtime_end": "2022-04-06",
    "title": "CBOE NASDAQ 100 Volatility Index",
    "observation_start": "2001-02-02",
    "observation_end": "2022-04-04",
    "frequency": "Daily, Close",
    "frequency_short": "D",
    "units": "Index",
    "units_short": "Index",
    "seasonal_adjustment": "Not Seasonally Adjusted",
    "seasonal_adjustment_short": "NSA",
    "last_updated": "2022-04-05 08:36:04-05",
    "popularity": 34,
    "group_popularity": 34,
    "notes": "Copyright, 2016, Chicago Board Options Exchange, Inc. Reprinted with permission.",
    "path": "../Database/Money, Banking, & Finance/Financial Indicators/Volatility Indexes"
  },
  "VXOCLS": {
    "id": "VXOCLS",
    "realtime_start": "2022-04-06",
    "realtime_end": "2022-04-06",
    "title": "CBOE S&P 100 Volatility Index: VXO (DISCONTINUED)",
    "observation_start": "1986-01-02",
    "observation_end": "2021-09-23",
    "frequency": "Daily, Close",
    "frequency_short": "D",
    "units": "Index",
    "units_short": "Index",
    "seasonal_adjustment": "Not Seasonally Adjusted",
    "seasonal_adjustment_short": "NSA",
    "last_updated": "2021-09-24 08:36:03-05",
    "popularity": 41,
    "group_popularity": 41,
    "notes": "This series is no longer being updated by the source. More information regarding the changes may be found on both  the initial</> and <a href=\"https://cdn.cboe.com/resources/release_notes/2021/VXO-and-VXHYG-Indices-Consultation-Notice-Final-_v3.pdf\"> the final  (https://cdn.cboe.com/resources/release_notes/2021/VXO-and-VXHYG-Indices-Consultation-Summary.pdf) announcement pages.",
    "path": "../Database/Money, Banking, & Finance/Financial Indicators/Volatility Indexes"
  },
  "VXSLVCLS": {
    "id": "VXSLVCLS",
    "realtime_start": "2022-04-06",
    "realtime_end": "2022-04-06",
    "title": "CBOE Silver ETF Volatility Index (DISCONTINUED)",
    "observation_start": "2011-03-16",
    "observation_end": "2022-02-11",
    "frequency": "Daily, Close",
    "frequency_short": "D",
    "units": "Index",
    "units_short": "Index",
    "seasonal_adjustment": "Not Seasonally Adjusted",
    "seasonal_adjustment_short": "NSA",
    "last_updated": "2022-02-14 08:36:12-06",
    "popularity": 23,
    "group_popularity": 23,
    "notes": "Exchange Traded Funds (ETFs) are shares of trusts that hold portfolios of stocks designed to closely track the price performance and yield of specific indices. Copyright, 2016, Chicago Board Options Exchange, Inc. Reprinted with permission.",
    "path": "../Database/Money, Banking, & Finance/Financial Indicators/Volatility Indexes"
  },
  "VXTYN": {
    "id": "VXTYN",
    "realtime_start": "2022-04-06",
    "realtime_end": "2022-04-06",
    "title": "CBOE 10-Year Treasury Note Volatility Futures (DISCONTINUED)",
    "observation_start": "2003-01-02",
    "observation_end": "2020-05-15",
    "frequency": "Daily, Close",
    "frequency_short": "D",
    "units": "Index",
    "units_short": "Index",
    "seasonal_adjustment": "Not Seasonally Adjusted",
    "seasonal_adjustment_short": "NSA",
    "last_updated": "2020-06-17 09:20:48-05",
    "popularity": 40,
    "group_popularity": 40,
    "notes": "Copyright, 2016, Chicago Board Options Exchange, Inc. Reprinted with permission.",
    "path": "../Database/Money, Banking, & Finance/Financial Indicators/Volatility Indexes"
  },
  "VXVCLS": {
    "id": "VXVCLS",
    "realtime_start": "2022-04-06",
    "realtime_end": "2022-04-06",
    "title": "CBOE S&P 500 3-Month Volatility Index",
    "observation_start": "2007-12-04",
    "observation_end": "2022-04-04",
    "frequency": "Daily, Close",
    "frequency_short": "D",
    "units": "Index",
    "units_short": "Index",
    "seasonal_adjustment": "Not Seasonally Adjusted",
    "seasonal_adjustment_short": "NSA",
    "last_updated": "2022-04-05 08:36:03-05",
    "popularity": 50,
    "group_popularity": 50,
    "notes": "Copyright, 2016, Chicago Board Options Exchange, Inc. Reprinted with permission.",
    "path": "../Database/Money, Banking, & Finance/Financial Indicators/Volatility Indexes"
  },
  "VXXLECLS": {
    "id": "VXXLECLS",
    "realtime_start": "2022-04-06",
    "realtime_end": "2022-04-06",
    "title": "CBOE Energy Sector ETF Volatility Index (DISCONTINUED)",
    "observation_start": "2011-03-16",
    "observation_end": "2022-02-11",
    "frequency": "Daily, Close",
    "frequency_short": "D",
    "units": "Index",
    "units_short": "Index",
    "seasonal_adjustment": "Not Seasonally Adjusted",
    "seasonal_adjustment_short": "NSA",
    "last_updated": "2022-02-14 08:36:13-06",
    "popularity": 24,
    "group_popularity": 24,
    "notes": "Exchange Traded Funds (ETFs) are shares of trusts that hold portfolios of stocks designed to closely track the price performance and yield of specific indices. Copyright, 2016, Chicago Board Options Exchange, Inc. Reprinted with permission.",
    "path": "../Database/Money, Banking, & Finance/Financial Indicators/Volatility Indexes"
  }
}