{
  "id": "MPU5250192",
  "realtime_start": "2022-04-06",
  "realtime_end": "2022-04-06",
  "title": "Computer and Electronic Products: Contribution of Research and Development (R&D) Intensity",
  "observation_start": "1987-01-01",
  "observation_end": "2020-01-01",
  "frequency": "Annual",
  "frequency_short": "A",
  "units": "Index 2012=100",
  "units_short": "Index 2012=100",
  "seasonal_adjustment": "Not Seasonally Adjusted",
  "seasonal_adjustment_short": "NSA",
  "last_updated": "2022-03-25 12:24:36-05",
  "popularity": 1,
  "group_popularity": 1,
  "notes": "The portion of labor productivity change attributed to research and development. \n\n For more information, please go to https://www.bls.gov/mfp/\n\n Source Indicator: MPU5250192"
}