{
  "id": "T3MFFM",
  "realtime_start": "2022-04-05",
  "realtime_end": "2022-04-05",
  "title": "3-Month Treasury Constant Maturity Minus Federal Funds Rate",
  "observation_start": "1982-01-01",
  "observation_end": "2022-03-01",
  "frequency": "Monthly",
  "frequency_short": "M",
  "units": "Percent",
  "units_short": "%",
  "seasonal_adjustment": "Not Seasonally Adjusted",
  "seasonal_adjustment_short": "NSA",
  "last_updated": "2022-04-01 16:01:16-05",
  "popularity": 10,
  "group_popularity": 40,
  "notes": "Series is calculated as the spread between 3-Month Treasury Constant Maturity (BC_3MONTHM) and Effective Federal Funds Rate (https://fred.stlouisfed.org/series/EFFR).\nStarting with the update on June 21, 2019, the Treasury bond data used in calculating interest rate spreads is obtained directly from the U.S. Treasury Department (https://www.treasury.gov/resource-center/data-chart-center/interest-rates/Pages/TextView.aspx?data=yield)."
}