{
  "A006RE1A156NBEA": {
    "id": "A006RE1A156NBEA",
    "realtime_start": "2022-04-05",
    "realtime_end": "2022-04-05",
    "title": "Shares of gross domestic product: Gross private domestic investment",
    "observation_start": "1929-01-01",
    "observation_end": "2021-01-01",
    "frequency": "Annual",
    "frequency_short": "A",
    "units": "Percent",
    "units_short": "%",
    "seasonal_adjustment": "Not Seasonally Adjusted",
    "seasonal_adjustment_short": "NSA",
    "last_updated": "2022-01-27 07:53:20-06",
    "popularity": 12,
    "group_popularity": 51,
    "notes": "BEA Account Code: A006RE\n\nFor more information about this series, please see http://www.bea.gov/national/.",
    "path": "../Database/National Accounts/National Income & Product Accounts/GDP - GNP/Shares of GDP"
  },
  "A006RE1Q156NBEA": {
    "id": "A006RE1Q156NBEA",
    "realtime_start": "2022-04-05",
    "realtime_end": "2022-04-05",
    "title": "Shares of gross domestic product: Gross private domestic investment",
    "observation_start": "1947-01-01",
    "observation_end": "2021-10-01",
    "frequency": "Quarterly",
    "frequency_short": "Q",
    "units": "Percent",
    "units_short": "%",
    "seasonal_adjustment": "Not Seasonally Adjusted",
    "seasonal_adjustment_short": "NSA",
    "last_updated": "2022-03-30 07:57:03-05",
    "popularity": 50,
    "group_popularity": 51,
    "notes": "BEA Account Code: A006RE\n\nFor more information about this series, please see http://www.bea.gov/national/.",
    "path": "../Database/National Accounts/National Income & Product Accounts/GDP - GNP/Shares of GDP"
  },
  "A007RE1A156NBEA": {
    "id": "A007RE1A156NBEA",
    "realtime_start": "2022-04-05",
    "realtime_end": "2022-04-05",
    "title": "Shares of gross domestic product: Gross private domestic investment: Fixed investment",
    "observation_start": "1929-01-01",
    "observation_end": "2021-01-01",
    "frequency": "Annual",
    "frequency_short": "A",
    "units": "Percent",
    "units_short": "%",
    "seasonal_adjustment": "Not Seasonally Adjusted",
    "seasonal_adjustment_short": "NSA",
    "last_updated": "2022-01-27 08:01:13-06",
    "popularity": 2,
    "group_popularity": 3,
    "notes": "BEA Account Code: A007RE\n\nFor more information about this series, please see http://www.bea.gov/national/.",
    "path": "../Database/National Accounts/National Income & Product Accounts/GDP - GNP/Shares of GDP"
  },
  "A007RE1Q156NBEA": {
    "id": "A007RE1Q156NBEA",
    "realtime_start": "2022-04-05",
    "realtime_end": "2022-04-05",
    "title": "Shares of gross domestic product: Gross private domestic investment: Fixed investment",
    "observation_start": "1947-01-01",
    "observation_end": "2021-10-01",
    "frequency": "Quarterly",
    "frequency_short": "Q",
    "units": "Percent",
    "units_short": "%",
    "seasonal_adjustment": "Not Seasonally Adjusted",
    "seasonal_adjustment_short": "NSA",
    "last_updated": "2022-02-24 07:58:18-06",
    "popularity": 3,
    "group_popularity": 3,
    "notes": "BEA Account Code: A007RE\n\nFor more information about this series, please see http://www.bea.gov/national/.",
    "path": "../Database/National Accounts/National Income & Product Accounts/GDP - GNP/Shares of GDP"
  },
  "A008RE1A156NBEA": {
    "id": "A008RE1A156NBEA",
    "realtime_start": "2022-04-05",
    "realtime_end": "2022-04-05",
    "title": "Shares of gross domestic product: Gross private domestic investment: Fixed investment: Nonresidential",
    "observation_start": "1929-01-01",
    "observation_end": "2021-01-01",
    "frequency": "Annual",
    "frequency_short": "A",
    "units": "Percent",
    "units_short": "%",
    "seasonal_adjustment": "Not Seasonally Adjusted",
    "seasonal_adjustment_short": "NSA",
    "last_updated": "2022-01-27 08:01:12-06",
    "popularity": 2,
    "group_popularity": 12,
    "notes": "BEA Account Code: A008RE\n\nFor more information about this series, please see http://www.bea.gov/national/.",
    "path": "../Database/National Accounts/National Income & Product Accounts/GDP - GNP/Shares of GDP"
  },
  "A008RE1Q156NBEA": {
    "id": "A008RE1Q156NBEA",
    "realtime_start": "2022-04-05",
    "realtime_end": "2022-04-05",
    "title": "Shares of gross domestic product: Gross private domestic investment: Fixed investment: Nonresidential",
    "observation_start": "1947-01-01",
    "observation_end": "2021-10-01",
    "frequency": "Quarterly",
    "frequency_short": "Q",
    "units": "Percent",
    "units_short": "%",
    "seasonal_adjustment": "Not Seasonally Adjusted",
    "seasonal_adjustment_short": "NSA",
    "last_updated": "2022-01-27 07:54:20-06",
    "popularity": 11,
    "group_popularity": 12,
    "notes": "BEA Account Code: A008RE\n\nFor more information about this series, please see http://www.bea.gov/national/.",
    "path": "../Database/National Accounts/National Income & Product Accounts/GDP - GNP/Shares of GDP"
  },
  "A011RE1A156NBEA": {
    "id": "A011RE1A156NBEA",
    "realtime_start": "2022-04-05",
    "realtime_end": "2022-04-05",
    "title": "Shares of gross domestic product: Gross private domestic investment: Fixed investment: Residential",
    "observation_start": "1929-01-01",
    "observation_end": "2021-01-01",
    "frequency": "Annual",
    "frequency_short": "A",
    "units": "Percent",
    "units_short": "%",
    "seasonal_adjustment": "Not Seasonally Adjusted",
    "seasonal_adjustment_short": "NSA",
    "last_updated": "2022-01-27 08:01:11-06",
    "popularity": 2,
    "group_popularity": 28,
    "notes": "BEA Account Code: A011RE\n\nFor more information about this series, please see http://www.bea.gov/national/.",
    "path": "../Database/National Accounts/National Income & Product Accounts/GDP - GNP/Shares of GDP"
  },
  "A011RE1Q156NBEA": {
    "id": "A011RE1Q156NBEA",
    "realtime_start": "2022-04-05",
    "realtime_end": "2022-04-05",
    "title": "Shares of gross domestic product: Gross private domestic investment: Fixed investment: Residential",
    "observation_start": "1947-01-01",
    "observation_end": "2021-10-01",
    "frequency": "Quarterly",
    "frequency_short": "Q",
    "units": "Percent",
    "units_short": "%",
    "seasonal_adjustment": "Not Seasonally Adjusted",
    "seasonal_adjustment_short": "NSA",
    "last_updated": "2022-02-24 07:57:22-06",
    "popularity": 28,
    "group_popularity": 28,
    "notes": "BEA Account Code: A011RE\n\nFor more information about this series, please see http://www.bea.gov/national/.",
    "path": "../Database/National Accounts/National Income & Product Accounts/GDP - GNP/Shares of GDP"
  },
  "A014RE1A156NBEA": {
    "id": "A014RE1A156NBEA",
    "realtime_start": "2022-04-05",
    "realtime_end": "2022-04-05",
    "title": "Shares of gross domestic product: Gross private domestic investment: Change in private inventories",
    "observation_start": "1929-01-01",
    "observation_end": "2021-01-01",
    "frequency": "Annual",
    "frequency_short": "A",
    "units": "Percent",
    "units_short": "%",
    "seasonal_adjustment": "Not Seasonally Adjusted",
    "seasonal_adjustment_short": "NSA",
    "last_updated": "2022-01-27 08:01:07-06",
    "popularity": 2,
    "group_popularity": 4,
    "notes": "BEA Account Code: A014RE\n\nFor more information about this series, please see http://www.bea.gov/national/.",
    "path": "../Database/National Accounts/National Income & Product Accounts/GDP - GNP/Shares of GDP"
  },
  "A014RE1Q156NBEA": {
    "id": "A014RE1Q156NBEA",
    "realtime_start": "2022-04-05",
    "realtime_end": "2022-04-05",
    "title": "Shares of gross domestic product: Gross private domestic investment: Change in private inventories",
    "observation_start": "1947-01-01",
    "observation_end": "2021-10-01",
    "frequency": "Quarterly",
    "frequency_short": "Q",
    "units": "Percent",
    "units_short": "%",
    "seasonal_adjustment": "Not Seasonally Adjusted",
    "seasonal_adjustment_short": "NSA",
    "last_updated": "2022-03-30 07:57:17-05",
    "popularity": 3,
    "group_popularity": 4,
    "notes": "BEA Account Code: A014RE\n\nFor more information about this series, please see http://www.bea.gov/national/.",
    "path": "../Database/National Accounts/National Income & Product Accounts/GDP - GNP/Shares of GDP"
  },
  "A019RE1A156NBEA": {
    "id": "A019RE1A156NBEA",
    "realtime_start": "2022-04-05",
    "realtime_end": "2022-04-05",
    "title": "Shares of gross domestic product: Net exports of goods and services",
    "observation_start": "1929-01-01",
    "observation_end": "2021-01-01",
    "frequency": "Annual",
    "frequency_short": "A",
    "units": "Percent",
    "units_short": "%",
    "seasonal_adjustment": "Not Seasonally Adjusted",
    "seasonal_adjustment_short": "NSA",
    "last_updated": "2022-01-27 07:53:10-06",
    "popularity": 32,
    "group_popularity": 45,
    "notes": "BEA Account Code: A019RE\n\nFor more information about this series, please see http://www.bea.gov/national/.",
    "path": "../Database/National Accounts/National Income & Product Accounts/GDP - GNP/Shares of GDP"
  },
  "A019RE1Q156NBEA": {
    "id": "A019RE1Q156NBEA",
    "realtime_start": "2022-04-05",
    "realtime_end": "2022-04-05",
    "title": "Shares of gross domestic product: Net exports of goods and services",
    "observation_start": "1947-01-01",
    "observation_end": "2021-10-01",
    "frequency": "Quarterly",
    "frequency_short": "Q",
    "units": "Percent",
    "units_short": "%",
    "seasonal_adjustment": "Not Seasonally Adjusted",
    "seasonal_adjustment_short": "NSA",
    "last_updated": "2022-01-27 07:54:16-06",
    "popularity": 35,
    "group_popularity": 45,
    "notes": "BEA Account Code: A019RE\n\nFor more information about this series, please see http://www.bea.gov/national/.",
    "path": "../Database/National Accounts/National Income & Product Accounts/GDP - GNP/Shares of GDP"
  },
  "A024RE1A156NBEA": {
    "id": "A024RE1A156NBEA",
    "realtime_start": "2022-04-05",
    "realtime_end": "2022-04-05",
    "title": "Shares of gross domestic income: Consumption of fixed capital: Private",
    "observation_start": "1929-01-01",
    "observation_end": "2020-01-01",
    "frequency": "Annual",
    "frequency_short": "A",
    "units": "Percent",
    "units_short": "%",
    "seasonal_adjustment": "Not Seasonally Adjusted",
    "seasonal_adjustment_short": "NSA",
    "last_updated": "2021-08-06 14:34:36-05",
    "popularity": 3,
    "group_popularity": 3,
    "notes": "BEA Account Code: A024RE\n\nFor more information about this series, please see http://www.bea.gov/national/.",
    "path": "../Database/National Accounts/National Income & Product Accounts/GDP - GNP/Shares of GDP"
  },
  "A038RE1A156NBEA": {
    "id": "A038RE1A156NBEA",
    "realtime_start": "2022-04-05",
    "realtime_end": "2022-04-05",
    "title": "Shares of gross domestic income: Compensation of employees, paid: Supplements to wages and salaries",
    "observation_start": "1929-01-01",
    "observation_end": "2020-01-01",
    "frequency": "Annual",
    "frequency_short": "A",
    "units": "Percent",
    "units_short": "%",
    "seasonal_adjustment": "Not Seasonally Adjusted",
    "seasonal_adjustment_short": "NSA",
    "last_updated": "2021-08-06 14:34:23-05",
    "popularity": 3,
    "group_popularity": 3,
    "notes": "BEA Account Code: A038RE\n\nFor more information about this series, please see http://www.bea.gov/national/.",
    "path": "../Database/National Accounts/National Income & Product Accounts/GDP - GNP/Shares of GDP"
  },
  "A041RE1A156NBEA": {
    "id": "A041RE1A156NBEA",
    "realtime_start": "2022-04-05",
    "realtime_end": "2022-04-05",
    "title": "Shares of gross domestic income: Net operating surplus: Private enterprises: Proprietors' income with inventory valuation and capital consumption adjustments",
    "observation_start": "1929-01-01",
    "observation_end": "2020-01-01",
    "frequency": "Annual",
    "frequency_short": "A",
    "units": "Percent",
    "units_short": "%",
    "seasonal_adjustment": "Not Seasonally Adjusted",
    "seasonal_adjustment_short": "NSA",
    "last_updated": "2021-08-06 14:34:35-05",
    "popularity": 2,
    "group_popularity": 2,
    "notes": "BEA Account Code: A041RE\n\nFor more information about this series, please see http://www.bea.gov/national/.",
    "path": "../Database/National Accounts/National Income & Product Accounts/GDP - GNP/Shares of GDP"
  },
  "A048RE1A156NBEA": {
    "id": "A048RE1A156NBEA",
    "realtime_start": "2022-04-05",
    "realtime_end": "2022-04-05",
    "title": "Shares of gross domestic income: Net operating surplus: Private enterprises: Rental income of persons with capital consumption adjustment",
    "observation_start": "1929-01-01",
    "observation_end": "2020-01-01",
    "frequency": "Annual",
    "frequency_short": "A",
    "units": "Percent",
    "units_short": "%",
    "seasonal_adjustment": "Not Seasonally Adjusted",
    "seasonal_adjustment_short": "NSA",
    "last_updated": "2021-08-06 14:34:35-05",
    "popularity": 2,
    "group_popularity": 2,
    "notes": "BEA Account Code: A048RE\n\nFor more information about this series, please see http://www.bea.gov/national/.",
    "path": "../Database/National Accounts/National Income & Product Accounts/GDP - GNP/Shares of GDP"
  },
  "A054RE1A156NBEA": {
    "id": "A054RE1A156NBEA",
    "realtime_start": "2022-04-05",
    "realtime_end": "2022-04-05",
    "title": "Shares of gross domestic income: Corporate profits with inventory valuation and capital consumption adjustments, domestic industries: Taxes on corporate income",
    "observation_start": "1929-01-01",
    "observation_end": "2020-01-01",
    "frequency": "Annual",
    "frequency_short": "A",
    "units": "Percent",
    "units_short": "%",
    "seasonal_adjustment": "Not Seasonally Adjusted",
    "seasonal_adjustment_short": "NSA",
    "last_updated": "2021-08-06 14:34:15-05",
    "popularity": 6,
    "group_popularity": 6,
    "notes": "BEA Account Code: A054RE\n\nFor more information about this series, please see http://www.bea.gov/national/.",
    "path": "../Database/National Accounts/National Income & Product Accounts/GDP - GNP/Shares of GDP"
  },
  "A107RE1A156NBEA": {
    "id": "A107RE1A156NBEA",
    "realtime_start": "2022-04-05",
    "realtime_end": "2022-04-05",
    "title": "Shares of gross domestic income: Subsidies",
    "observation_start": "1929-01-01",
    "observation_end": "2020-01-01",
    "frequency": "Annual",
    "frequency_short": "A",
    "units": "Percent",
    "units_short": "%",
    "seasonal_adjustment": "Not Seasonally Adjusted",
    "seasonal_adjustment_short": "NSA",
    "last_updated": "2021-08-06 14:41:34-05",
    "popularity": 1,
    "group_popularity": 1,
    "notes": "BEA Account Code: A107RE\n\nFor more information about this series, please see http://www.bea.gov/national/.",
    "path": "../Database/National Accounts/National Income & Product Accounts/GDP - GNP/Shares of GDP"
  },
  "A108RE1A156NBEA": {
    "id": "A108RE1A156NBEA",
    "realtime_start": "2022-04-05",
    "realtime_end": "2022-04-05",
    "title": "Shares of gross domestic income: Current surplus of government enterprises",
    "observation_start": "1959-01-01",
    "observation_end": "2020-01-01",
    "frequency": "Annual",
    "frequency_short": "A",
    "units": "Percent",
    "units_short": "%",
    "seasonal_adjustment": "Not Seasonally Adjusted",
    "seasonal_adjustment_short": "NSA",
    "last_updated": "2021-08-06 14:34:35-05",
    "popularity": 2,
    "group_popularity": 2,
    "notes": "BEA Account Code: A108RE\n\nFor more information about this series, please see http://www.bea.gov/national/.",
    "path": "../Database/National Accounts/National Income & Product Accounts/GDP - GNP/Shares of GDP"
  },
  "A191RE1A156NBEA": {
    "id": "A191RE1A156NBEA",
    "realtime_start": "2022-04-05",
    "realtime_end": "2022-04-05",
    "title": "Shares of gross domestic product",
    "observation_start": "1929-01-01",
    "observation_end": "2021-01-01",
    "frequency": "Annual",
    "frequency_short": "A",
    "units": "Percent",
    "units_short": "%",
    "seasonal_adjustment": "Not Seasonally Adjusted",
    "seasonal_adjustment_short": "NSA",
    "last_updated": "2022-01-27 08:01:00-06",
    "popularity": 3,
    "group_popularity": 12,
    "notes": "BEA Account Code: A191RE\n\nFor more information about this series, please see http://www.bea.gov/national/.",
    "path": "../Database/National Accounts/National Income & Product Accounts/GDP - GNP/Shares of GDP"
  },
  "A191RE1Q156NBEA": {
    "id": "A191RE1Q156NBEA",
    "realtime_start": "2022-04-05",
    "realtime_end": "2022-04-05",
    "title": "Shares of gross domestic product",
    "observation_start": "1947-01-01",
    "observation_end": "2021-10-01",
    "frequency": "Quarterly",
    "frequency_short": "Q",
    "units": "Percent",
    "units_short": "%",
    "seasonal_adjustment": "Not Seasonally Adjusted",
    "seasonal_adjustment_short": "NSA",
    "last_updated": "2022-01-27 07:54:22-06",
    "popularity": 11,
    "group_popularity": 12,
    "notes": "BEA Account Code: A191RE\n\nFor more information about this series, please see http://www.bea.gov/national/.",
    "path": "../Database/National Accounts/National Income & Product Accounts/GDP - GNP/Shares of GDP"
  },
  "A253RE1A156NBEA": {
    "id": "A253RE1A156NBEA",
    "realtime_start": "2022-04-05",
    "realtime_end": "2022-04-05",
    "title": "Shares of gross domestic product: Exports of goods",
    "observation_start": "1929-01-01",
    "observation_end": "2021-01-01",
    "frequency": "Annual",
    "frequency_short": "A",
    "units": "Percent",
    "units_short": "%",
    "seasonal_adjustment": "Not Seasonally Adjusted",
    "seasonal_adjustment_short": "NSA",
    "last_updated": "2022-01-27 08:00:58-06",
    "popularity": 2,
    "group_popularity": 6,
    "notes": "BEA Account Code: A253RE\n\nFor more information about this series, please see http://www.bea.gov/national/.",
    "path": "../Database/National Accounts/National Income & Product Accounts/GDP - GNP/Shares of GDP"
  },
  "A253RE1Q156NBEA": {
    "id": "A253RE1Q156NBEA",
    "realtime_start": "2022-04-05",
    "realtime_end": "2022-04-05",
    "title": "Shares of gross domestic product: Exports of goods",
    "observation_start": "1947-01-01",
    "observation_end": "2021-10-01",
    "frequency": "Quarterly",
    "frequency_short": "Q",
    "units": "Percent",
    "units_short": "%",
    "seasonal_adjustment": "Not Seasonally Adjusted",
    "seasonal_adjustment_short": "NSA",
    "last_updated": "2022-01-27 08:02:43-06",
    "popularity": 5,
    "group_popularity": 6,
    "notes": "BEA Account Code: A253RE\n\nFor more information about this series, please see http://www.bea.gov/national/.",
    "path": "../Database/National Accounts/National Income & Product Accounts/GDP - GNP/Shares of GDP"
  },
  "A255RE1A156NBEA": {
    "id": "A255RE1A156NBEA",
    "realtime_start": "2022-04-05",
    "realtime_end": "2022-04-05",
    "title": "Shares of gross domestic product: Imports of goods",
    "observation_start": "1929-01-01",
    "observation_end": "2021-01-01",
    "frequency": "Annual",
    "frequency_short": "A",
    "units": "Percent",
    "units_short": "%",
    "seasonal_adjustment": "Not Seasonally Adjusted",
    "seasonal_adjustment_short": "NSA",
    "last_updated": "2022-01-27 08:00:57-06",
    "popularity": 2,
    "group_popularity": 5,
    "notes": "BEA Account Code: A255RE\n\nFor more information about this series, please see http://www.bea.gov/national/.",
    "path": "../Database/National Accounts/National Income & Product Accounts/GDP - GNP/Shares of GDP"
  },
  "A255RE1Q156NBEA": {
    "id": "A255RE1Q156NBEA",
    "realtime_start": "2022-04-05",
    "realtime_end": "2022-04-05",
    "title": "Shares of gross domestic product: Imports of goods",
    "observation_start": "1947-01-01",
    "observation_end": "2021-10-01",
    "frequency": "Quarterly",
    "frequency_short": "Q",
    "units": "Percent",
    "units_short": "%",
    "seasonal_adjustment": "Not Seasonally Adjusted",
    "seasonal_adjustment_short": "NSA",
    "last_updated": "2022-01-27 07:55:31-06",
    "popularity": 4,
    "group_popularity": 5,
    "notes": "BEA Account Code: A255RE\n\nFor more information about this series, please see http://www.bea.gov/national/.",
    "path": "../Database/National Accounts/National Income & Product Accounts/GDP - GNP/Shares of GDP"
  },
  "A261RE1A156NBEA": {
    "id": "A261RE1A156NBEA",
    "realtime_start": "2022-04-05",
    "realtime_end": "2022-04-05",
    "title": "Shares of gross domestic income",
    "observation_start": "1929-01-01",
    "observation_end": "2020-01-01",
    "frequency": "Annual",
    "frequency_short": "A",
    "units": "Percent",
    "units_short": "%",
    "seasonal_adjustment": "Not Seasonally Adjusted",
    "seasonal_adjustment_short": "NSA",
    "last_updated": "2021-08-06 14:34:22-05",
    "popularity": 6,
    "group_popularity": 6,
    "notes": "BEA Account Code: A261RE\n\nFor more information about this series, please see http://www.bea.gov/national/.",
    "path": "../Database/National Accounts/National Income & Product Accounts/GDP - GNP/Shares of GDP"
  },
  "A262RE1A156NBEA": {
    "id": "A262RE1A156NBEA",
    "realtime_start": "2022-04-05",
    "realtime_end": "2022-04-05",
    "title": "Shares of gross domestic income: Consumption of fixed capital",
    "observation_start": "1929-01-01",
    "observation_end": "2020-01-01",
    "frequency": "Annual",
    "frequency_short": "A",
    "units": "Percent",
    "units_short": "%",
    "seasonal_adjustment": "Not Seasonally Adjusted",
    "seasonal_adjustment_short": "NSA",
    "last_updated": "2021-08-06 14:34:08-05",
    "popularity": 10,
    "group_popularity": 10,
    "notes": "BEA Account Code: A262RE\n\nFor more information about this series, please see http://www.bea.gov/national/.",
    "path": "../Database/National Accounts/National Income & Product Accounts/GDP - GNP/Shares of GDP"
  },
  "A264RE1A156NBEA": {
    "id": "A264RE1A156NBEA",
    "realtime_start": "2022-04-05",
    "realtime_end": "2022-04-05",
    "title": "Shares of gross domestic income: Consumption of fixed capital: Government",
    "observation_start": "1929-01-01",
    "observation_end": "2020-01-01",
    "frequency": "Annual",
    "frequency_short": "A",
    "units": "Percent",
    "units_short": "%",
    "seasonal_adjustment": "Not Seasonally Adjusted",
    "seasonal_adjustment_short": "NSA",
    "last_updated": "2021-08-06 14:40:57-05",
    "popularity": 2,
    "group_popularity": 2,
    "notes": "BEA Account Code: A264RE\n\nFor more information about this series, please see http://www.bea.gov/national/.",
    "path": "../Database/National Accounts/National Income & Product Accounts/GDP - GNP/Shares of GDP"
  },
  "A445RE1A156NBEA": {
    "id": "A445RE1A156NBEA",
    "realtime_start": "2022-04-05",
    "realtime_end": "2022-04-05",
    "title": "Shares of gross domestic income: Corporate profits with inventory valuation and capital consumption adjustments, domestic industries",
    "observation_start": "1929-01-01",
    "observation_end": "2020-01-01",
    "frequency": "Annual",
    "frequency_short": "A",
    "units": "Percent",
    "units_short": "%",
    "seasonal_adjustment": "Not Seasonally Adjusted",
    "seasonal_adjustment_short": "NSA",
    "last_updated": "2021-08-06 14:34:06-05",
    "popularity": 14,
    "group_popularity": 14,
    "notes": "BEA Account Code: A445RE\n\nFor more information about this series, please see http://www.bea.gov/national/.",
    "path": "../Database/National Accounts/National Income & Product Accounts/GDP - GNP/Shares of GDP"
  },
  "A449RE1A156NBEA": {
    "id": "A449RE1A156NBEA",
    "realtime_start": "2022-04-05",
    "realtime_end": "2022-04-05",
    "title": "Shares of gross domestic income: Corporate profits with inventory valuation and capital consumption adjustments, domestic industries: Profits after tax with inventory valuation and capital consumption adjustments: Net dividends",
    "observation_start": "1929-01-01",
    "observation_end": "2020-01-01",
    "frequency": "Annual",
    "frequency_short": "A",
    "units": "Percent",
    "units_short": "%",
    "seasonal_adjustment": "Not Seasonally Adjusted",
    "seasonal_adjustment_short": "NSA",
    "last_updated": "2021-08-06 14:34:15-05",
    "popularity": 6,
    "group_popularity": 6,
    "notes": "BEA Account Code: A449RE\n\nFor more information about this series, please see http://www.bea.gov/national/.",
    "path": "../Database/National Accounts/National Income & Product Accounts/GDP - GNP/Shares of GDP"
  },
  "A646RE1A156NBEA": {
    "id": "A646RE1A156NBEA",
    "realtime_start": "2022-04-05",
    "realtime_end": "2022-04-05",
    "title": "Shares of gross domestic product: Exports of services",
    "observation_start": "1929-01-01",
    "observation_end": "2021-01-01",
    "frequency": "Annual",
    "frequency_short": "A",
    "units": "Percent",
    "units_short": "%",
    "seasonal_adjustment": "Not Seasonally Adjusted",
    "seasonal_adjustment_short": "NSA",
    "last_updated": "2022-01-27 08:00:42-06",
    "popularity": 1,
    "group_popularity": 2,
    "notes": "BEA Account Code: A646RE\n\nFor more information about this series, please see http://www.bea.gov/national/.",
    "path": "../Database/National Accounts/National Income & Product Accounts/GDP - GNP/Shares of GDP"
  },
  "A646RE1Q156NBEA": {
    "id": "A646RE1Q156NBEA",
    "realtime_start": "2022-04-05",
    "realtime_end": "2022-04-05",
    "title": "Shares of gross domestic product: Exports of services",
    "observation_start": "1947-01-01",
    "observation_end": "2021-10-01",
    "frequency": "Quarterly",
    "frequency_short": "Q",
    "units": "Percent",
    "units_short": "%",
    "seasonal_adjustment": "Not Seasonally Adjusted",
    "seasonal_adjustment_short": "NSA",
    "last_updated": "2022-03-30 08:05:38-05",
    "popularity": 2,
    "group_popularity": 2,
    "notes": "BEA Account Code: A646RE\n\nFor more information about this series, please see http://www.bea.gov/national/.",
    "path": "../Database/National Accounts/National Income & Product Accounts/GDP - GNP/Shares of GDP"
  },
  "A822RE1A156NBEA": {
    "id": "A822RE1A156NBEA",
    "realtime_start": "2022-04-05",
    "realtime_end": "2022-04-05",
    "title": "Shares of gross domestic product: Government consumption expenditures and gross investment",
    "observation_start": "1929-01-01",
    "observation_end": "2021-01-01",
    "frequency": "Annual",
    "frequency_short": "A",
    "units": "Percent",
    "units_short": "%",
    "seasonal_adjustment": "Not Seasonally Adjusted",
    "seasonal_adjustment_short": "NSA",
    "last_updated": "2022-01-27 07:53:18-06",
    "popularity": 14,
    "group_popularity": 40,
    "notes": "BEA Account Code: A822RE\n\nFor more information about this series, please see http://www.bea.gov/national/.",
    "path": "../Database/National Accounts/National Income & Product Accounts/GDP - GNP/Shares of GDP"
  },
  "A822RE1Q156NBEA": {
    "id": "A822RE1Q156NBEA",
    "realtime_start": "2022-04-05",
    "realtime_end": "2022-04-05",
    "title": "Shares of gross domestic product: Government consumption expenditures and gross investment",
    "observation_start": "1947-01-01",
    "observation_end": "2021-10-01",
    "frequency": "Quarterly",
    "frequency_short": "Q",
    "units": "Percent",
    "units_short": "%",
    "seasonal_adjustment": "Not Seasonally Adjusted",
    "seasonal_adjustment_short": "NSA",
    "last_updated": "2022-01-27 07:54:15-06",
    "popularity": 38,
    "group_popularity": 40,
    "notes": "BEA Account Code: A822RE\n\nFor more information about this series, please see http://www.bea.gov/national/.",
    "path": "../Database/National Accounts/National Income & Product Accounts/GDP - GNP/Shares of GDP"
  },
  "A823RE1A156NBEA": {
    "id": "A823RE1A156NBEA",
    "realtime_start": "2022-04-05",
    "realtime_end": "2022-04-05",
    "title": "Shares of gross domestic product: Government consumption expenditures and gross investment: Federal",
    "observation_start": "1929-01-01",
    "observation_end": "2021-01-01",
    "frequency": "Annual",
    "frequency_short": "A",
    "units": "Percent",
    "units_short": "%",
    "seasonal_adjustment": "Not Seasonally Adjusted",
    "seasonal_adjustment_short": "NSA",
    "last_updated": "2022-01-27 08:00:26-06",
    "popularity": 2,
    "group_popularity": 7,
    "notes": "BEA Account Code: A823RE\n\nFor more information about this series, please see http://www.bea.gov/national/.",
    "path": "../Database/National Accounts/National Income & Product Accounts/GDP - GNP/Shares of GDP"
  },
  "A823RE1Q156NBEA": {
    "id": "A823RE1Q156NBEA",
    "realtime_start": "2022-04-05",
    "realtime_end": "2022-04-05",
    "title": "Shares of gross domestic product: Government consumption expenditures and gross investment: Federal",
    "observation_start": "1947-01-01",
    "observation_end": "2021-10-01",
    "frequency": "Quarterly",
    "frequency_short": "Q",
    "units": "Percent",
    "units_short": "%",
    "seasonal_adjustment": "Not Seasonally Adjusted",
    "seasonal_adjustment_short": "NSA",
    "last_updated": "2022-01-27 07:54:34-06",
    "popularity": 6,
    "group_popularity": 7,
    "notes": "BEA Account Code: A823RE\n\nFor more information about this series, please see http://www.bea.gov/national/.",
    "path": "../Database/National Accounts/National Income & Product Accounts/GDP - GNP/Shares of GDP"
  },
  "A824RE1A156NBEA": {
    "id": "A824RE1A156NBEA",
    "realtime_start": "2022-04-05",
    "realtime_end": "2022-04-05",
    "title": "Shares of gross domestic product: Government consumption expenditures and gross investment: Federal: National defense",
    "observation_start": "1929-01-01",
    "observation_end": "2021-01-01",
    "frequency": "Annual",
    "frequency_short": "A",
    "units": "Percent",
    "units_short": "%",
    "seasonal_adjustment": "Not Seasonally Adjusted",
    "seasonal_adjustment_short": "NSA",
    "last_updated": "2022-01-27 07:54:49-06",
    "popularity": 5,
    "group_popularity": 23,
    "notes": "BEA Account Code: A824RE\n\nFor more information about this series, please see http://www.bea.gov/national/.",
    "path": "../Database/National Accounts/National Income & Product Accounts/GDP - GNP/Shares of GDP"
  },
  "A824RE1Q156NBEA": {
    "id": "A824RE1Q156NBEA",
    "realtime_start": "2022-04-05",
    "realtime_end": "2022-04-05",
    "title": "Shares of gross domestic product: Government consumption expenditures and gross investment: Federal: National defense",
    "observation_start": "1947-01-01",
    "observation_end": "2021-10-01",
    "frequency": "Quarterly",
    "frequency_short": "Q",
    "units": "Percent",
    "units_short": "%",
    "seasonal_adjustment": "Not Seasonally Adjusted",
    "seasonal_adjustment_short": "NSA",
    "last_updated": "2022-01-27 07:54:23-06",
    "popularity": 20,
    "group_popularity": 23,
    "notes": "BEA Account Code: A824RE\n\nFor more information about this series, please see http://www.bea.gov/national/.",
    "path": "../Database/National Accounts/National Income & Product Accounts/GDP - GNP/Shares of GDP"
  },
  "A825RE1A156NBEA": {
    "id": "A825RE1A156NBEA",
    "realtime_start": "2022-04-05",
    "realtime_end": "2022-04-05",
    "title": "Shares of gross domestic product: Government consumption expenditures and gross investment: Federal: Nondefense",
    "observation_start": "1929-01-01",
    "observation_end": "2021-01-01",
    "frequency": "Annual",
    "frequency_short": "A",
    "units": "Percent",
    "units_short": "%",
    "seasonal_adjustment": "Not Seasonally Adjusted",
    "seasonal_adjustment_short": "NSA",
    "last_updated": "2022-01-27 07:55:22-06",
    "popularity": 2,
    "group_popularity": 6,
    "notes": "BEA Account Code: A825RE\n\nFor more information about this series, please see http://www.bea.gov/national/.",
    "path": "../Database/National Accounts/National Income & Product Accounts/GDP - GNP/Shares of GDP"
  },
  "A825RE1Q156NBEA": {
    "id": "A825RE1Q156NBEA",
    "realtime_start": "2022-04-05",
    "realtime_end": "2022-04-05",
    "title": "Shares of gross domestic product: Government consumption expenditures and gross investment: Federal: Nondefense",
    "observation_start": "1947-01-01",
    "observation_end": "2021-10-01",
    "frequency": "Quarterly",
    "frequency_short": "Q",
    "units": "Percent",
    "units_short": "%",
    "seasonal_adjustment": "Not Seasonally Adjusted",
    "seasonal_adjustment_short": "NSA",
    "last_updated": "2022-01-27 07:54:39-06",
    "popularity": 5,
    "group_popularity": 6,
    "notes": "BEA Account Code: A825RE\n\nFor more information about this series, please see http://www.bea.gov/national/.",
    "path": "../Database/National Accounts/National Income & Product Accounts/GDP - GNP/Shares of GDP"
  },
  "A829RE1A156NBEA": {
    "id": "A829RE1A156NBEA",
    "realtime_start": "2022-04-05",
    "realtime_end": "2022-04-05",
    "title": "Shares of gross domestic product: Government consumption expenditures and gross investment: State and local",
    "observation_start": "1929-01-01",
    "observation_end": "2021-01-01",
    "frequency": "Annual",
    "frequency_short": "A",
    "units": "Percent",
    "units_short": "%",
    "seasonal_adjustment": "Not Seasonally Adjusted",
    "seasonal_adjustment_short": "NSA",
    "last_updated": "2022-01-27 08:00:24-06",
    "popularity": 2,
    "group_popularity": 4,
    "notes": "BEA Account Code: A829RE\n\nFor more information about this series, please see http://www.bea.gov/national/.",
    "path": "../Database/National Accounts/National Income & Product Accounts/GDP - GNP/Shares of GDP"
  },
  "A829RE1Q156NBEA": {
    "id": "A829RE1Q156NBEA",
    "realtime_start": "2022-04-05",
    "realtime_end": "2022-04-05",
    "title": "Shares of gross domestic product: Government consumption expenditures and gross investment: State and local",
    "observation_start": "1947-01-01",
    "observation_end": "2021-10-01",
    "frequency": "Quarterly",
    "frequency_short": "Q",
    "units": "Percent",
    "units_short": "%",
    "seasonal_adjustment": "Not Seasonally Adjusted",
    "seasonal_adjustment_short": "NSA",
    "last_updated": "2022-01-27 07:54:54-06",
    "popularity": 3,
    "group_popularity": 4,
    "notes": "BEA Account Code: A829RE\n\nFor more information about this series, please see http://www.bea.gov/national/.",
    "path": "../Database/National Accounts/National Income & Product Accounts/GDP - GNP/Shares of GDP"
  },
  "A4002E1A156NBEA": {
    "id": "A4002E1A156NBEA",
    "realtime_start": "2022-04-05",
    "realtime_end": "2022-04-05",
    "title": "Shares of gross domestic income: Compensation of employees, paid",
    "observation_start": "1929-01-01",
    "observation_end": "2020-01-01",
    "frequency": "Annual",
    "frequency_short": "A",
    "units": "Percent",
    "units_short": "%",
    "seasonal_adjustment": "Not Seasonally Adjusted",
    "seasonal_adjustment_short": "NSA",
    "last_updated": "2021-08-06 14:34:05-05",
    "popularity": 17,
    "group_popularity": 17,
    "notes": "BEA Account Code: A4002E\n\nFor more information about this series, please see http://www.bea.gov/national/.",
    "path": "../Database/National Accounts/National Income & Product Accounts/GDP - GNP/Shares of GDP"
  },
  "A4102E1A156NBEA": {
    "id": "A4102E1A156NBEA",
    "realtime_start": "2022-04-05",
    "realtime_end": "2022-04-05",
    "title": "Shares of gross domestic income: Compensation of employees, paid: Wage and salary accruals",
    "observation_start": "1929-01-01",
    "observation_end": "2020-01-01",
    "frequency": "Annual",
    "frequency_short": "A",
    "units": "Percent",
    "units_short": "%",
    "seasonal_adjustment": "Not Seasonally Adjusted",
    "seasonal_adjustment_short": "NSA",
    "last_updated": "2021-08-06 14:34:08-05",
    "popularity": 6,
    "group_popularity": 6,
    "notes": "BEA Account Code: A4102E\n\nFor more information about this series, please see http://www.bea.gov/national/.",
    "path": "../Database/National Accounts/National Income & Product Accounts/GDP - GNP/Shares of GDP"
  },
  "B009RE1A156NBEA": {
    "id": "B009RE1A156NBEA",
    "realtime_start": "2022-04-05",
    "realtime_end": "2022-04-05",
    "title": "Shares of gross domestic product: Gross private domestic investment: Fixed investment: Nonresidential: Structures",
    "observation_start": "1929-01-01",
    "observation_end": "2021-01-01",
    "frequency": "Annual",
    "frequency_short": "A",
    "units": "Percent",
    "units_short": "%",
    "seasonal_adjustment": "Not Seasonally Adjusted",
    "seasonal_adjustment_short": "NSA",
    "last_updated": "2022-01-27 08:00:47-06",
    "popularity": 2,
    "group_popularity": 3,
    "notes": "BEA Account Code: B009RE\n\nFor more information about this series, please see http://www.bea.gov/national/.",
    "path": "../Database/National Accounts/National Income & Product Accounts/GDP - GNP/Shares of GDP"
  },
  "B009RE1Q156NBEA": {
    "id": "B009RE1Q156NBEA",
    "realtime_start": "2022-04-05",
    "realtime_end": "2022-04-05",
    "title": "Shares of gross domestic product: Gross private domestic investment: Fixed investment: Nonresidential: Structures",
    "observation_start": "1947-01-01",
    "observation_end": "2021-10-01",
    "frequency": "Quarterly",
    "frequency_short": "Q",
    "units": "Percent",
    "units_short": "%",
    "seasonal_adjustment": "Not Seasonally Adjusted",
    "seasonal_adjustment_short": "NSA",
    "last_updated": "2022-01-27 07:54:53-06",
    "popularity": 3,
    "group_popularity": 3,
    "notes": "BEA Account Code: B009RE\n\nFor more information about this series, please see http://www.bea.gov/national/.",
    "path": "../Database/National Accounts/National Income & Product Accounts/GDP - GNP/Shares of GDP"
  },
  "B020RE1A156NBEA": {
    "id": "B020RE1A156NBEA",
    "realtime_start": "2022-04-05",
    "realtime_end": "2022-04-05",
    "title": "Shares of gross domestic product: Exports of goods and services",
    "observation_start": "1929-01-01",
    "observation_end": "2021-01-01",
    "frequency": "Annual",
    "frequency_short": "A",
    "units": "Percent",
    "units_short": "%",
    "seasonal_adjustment": "Not Seasonally Adjusted",
    "seasonal_adjustment_short": "NSA",
    "last_updated": "2022-01-27 07:55:21-06",
    "popularity": 8,
    "group_popularity": 35,
    "notes": "BEA Account Code: B020RE\n\nFor more information about this series, please see http://www.bea.gov/national/.",
    "path": "../Database/National Accounts/National Income & Product Accounts/GDP - GNP/Shares of GDP"
  },
  "B020RE1Q156NBEA": {
    "id": "B020RE1Q156NBEA",
    "realtime_start": "2022-04-05",
    "realtime_end": "2022-04-05",
    "title": "Shares of gross domestic product: Exports of goods and services",
    "observation_start": "1947-01-01",
    "observation_end": "2021-10-01",
    "frequency": "Quarterly",
    "frequency_short": "Q",
    "units": "Percent",
    "units_short": "%",
    "seasonal_adjustment": "Not Seasonally Adjusted",
    "seasonal_adjustment_short": "NSA",
    "last_updated": "2022-01-27 07:54:15-06",
    "popularity": 34,
    "group_popularity": 35,
    "notes": "BEA Account Code: B020RE\n\nFor more information about this series, please see http://www.bea.gov/national/.",
    "path": "../Database/National Accounts/National Income & Product Accounts/GDP - GNP/Shares of GDP"
  },
  "B021RE1A156NBEA": {
    "id": "B021RE1A156NBEA",
    "realtime_start": "2022-04-05",
    "realtime_end": "2022-04-05",
    "title": "Shares of gross domestic product: Imports of goods and services",
    "observation_start": "1929-01-01",
    "observation_end": "2021-01-01",
    "frequency": "Annual",
    "frequency_short": "A",
    "units": "Percent",
    "units_short": "%",
    "seasonal_adjustment": "Not Seasonally Adjusted",
    "seasonal_adjustment_short": "NSA",
    "last_updated": "2022-01-27 07:53:28-06",
    "popularity": 15,
    "group_popularity": 26,
    "notes": "BEA Account Code: B021RE\n\nFor more information about this series, please see http://www.bea.gov/national/.",
    "path": "../Database/National Accounts/National Income & Product Accounts/GDP - GNP/Shares of GDP"
  },
  "B021RE1Q156NBEA": {
    "id": "B021RE1Q156NBEA",
    "realtime_start": "2022-04-05",
    "realtime_end": "2022-04-05",
    "title": "Shares of gross domestic product: Imports of goods and services",
    "observation_start": "1947-01-01",
    "observation_end": "2021-10-01",
    "frequency": "Quarterly",
    "frequency_short": "Q",
    "units": "Percent",
    "units_short": "%",
    "seasonal_adjustment": "Not Seasonally Adjusted",
    "seasonal_adjustment_short": "NSA",
    "last_updated": "2022-01-27 07:54:21-06",
    "popularity": 20,
    "group_popularity": 26,
    "notes": "BEA Account Code: B021RE\n\nFor more information about this series, please see http://www.bea.gov/national/.",
    "path": "../Database/National Accounts/National Income & Product Accounts/GDP - GNP/Shares of GDP"
  },
  "B029RE1A156NBEA": {
    "id": "B029RE1A156NBEA",
    "realtime_start": "2022-04-05",
    "realtime_end": "2022-04-05",
    "title": "Shares of gross domestic income: Net operating surplus: Private enterprises: Business current transfer payments (net)",
    "observation_start": "1929-01-01",
    "observation_end": "2020-01-01",
    "frequency": "Annual",
    "frequency_short": "A",
    "units": "Percent",
    "units_short": "%",
    "seasonal_adjustment": "Not Seasonally Adjusted",
    "seasonal_adjustment_short": "NSA",
    "last_updated": "2021-08-06 14:40:33-05",
    "popularity": 1,
    "group_popularity": 1,
    "notes": "BEA Account Code: B029RE\n\nFor more information about this series, please see http://www.bea.gov/national/.",
    "path": "../Database/National Accounts/National Income & Product Accounts/GDP - GNP/Shares of GDP"
  },
  "B656RE1A156NBEA": {
    "id": "B656RE1A156NBEA",
    "realtime_start": "2022-04-05",
    "realtime_end": "2022-04-05",
    "title": "Shares of gross domestic product: Imports of services",
    "observation_start": "1929-01-01",
    "observation_end": "2021-01-01",
    "frequency": "Annual",
    "frequency_short": "A",
    "units": "Percent",
    "units_short": "%",
    "seasonal_adjustment": "Not Seasonally Adjusted",
    "seasonal_adjustment_short": "NSA",
    "last_updated": "2022-01-27 07:57:56-06",
    "popularity": 1,
    "group_popularity": 1,
    "notes": "BEA Account Code: B656RE\n\nFor more information about this series, please see http://www.bea.gov/national/.",
    "path": "../Database/National Accounts/National Income & Product Accounts/GDP - GNP/Shares of GDP"
  },
  "B656RE1Q156NBEA": {
    "id": "B656RE1Q156NBEA",
    "realtime_start": "2022-04-05",
    "realtime_end": "2022-04-05",
    "title": "Shares of gross domestic product: Imports of services",
    "observation_start": "1947-01-01",
    "observation_end": "2021-10-01",
    "frequency": "Quarterly",
    "frequency_short": "Q",
    "units": "Percent",
    "units_short": "%",
    "seasonal_adjustment": "Not Seasonally Adjusted",
    "seasonal_adjustment_short": "NSA",
    "last_updated": "2022-01-27 08:02:24-06",
    "popularity": 1,
    "group_popularity": 1,
    "notes": "BEA Account Code: B656RE\n\nFor more information about this series, please see http://www.bea.gov/national/.",
    "path": "../Database/National Accounts/National Income & Product Accounts/GDP - GNP/Shares of GDP"
  },
  "B4189E1A156NBEA": {
    "id": "B4189E1A156NBEA",
    "realtime_start": "2022-04-05",
    "realtime_end": "2022-04-05",
    "title": "Shares of gross domestic income: Compensation of employees, paid: Wage and salary accruals: Disbursements: to the rest of the world",
    "observation_start": "1948-01-01",
    "observation_end": "2020-01-01",
    "frequency": "Annual",
    "frequency_short": "A",
    "units": "Percent",
    "units_short": "%",
    "seasonal_adjustment": "Not Seasonally Adjusted",
    "seasonal_adjustment_short": "NSA",
    "last_updated": "2021-08-06 14:39:54-05",
    "popularity": 1,
    "group_popularity": 1,
    "notes": "BEA Account Code: B4189E\n\nFor more information about this series, please see http://www.bea.gov/national/.",
    "path": "../Database/National Accounts/National Income & Product Accounts/GDP - GNP/Shares of GDP"
  },
  "DDURRE1A156NBEA": {
    "id": "DDURRE1A156NBEA",
    "realtime_start": "2022-04-05",
    "realtime_end": "2022-04-05",
    "title": "Shares of gross domestic product: Personal consumption expenditures: Durable goods",
    "observation_start": "1929-01-01",
    "observation_end": "2021-01-01",
    "frequency": "Annual",
    "frequency_short": "A",
    "units": "Percent",
    "units_short": "%",
    "seasonal_adjustment": "Not Seasonally Adjusted",
    "seasonal_adjustment_short": "NSA",
    "last_updated": "2022-01-27 07:57:20-06",
    "popularity": 2,
    "group_popularity": 7,
    "notes": "BEA Account Code: DDURRE\n\nFor more information about this series, please see http://www.bea.gov/national/.",
    "path": "../Database/National Accounts/National Income & Product Accounts/GDP - GNP/Shares of GDP"
  },
  "DDURRE1Q156NBEA": {
    "id": "DDURRE1Q156NBEA",
    "realtime_start": "2022-04-05",
    "realtime_end": "2022-04-05",
    "title": "Shares of gross domestic product: Personal consumption expenditures: Durable goods",
    "observation_start": "1947-01-01",
    "observation_end": "2021-10-01",
    "frequency": "Quarterly",
    "frequency_short": "Q",
    "units": "Percent",
    "units_short": "%",
    "seasonal_adjustment": "Not Seasonally Adjusted",
    "seasonal_adjustment_short": "NSA",
    "last_updated": "2022-01-27 07:53:35-06",
    "popularity": 6,
    "group_popularity": 7,
    "notes": "BEA Account Code: DDURRE\n\nFor more information about this series, please see http://www.bea.gov/national/.",
    "path": "../Database/National Accounts/National Income & Product Accounts/GDP - GNP/Shares of GDP"
  },
  "DGDSRE1A156NBEA": {
    "id": "DGDSRE1A156NBEA",
    "realtime_start": "2022-04-05",
    "realtime_end": "2022-04-05",
    "title": "Shares of gross domestic product: Personal consumption expenditures: Goods",
    "observation_start": "1929-01-01",
    "observation_end": "2021-01-01",
    "frequency": "Annual",
    "frequency_short": "A",
    "units": "Percent",
    "units_short": "%",
    "seasonal_adjustment": "Not Seasonally Adjusted",
    "seasonal_adjustment_short": "NSA",
    "last_updated": "2022-01-27 07:57:10-06",
    "popularity": 2,
    "group_popularity": 8,
    "notes": "BEA Account Code: DGDSRE\n\nFor more information about this series, please see http://www.bea.gov/national/.",
    "path": "../Database/National Accounts/National Income & Product Accounts/GDP - GNP/Shares of GDP"
  },
  "DGDSRE1Q156NBEA": {
    "id": "DGDSRE1Q156NBEA",
    "realtime_start": "2022-04-05",
    "realtime_end": "2022-04-05",
    "title": "Shares of gross domestic product: Personal consumption expenditures: Goods",
    "observation_start": "1947-01-01",
    "observation_end": "2021-10-01",
    "frequency": "Quarterly",
    "frequency_short": "Q",
    "units": "Percent",
    "units_short": "%",
    "seasonal_adjustment": "Not Seasonally Adjusted",
    "seasonal_adjustment_short": "NSA",
    "last_updated": "2022-03-30 07:56:52-05",
    "popularity": 7,
    "group_popularity": 8,
    "notes": "BEA Account Code: DGDSRE\n\nFor more information about this series, please see http://www.bea.gov/national/.",
    "path": "../Database/National Accounts/National Income & Product Accounts/GDP - GNP/Shares of GDP"
  },
  "DNDGRE1A156NBEA": {
    "id": "DNDGRE1A156NBEA",
    "realtime_start": "2022-04-05",
    "realtime_end": "2022-04-05",
    "title": "Shares of gross domestic product: Personal consumption expenditures: Nondurable goods",
    "observation_start": "1929-01-01",
    "observation_end": "2021-01-01",
    "frequency": "Annual",
    "frequency_short": "A",
    "units": "Percent",
    "units_short": "%",
    "seasonal_adjustment": "Not Seasonally Adjusted",
    "seasonal_adjustment_short": "NSA",
    "last_updated": "2022-01-27 07:56:52-06",
    "popularity": 2,
    "group_popularity": 5,
    "notes": "BEA Account Code: DNDGRE\n\nFor more information about this series, please see http://www.bea.gov/national/.",
    "path": "../Database/National Accounts/National Income & Product Accounts/GDP - GNP/Shares of GDP"
  },
  "DNDGRE1Q156NBEA": {
    "id": "DNDGRE1Q156NBEA",
    "realtime_start": "2022-04-05",
    "realtime_end": "2022-04-05",
    "title": "Shares of gross domestic product: Personal consumption expenditures: Nondurable goods",
    "observation_start": "1947-01-01",
    "observation_end": "2021-10-01",
    "frequency": "Quarterly",
    "frequency_short": "Q",
    "units": "Percent",
    "units_short": "%",
    "seasonal_adjustment": "Not Seasonally Adjusted",
    "seasonal_adjustment_short": "NSA",
    "last_updated": "2022-01-27 07:53:53-06",
    "popularity": 5,
    "group_popularity": 5,
    "notes": "BEA Account Code: DNDGRE\n\nFor more information about this series, please see http://www.bea.gov/national/.",
    "path": "../Database/National Accounts/National Income & Product Accounts/GDP - GNP/Shares of GDP"
  },
  "DPCERE1A156NBEA": {
    "id": "DPCERE1A156NBEA",
    "realtime_start": "2022-04-05",
    "realtime_end": "2022-04-05",
    "title": "Shares of gross domestic product: Personal consumption expenditures",
    "observation_start": "1929-01-01",
    "observation_end": "2021-01-01",
    "frequency": "Annual",
    "frequency_short": "A",
    "units": "Percent",
    "units_short": "%",
    "seasonal_adjustment": "Not Seasonally Adjusted",
    "seasonal_adjustment_short": "NSA",
    "last_updated": "2022-01-27 07:52:06-06",
    "popularity": 13,
    "group_popularity": 58,
    "notes": "BEA Account Code: DPCERE\n\nFor more information about this series, please see http://www.bea.gov/national/.",
    "path": "../Database/National Accounts/National Income & Product Accounts/GDP - GNP/Shares of GDP"
  },
  "DPCERE1Q156NBEA": {
    "id": "DPCERE1Q156NBEA",
    "realtime_start": "2022-04-05",
    "realtime_end": "2022-04-05",
    "title": "Shares of gross domestic product: Personal consumption expenditures",
    "observation_start": "1947-01-01",
    "observation_end": "2021-10-01",
    "frequency": "Quarterly",
    "frequency_short": "Q",
    "units": "Percent",
    "units_short": "%",
    "seasonal_adjustment": "Not Seasonally Adjusted",
    "seasonal_adjustment_short": "NSA",
    "last_updated": "2022-02-24 07:56:03-06",
    "popularity": 58,
    "group_popularity": 58,
    "notes": "BEA Account Code: DPCERE\n\nFor more information about this series, please see http://www.bea.gov/national/.",
    "path": "../Database/National Accounts/National Income & Product Accounts/GDP - GNP/Shares of GDP"
  },
  "DSERRE1A156NBEA": {
    "id": "DSERRE1A156NBEA",
    "realtime_start": "2022-04-05",
    "realtime_end": "2022-04-05",
    "title": "Shares of gross domestic product: Personal consumption expenditures: Services",
    "observation_start": "1929-01-01",
    "observation_end": "2021-01-01",
    "frequency": "Annual",
    "frequency_short": "A",
    "units": "Percent",
    "units_short": "%",
    "seasonal_adjustment": "Not Seasonally Adjusted",
    "seasonal_adjustment_short": "NSA",
    "last_updated": "2022-02-24 07:53:11-06",
    "popularity": 3,
    "group_popularity": 11,
    "notes": "BEA Account Code: DSERRE\n\nFor more information about this series, please see http://www.bea.gov/national/.",
    "path": "../Database/National Accounts/National Income & Product Accounts/GDP - GNP/Shares of GDP"
  },
  "DSERRE1Q156NBEA": {
    "id": "DSERRE1Q156NBEA",
    "realtime_start": "2022-04-05",
    "realtime_end": "2022-04-05",
    "title": "Shares of gross domestic product: Personal consumption expenditures: Services",
    "observation_start": "1947-01-01",
    "observation_end": "2021-10-01",
    "frequency": "Quarterly",
    "frequency_short": "Q",
    "units": "Percent",
    "units_short": "%",
    "seasonal_adjustment": "Not Seasonally Adjusted",
    "seasonal_adjustment_short": "NSA",
    "last_updated": "2022-03-30 07:56:46-05",
    "popularity": 9,
    "group_popularity": 11,
    "notes": "BEA Account Code: DSERRE\n\nFor more information about this series, please see http://www.bea.gov/national/.",
    "path": "../Database/National Accounts/National Income & Product Accounts/GDP - GNP/Shares of GDP"
  },
  "W056RE1A156NBEA": {
    "id": "W056RE1A156NBEA",
    "realtime_start": "2022-04-05",
    "realtime_end": "2022-04-05",
    "title": "Shares of gross domestic income: Taxes on production and imports",
    "observation_start": "1929-01-01",
    "observation_end": "2020-01-01",
    "frequency": "Annual",
    "frequency_short": "A",
    "units": "Percent",
    "units_short": "%",
    "seasonal_adjustment": "Not Seasonally Adjusted",
    "seasonal_adjustment_short": "NSA",
    "last_updated": "2021-08-06 14:36:24-05",
    "popularity": 2,
    "group_popularity": 2,
    "notes": "BEA Account Code: W056RE\n\nFor more information about this series, please see http://www.bea.gov/national/.",
    "path": "../Database/National Accounts/National Income & Product Accounts/GDP - GNP/Shares of GDP"
  },
  "W260RE1A156NBEA": {
    "id": "W260RE1A156NBEA",
    "realtime_start": "2022-04-05",
    "realtime_end": "2022-04-05",
    "title": "Shares of gross domestic income: Net operating surplus: Private enterprises",
    "observation_start": "1929-01-01",
    "observation_end": "2020-01-01",
    "frequency": "Annual",
    "frequency_short": "A",
    "units": "Percent",
    "units_short": "%",
    "seasonal_adjustment": "Not Seasonally Adjusted",
    "seasonal_adjustment_short": "NSA",
    "last_updated": "2021-08-06 14:33:17-05",
    "popularity": 3,
    "group_popularity": 3,
    "notes": "BEA Account Code: W260RE\n\nFor more information about this series, please see http://www.bea.gov/national/.",
    "path": "../Database/National Accounts/National Income & Product Accounts/GDP - GNP/Shares of GDP"
  },
  "W270RE1A156NBEA": {
    "id": "W270RE1A156NBEA",
    "realtime_start": "2022-04-05",
    "realtime_end": "2022-04-05",
    "title": "Shares of gross domestic income: Compensation of employees, paid: Wage and salary accruals: Disbursements: to persons",
    "observation_start": "1948-01-01",
    "observation_end": "2020-01-01",
    "frequency": "Annual",
    "frequency_short": "A",
    "units": "Percent",
    "units_short": "%",
    "seasonal_adjustment": "Not Seasonally Adjusted",
    "seasonal_adjustment_short": "NSA",
    "last_updated": "2021-08-06 14:33:02-05",
    "popularity": 42,
    "group_popularity": 42,
    "notes": "BEA Account Code: W270RE\n\nFor more information about this series, please see http://www.bea.gov/national/.",
    "path": "../Database/National Accounts/National Income & Product Accounts/GDP - GNP/Shares of GDP"
  },
  "W271RE1A156NBEA": {
    "id": "W271RE1A156NBEA",
    "realtime_start": "2022-04-05",
    "realtime_end": "2022-04-05",
    "title": "Shares of gross domestic income: Net operating surplus",
    "observation_start": "1959-01-01",
    "observation_end": "2020-01-01",
    "frequency": "Annual",
    "frequency_short": "A",
    "units": "Percent",
    "units_short": "%",
    "seasonal_adjustment": "Not Seasonally Adjusted",
    "seasonal_adjustment_short": "NSA",
    "last_updated": "2021-08-06 14:33:07-05",
    "popularity": 6,
    "group_popularity": 6,
    "notes": "BEA Account Code: W271RE\n\nFor more information about this series, please see http://www.bea.gov/national/.",
    "path": "../Database/National Accounts/National Income & Product Accounts/GDP - GNP/Shares of GDP"
  },
  "W272RE1A156NBEA": {
    "id": "W272RE1A156NBEA",
    "realtime_start": "2022-04-05",
    "realtime_end": "2022-04-05",
    "title": "Shares of gross domestic income: Net operating surplus: Private enterprises: Net interest and miscellaneous payments, domestic industries",
    "observation_start": "1929-01-01",
    "observation_end": "2020-01-01",
    "frequency": "Annual",
    "frequency_short": "A",
    "units": "Percent",
    "units_short": "%",
    "seasonal_adjustment": "Not Seasonally Adjusted",
    "seasonal_adjustment_short": "NSA",
    "last_updated": "2021-08-06 14:36:11-05",
    "popularity": 1,
    "group_popularity": 1,
    "notes": "BEA Account Code: W272RE\n\nFor more information about this series, please see http://www.bea.gov/national/.",
    "path": "../Database/National Accounts/National Income & Product Accounts/GDP - GNP/Shares of GDP"
  },
  "W273RE1A156NBEA": {
    "id": "W273RE1A156NBEA",
    "realtime_start": "2022-04-05",
    "realtime_end": "2022-04-05",
    "title": "Shares of gross domestic income: Corporate profits with inventory valuation and capital consumption adjustments, domestic industries: Profits after tax with inventory valuation and capital consumption adjustments",
    "observation_start": "1929-01-01",
    "observation_end": "2020-01-01",
    "frequency": "Annual",
    "frequency_short": "A",
    "units": "Percent",
    "units_short": "%",
    "seasonal_adjustment": "Not Seasonally Adjusted",
    "seasonal_adjustment_short": "NSA",
    "last_updated": "2021-08-06 14:33:03-05",
    "popularity": 34,
    "group_popularity": 34,
    "notes": "BEA Account Code: W273RE\n\nFor more information about this series, please see http://www.bea.gov/national/.",
    "path": "../Database/National Accounts/National Income & Product Accounts/GDP - GNP/Shares of GDP"
  },
  "W274RE1A156NBEA": {
    "id": "W274RE1A156NBEA",
    "realtime_start": "2022-04-05",
    "realtime_end": "2022-04-05",
    "title": "Shares of gross domestic income: Profits after tax with inventory valuation and capital consumption adjustments: Undistributed corporate profits with inventory valuation and capital consumption adjustments",
    "observation_start": "1929-01-01",
    "observation_end": "2020-01-01",
    "frequency": "Annual",
    "frequency_short": "A",
    "units": "Percent",
    "units_short": "%",
    "seasonal_adjustment": "Not Seasonally Adjusted",
    "seasonal_adjustment_short": "NSA",
    "last_updated": "2021-08-06 14:33:08-05",
    "popularity": 6,
    "group_popularity": 6,
    "notes": "BEA Account Code: W274RE\n\nFor more information about this series, please see http://www.bea.gov/national/.",
    "path": "../Database/National Accounts/National Income & Product Accounts/GDP - GNP/Shares of GDP"
  }
}