{
  "Saudi Arabia": {
    "id": "SAUXTNTVA01NCMLQ",
    "realtime_start": "2022-04-06",
    "realtime_end": "2022-04-06",
    "title": "International Trade: Net trade: Value (goods): Total for Saudi Arabia",
    "observation_start": "2006-01-01",
    "observation_end": "2021-10-01",
    "frequency": "Quarterly",
    "frequency_short": "Q",
    "units": "National currency, monthly level",
    "units_short": "National currency, monthly level",
    "seasonal_adjustment": "Not Seasonally Adjusted",
    "seasonal_adjustment_short": "NSA",
    "last_updated": "2022-03-10 10:34:34-06",
    "popularity": 1,
    "group_popularity": 3,
    "notes": "OECD descriptor ID: XTNTVA01 OECD unit ID: NCML OECD country ID: SAU All OECD data should be cited as follows: OECD,\"Main Economic Indicators - complete database\"Main Economic Indicators(database)http://dx.doi.org/10.1787/data-00052-en(Accessed on date)Copyright, 2016, OECD. Reprinted with permission.",
    "path": "../Database/International Data/Countries/Saudi Arabia"
  },
  "Argentina": {
    "id": "ARGXTNTVA01STSAQ",
    "realtime_start": "2022-04-06",
    "realtime_end": "2022-04-06",
    "title": "International Trade: Net trade: Value (goods): Total for Argentina",
    "observation_start": "2004-01-01",
    "observation_end": "2021-07-01",
    "frequency": "Quarterly",
    "frequency_short": "Q",
    "units": "Percent",
    "units_short": "%",
    "seasonal_adjustment": "Seasonally Adjusted",
    "seasonal_adjustment_short": "SA",
    "last_updated": "2022-03-10 10:58:07-06",
    "popularity": 1,
    "group_popularity": 10,
    "notes": "OECD descriptor ID: XTNTVA01 OECD unit ID: STSA OECD country ID: ARG All OECD data should be cited as follows: OECD,\"Main Economic Indicators - complete database\"Main Economic Indicators(database)http://dx.doi.org/10.1787/data-00052-en(Accessed on date)Copyright, 2016, OECD. Reprinted with permission.",
    "path": "../Database/International Data/Countries/Argentina"
  },
  "Belgium": {
    "id": "BELXTNTVA01STSAQ",
    "realtime_start": "2022-04-06",
    "realtime_end": "2022-04-06",
    "title": "International Trade: Net trade: Value (goods): Total for Belgium",
    "observation_start": "1995-01-01",
    "observation_end": "2021-10-01",
    "frequency": "Quarterly",
    "frequency_short": "Q",
    "units": "Percent",
    "units_short": "%",
    "seasonal_adjustment": "Seasonally Adjusted",
    "seasonal_adjustment_short": "SA",
    "last_updated": "2022-03-10 10:57:58-06",
    "popularity": 1,
    "group_popularity": 1,
    "notes": "OECD descriptor ID: XTNTVA01 OECD unit ID: STSA OECD country ID: BEL All OECD data should be cited as follows: OECD,\"Main Economic Indicators - complete database\"Main Economic Indicators(database)http://dx.doi.org/10.1787/data-00052-en(Accessed on date)Copyright, 2016, OECD. Reprinted with permission.",
    "path": "../Database/International Data/Countries/Belgium"
  },
  "Brazil": {
    "id": "BRAXTNTVA01STSAQ",
    "realtime_start": "2022-04-06",
    "realtime_end": "2022-04-06",
    "title": "International Trade: Net trade: Value (goods): Total for Brazil",
    "observation_start": "1996-01-01",
    "observation_end": "2021-10-01",
    "frequency": "Quarterly",
    "frequency_short": "Q",
    "units": "Percent",
    "units_short": "%",
    "seasonal_adjustment": "Seasonally Adjusted",
    "seasonal_adjustment_short": "SA",
    "last_updated": "2022-03-10 10:57:57-06",
    "popularity": 1,
    "group_popularity": 1,
    "notes": "OECD descriptor ID: XTNTVA01 OECD unit ID: STSA OECD country ID: BRA All OECD data should be cited as follows: OECD,\"Main Economic Indicators - complete database\"Main Economic Indicators(database)http://dx.doi.org/10.1787/data-00052-en(Accessed on date)Copyright, 2016, OECD. Reprinted with permission.",
    "path": "../Database/International Data/Countries/Brazil"
  },
  "Canada": {
    "id": "CANXTNTVA01STSAQ",
    "realtime_start": "2022-04-06",
    "realtime_end": "2022-04-06",
    "title": "International Trade: Net trade: Value (goods): Total for Canada",
    "observation_start": "1961-01-01",
    "observation_end": "2021-10-01",
    "frequency": "Quarterly",
    "frequency_short": "Q",
    "units": "Percent",
    "units_short": "%",
    "seasonal_adjustment": "Seasonally Adjusted",
    "seasonal_adjustment_short": "SA",
    "last_updated": "2022-03-10 10:56:51-06",
    "popularity": 1,
    "group_popularity": 3,
    "notes": "OECD descriptor ID: XTNTVA01 OECD unit ID: STSA OECD country ID: CAN All OECD data should be cited as follows: OECD,\"Main Economic Indicators - complete database\"Main Economic Indicators(database)http://dx.doi.org/10.1787/data-00052-en(Accessed on date)Copyright, 2016, OECD. Reprinted with permission.",
    "path": "../Database/International Data/Countries/Canada"
  },
  "Chile": {
    "id": "CHLXTNTVA01STSAQ",
    "realtime_start": "2022-04-06",
    "realtime_end": "2022-04-06",
    "title": "International Trade: Net trade: Value (goods): Total for Chile",
    "observation_start": "1996-01-01",
    "observation_end": "2021-07-01",
    "frequency": "Quarterly",
    "frequency_short": "Q",
    "units": "Percent",
    "units_short": "%",
    "seasonal_adjustment": "Seasonally Adjusted",
    "seasonal_adjustment_short": "SA",
    "last_updated": "2022-02-15 11:26:56-06",
    "popularity": 0,
    "group_popularity": 1,
    "notes": "OECD descriptor ID: XTNTVA01 OECD unit ID: STSA OECD country ID: CHL All OECD data should be cited as follows: OECD,\"Main Economic Indicators - complete database\"Main Economic Indicators(database)http://dx.doi.org/10.1787/data-00052-en(Accessed on date)Copyright, 2016, OECD. Reprinted with permission.",
    "path": "../Database/International Data/Countries/Chile"
  },
  "Colombia": {
    "id": "COLXTNTVA01STSAQ",
    "realtime_start": "2022-04-06",
    "realtime_end": "2022-04-06",
    "title": "International Trade: Net trade: Value (goods): Total for Colombia",
    "observation_start": "2005-01-01",
    "observation_end": "2021-10-01",
    "frequency": "Quarterly",
    "frequency_short": "Q",
    "units": "Percent",
    "units_short": "%",
    "seasonal_adjustment": "Seasonally Adjusted",
    "seasonal_adjustment_short": "SA",
    "last_updated": "2022-03-10 12:14:19-06",
    "popularity": 0,
    "group_popularity": 1,
    "notes": "OECD descriptor ID: XTNTVA01 OECD unit ID: STSA OECD country ID: COL All OECD data should be cited as follows: OECD,\"Main Economic Indicators - complete database\"Main Economic Indicators(database)http://dx.doi.org/10.1787/data-00052-en(Accessed on date)Copyright, 2016, OECD. Reprinted with permission.",
    "path": "../Database/International Data/Countries/Colombia"
  },
  "Costa Rica": {
    "id": "CRIXTNTVA01STSAQ",
    "realtime_start": "2022-04-06",
    "realtime_end": "2022-04-06",
    "title": "International Trade: Net trade: Value (goods): Total for Costa Rica",
    "observation_start": "1995-01-01",
    "observation_end": "2021-07-01",
    "frequency": "Quarterly",
    "frequency_short": "Q",
    "units": "Percent",
    "units_short": "%",
    "seasonal_adjustment": "Seasonally Adjusted",
    "seasonal_adjustment_short": "SA",
    "last_updated": "2022-02-15 11:26:55-06",
    "popularity": 0,
    "group_popularity": 1,
    "notes": "OECD descriptor ID: XTNTVA01 OECD unit ID: STSA OECD country ID: CRI All OECD data should be cited as follows: OECD,\"Main Economic Indicators - complete database\"Main Economic Indicators(database)http://dx.doi.org/10.1787/data-00052-en(Accessed on date)Copyright, 2016, OECD. Reprinted with permission.",
    "path": "../Database/International Data/Countries/Costa Rica"
  },
  "Estonia": {
    "id": "ESTXTNTVA01STSAQ",
    "realtime_start": "2022-04-06",
    "realtime_end": "2022-04-06",
    "title": "International Trade: Net trade: Value (goods): Total for Estonia",
    "observation_start": "1995-01-01",
    "observation_end": "2021-10-01",
    "frequency": "Quarterly",
    "frequency_short": "Q",
    "units": "Percent",
    "units_short": "%",
    "seasonal_adjustment": "Seasonally Adjusted",
    "seasonal_adjustment_short": "SA",
    "last_updated": "2022-03-10 10:53:53-06",
    "popularity": 1,
    "group_popularity": 1,
    "notes": "OECD descriptor ID: XTNTVA01 OECD unit ID: STSA OECD country ID: EST All OECD data should be cited as follows: OECD,\"Main Economic Indicators - complete database\"Main Economic Indicators(database)http://dx.doi.org/10.1787/data-00052-en(Accessed on date)Copyright, 2016, OECD. Reprinted with permission.",
    "path": "../Database/International Data/Countries/Estonia"
  },
  "Iceland": {
    "id": "ISLXTNTVA01STSAQ",
    "realtime_start": "2022-04-06",
    "realtime_end": "2022-04-06",
    "title": "International Trade: Net trade: Value (goods): Total for Iceland",
    "observation_start": "1995-01-01",
    "observation_end": "2021-10-01",
    "frequency": "Quarterly",
    "frequency_short": "Q",
    "units": "Percent",
    "units_short": "%",
    "seasonal_adjustment": "Seasonally Adjusted",
    "seasonal_adjustment_short": "SA",
    "last_updated": "2022-03-10 12:10:56-06",
    "popularity": 0,
    "group_popularity": 1,
    "notes": "OECD descriptor ID: XTNTVA01 OECD unit ID: STSA OECD country ID: ISL All OECD data should be cited as follows: OECD,\"Main Economic Indicators - complete database\"Main Economic Indicators(database)http://dx.doi.org/10.1787/data-00052-en(Accessed on date)Copyright, 2016, OECD. Reprinted with permission.",
    "path": "../Database/International Data/Countries/Iceland"
  },
  "Israel": {
    "id": "ISRXTNTVA01STSAQ",
    "realtime_start": "2022-04-06",
    "realtime_end": "2022-04-06",
    "title": "International Trade: Net trade: Value (goods): Total for Israel",
    "observation_start": "1995-01-01",
    "observation_end": "2021-10-01",
    "frequency": "Quarterly",
    "frequency_short": "Q",
    "units": "Percent",
    "units_short": "%",
    "seasonal_adjustment": "Seasonally Adjusted",
    "seasonal_adjustment_short": "SA",
    "last_updated": "2022-03-10 12:10:56-06",
    "popularity": 0,
    "group_popularity": 1,
    "notes": "OECD descriptor ID: XTNTVA01 OECD unit ID: STSA OECD country ID: ISR All OECD data should be cited as follows: OECD,\"Main Economic Indicators - complete database\"Main Economic Indicators(database)http://dx.doi.org/10.1787/data-00052-en(Accessed on date)Copyright, 2016, OECD. Reprinted with permission.",
    "path": "../Database/International Data/Countries/Israel"
  },
  "Switzerland": {
    "id": "CHEXTNTVA01STSAQ",
    "realtime_start": "2022-04-06",
    "realtime_end": "2022-04-06",
    "title": "International Trade: Net trade: Value (goods): Total for Switzerland",
    "observation_start": "1980-01-01",
    "observation_end": "2021-10-01",
    "frequency": "Quarterly",
    "frequency_short": "Q",
    "units": "Percent",
    "units_short": "%",
    "seasonal_adjustment": "Seasonally Adjusted",
    "seasonal_adjustment_short": "SA",
    "last_updated": "2022-03-10 12:14:31-06",
    "popularity": 0,
    "group_popularity": 1,
    "notes": "OECD descriptor ID: XTNTVA01 OECD unit ID: STSA OECD country ID: CHE All OECD data should be cited as follows: OECD,\"Main Economic Indicators - complete database\"Main Economic Indicators(database)http://dx.doi.org/10.1787/data-00052-en(Accessed on date)Copyright, 2016, OECD. Reprinted with permission.",
    "path": "../Database/International Data/Countries/Switzerland"
  }
}