{
  "OECDECP010000GPM": {
    "id": "OECDECP010000GPM",
    "realtime_start": "2022-04-06",
    "realtime_end": "2022-04-06",
    "title": "Consumer Price Index: Food and non-Alcoholic beverages (COICOP 01): Total: Total for OECD - Europe",
    "observation_start": "1970-02-01",
    "observation_end": "2022-01-01",
    "frequency": "Monthly",
    "frequency_short": "M",
    "units": "Growth rate previous period",
    "units_short": "Growth rate previous period",
    "seasonal_adjustment": "Not Seasonally Adjusted",
    "seasonal_adjustment_short": "NSA",
    "last_updated": "2022-03-10 11:06:04-06",
    "popularity": 1,
    "group_popularity": 1,
    "notes": "OECD descriptor ID: CP010000 OECD unit ID: GP OECD country ID: OECDE All OECD data should be cited as follows: OECD,\"Main Economic Indicators - complete database\"Main Economic Indicators(database)http://dx.doi.org/10.1787/data-00052-en(Accessed on date)Copyright, 2016, OECD. Reprinted with permission.",
    "path": "../Database/International Data/Institutions/OECD - Europe"
  },
  "OECDECP010000GPQ": {
    "id": "OECDECP010000GPQ",
    "realtime_start": "2022-04-06",
    "realtime_end": "2022-04-06",
    "title": "Consumer Price Index: Food and non-Alcoholic beverages (COICOP 01): Total: Total for OECD - Europe",
    "observation_start": "1970-04-01",
    "observation_end": "2021-10-01",
    "frequency": "Quarterly",
    "frequency_short": "Q",
    "units": "Growth rate previous period",
    "units_short": "Growth rate previous period",
    "seasonal_adjustment": "Not Seasonally Adjusted",
    "seasonal_adjustment_short": "NSA",
    "last_updated": "2022-03-10 10:35:42-06",
    "popularity": 0,
    "group_popularity": 1,
    "notes": "OECD descriptor ID: CP010000 OECD unit ID: GP OECD country ID: OECDE All OECD data should be cited as follows: OECD,\"Main Economic Indicators - complete database\"Main Economic Indicators(database)http://dx.doi.org/10.1787/data-00052-en(Accessed on date)Copyright, 2016, OECD. Reprinted with permission.",
    "path": "../Database/International Data/Institutions/OECD - Europe"
  },
  "OECDECP010000GYM": {
    "id": "OECDECP010000GYM",
    "realtime_start": "2022-04-06",
    "realtime_end": "2022-04-06",
    "title": "Consumer Price Index: Food and non-Alcoholic beverages (COICOP 01): Total: Total for OECD - Europe",
    "observation_start": "1971-01-01",
    "observation_end": "2022-01-01",
    "frequency": "Monthly",
    "frequency_short": "M",
    "units": "Growth rate same period previous year",
    "units_short": "Growth rate same period previous Yr.",
    "seasonal_adjustment": "Not Seasonally Adjusted",
    "seasonal_adjustment_short": "NSA",
    "last_updated": "2022-03-10 11:06:04-06",
    "popularity": 1,
    "group_popularity": 1,
    "notes": "OECD descriptor ID: CP010000 OECD unit ID: GY OECD country ID: OECDE All OECD data should be cited as follows: OECD,\"Main Economic Indicators - complete database\"Main Economic Indicators(database)http://dx.doi.org/10.1787/data-00052-en(Accessed on date)Copyright, 2016, OECD. Reprinted with permission.",
    "path": "../Database/International Data/Institutions/OECD - Europe"
  },
  "OECDECP010000GYQ": {
    "id": "OECDECP010000GYQ",
    "realtime_start": "2022-04-06",
    "realtime_end": "2022-04-06",
    "title": "Consumer Price Index: Food and non-Alcoholic beverages (COICOP 01): Total: Total for OECD - Europe",
    "observation_start": "1971-01-01",
    "observation_end": "2021-10-01",
    "frequency": "Quarterly",
    "frequency_short": "Q",
    "units": "Growth rate same period previous year",
    "units_short": "Growth rate same period previous Yr.",
    "seasonal_adjustment": "Not Seasonally Adjusted",
    "seasonal_adjustment_short": "NSA",
    "last_updated": "2022-03-10 10:35:41-06",
    "popularity": 0,
    "group_popularity": 1,
    "notes": "OECD descriptor ID: CP010000 OECD unit ID: GY OECD country ID: OECDE All OECD data should be cited as follows: OECD,\"Main Economic Indicators - complete database\"Main Economic Indicators(database)http://dx.doi.org/10.1787/data-00052-en(Accessed on date)Copyright, 2016, OECD. Reprinted with permission.",
    "path": "../Database/International Data/Institutions/OECD - Europe"
  },
  "OECDECP010000IXNBM": {
    "id": "OECDECP010000IXNBM",
    "realtime_start": "2022-04-06",
    "realtime_end": "2022-04-06",
    "title": "Consumer Price Index: Food and non-Alcoholic beverages (COICOP 01): Total: Total for OECD - Europe",
    "observation_start": "1970-01-01",
    "observation_end": "2022-01-01",
    "frequency": "Monthly",
    "frequency_short": "M",
    "units": "Index source base",
    "units_short": "Index source base",
    "seasonal_adjustment": "Not Seasonally Adjusted",
    "seasonal_adjustment_short": "NSA",
    "last_updated": "2022-03-10 11:06:03-06",
    "popularity": 1,
    "group_popularity": 1,
    "notes": "OECD descriptor ID: CP010000 OECD unit ID: IXNB OECD country ID: OECDE All OECD data should be cited as follows: OECD,\"Main Economic Indicators - complete database\"Main Economic Indicators(database)http://dx.doi.org/10.1787/data-00052-en(Accessed on date)Copyright, 2016, OECD. Reprinted with permission.",
    "path": "../Database/International Data/Institutions/OECD - Europe"
  },
  "OECDECP010000IXNBQ": {
    "id": "OECDECP010000IXNBQ",
    "realtime_start": "2022-04-06",
    "realtime_end": "2022-04-06",
    "title": "Consumer Price Index: Food and non-Alcoholic beverages (COICOP 01): Total: Total for OECD - Europe",
    "observation_start": "1970-01-01",
    "observation_end": "2021-10-01",
    "frequency": "Quarterly",
    "frequency_short": "Q",
    "units": "Index source base",
    "units_short": "Index source base",
    "seasonal_adjustment": "Not Seasonally Adjusted",
    "seasonal_adjustment_short": "NSA",
    "last_updated": "2022-03-10 10:35:41-06",
    "popularity": 1,
    "group_popularity": 1,
    "notes": "OECD descriptor ID: CP010000 OECD unit ID: IXNB OECD country ID: OECDE All OECD data should be cited as follows: OECD,\"Main Economic Indicators - complete database\"Main Economic Indicators(database)http://dx.doi.org/10.1787/data-00052-en(Accessed on date)Copyright, 2016, OECD. Reprinted with permission.",
    "path": "../Database/International Data/Institutions/OECD - Europe"
  },
  "OECDECP010000IXOBM": {
    "id": "OECDECP010000IXOBM",
    "realtime_start": "2022-04-06",
    "realtime_end": "2022-04-06",
    "title": "Consumer Price Index: Food and non-Alcoholic beverages (COICOP 01): Total: Total for OECD - Europe",
    "observation_start": "1970-01-01",
    "observation_end": "2022-01-01",
    "frequency": "Monthly",
    "frequency_short": "M",
    "units": "Index 2015=100",
    "units_short": "Index 2015=100",
    "seasonal_adjustment": "Not Seasonally Adjusted",
    "seasonal_adjustment_short": "NSA",
    "last_updated": "2022-03-10 11:06:03-06",
    "popularity": 1,
    "group_popularity": 1,
    "notes": "OECD descriptor ID: CP010000 OECD unit ID: IXOB OECD country ID: OECDE All OECD data should be cited as follows: OECD,\"Main Economic Indicators - complete database\"Main Economic Indicators(database)http://dx.doi.org/10.1787/data-00052-en(Accessed on date)Copyright, 2016, OECD. Reprinted with permission.",
    "path": "../Database/International Data/Institutions/OECD - Europe"
  },
  "OECDECP010000IXOBQ": {
    "id": "OECDECP010000IXOBQ",
    "realtime_start": "2022-04-06",
    "realtime_end": "2022-04-06",
    "title": "Consumer Price Index: Food and non-Alcoholic beverages (COICOP 01): Total: Total for OECD - Europe",
    "observation_start": "1970-01-01",
    "observation_end": "2021-10-01",
    "frequency": "Quarterly",
    "frequency_short": "Q",
    "units": "Index 2015=100",
    "units_short": "Index 2015=100",
    "seasonal_adjustment": "Not Seasonally Adjusted",
    "seasonal_adjustment_short": "NSA",
    "last_updated": "2022-03-10 10:35:41-06",
    "popularity": 0,
    "group_popularity": 1,
    "notes": "OECD descriptor ID: CP010000 OECD unit ID: IXOB OECD country ID: OECDE All OECD data should be cited as follows: OECD,\"Main Economic Indicators - complete database\"Main Economic Indicators(database)http://dx.doi.org/10.1787/data-00052-en(Accessed on date)Copyright, 2016, OECD. Reprinted with permission.",
    "path": "../Database/International Data/Institutions/OECD - Europe"
  },
  "OECDECPALTT01GPM": {
    "id": "OECDECPALTT01GPM",
    "realtime_start": "2022-04-06",
    "realtime_end": "2022-04-06",
    "title": "Consumer Price Index: All items: Total: Total for OECD - Europe",
    "observation_start": "1970-02-01",
    "observation_end": "2022-01-01",
    "frequency": "Monthly",
    "frequency_short": "M",
    "units": "Growth rate previous period",
    "units_short": "Growth rate previous period",
    "seasonal_adjustment": "Not Seasonally Adjusted",
    "seasonal_adjustment_short": "NSA",
    "last_updated": "2022-03-10 11:06:02-06",
    "popularity": 1,
    "group_popularity": 3,
    "notes": "OECD descriptor ID: CPALTT01 OECD unit ID: GP OECD country ID: OECDE All OECD data should be cited as follows: OECD,\"Main Economic Indicators - complete database\"Main Economic Indicators(database)http://dx.doi.org/10.1787/data-00052-en(Accessed on date)Copyright, 2016, OECD. Reprinted with permission.",
    "path": "../Database/International Data/Institutions/OECD - Europe"
  },
  "OECDECPALTT01GPQ": {
    "id": "OECDECPALTT01GPQ",
    "realtime_start": "2022-04-06",
    "realtime_end": "2022-04-06",
    "title": "Consumer Price Index: All items: Total: Total for OECD - Europe",
    "observation_start": "1970-04-01",
    "observation_end": "2021-10-01",
    "frequency": "Quarterly",
    "frequency_short": "Q",
    "units": "Growth rate previous period",
    "units_short": "Growth rate previous period",
    "seasonal_adjustment": "Not Seasonally Adjusted",
    "seasonal_adjustment_short": "NSA",
    "last_updated": "2022-03-10 10:35:41-06",
    "popularity": 1,
    "group_popularity": 3,
    "notes": "OECD descriptor ID: CPALTT01 OECD unit ID: GP OECD country ID: OECDE All OECD data should be cited as follows: OECD,\"Main Economic Indicators - complete database\"Main Economic Indicators(database)http://dx.doi.org/10.1787/data-00052-en(Accessed on date)Copyright, 2016, OECD. Reprinted with permission.",
    "path": "../Database/International Data/Institutions/OECD - Europe"
  },
  "OECDECPALTT01GYM": {
    "id": "OECDECPALTT01GYM",
    "realtime_start": "2022-04-06",
    "realtime_end": "2022-04-06",
    "title": "Consumer Price Index: All items: Total: Total for OECD - Europe",
    "observation_start": "1971-01-01",
    "observation_end": "2022-01-01",
    "frequency": "Monthly",
    "frequency_short": "M",
    "units": "Growth rate same period previous year",
    "units_short": "Growth rate same period previous Yr.",
    "seasonal_adjustment": "Not Seasonally Adjusted",
    "seasonal_adjustment_short": "NSA",
    "last_updated": "2022-03-10 11:06:02-06",
    "popularity": 1,
    "group_popularity": 3,
    "notes": "OECD descriptor ID: CPALTT01 OECD unit ID: GY OECD country ID: OECDE All OECD data should be cited as follows: OECD,\"Main Economic Indicators - complete database\"Main Economic Indicators(database)http://dx.doi.org/10.1787/data-00052-en(Accessed on date)Copyright, 2016, OECD. Reprinted with permission.",
    "path": "../Database/International Data/Institutions/OECD - Europe"
  },
  "OECDECPALTT01GYQ": {
    "id": "OECDECPALTT01GYQ",
    "realtime_start": "2022-04-06",
    "realtime_end": "2022-04-06",
    "title": "Consumer Price Index: All items: Total: Total for OECD - Europe",
    "observation_start": "1971-01-01",
    "observation_end": "2021-10-01",
    "frequency": "Quarterly",
    "frequency_short": "Q",
    "units": "Growth rate same period previous year",
    "units_short": "Growth rate same period previous Yr.",
    "seasonal_adjustment": "Not Seasonally Adjusted",
    "seasonal_adjustment_short": "NSA",
    "last_updated": "2022-03-10 10:35:41-06",
    "popularity": 1,
    "group_popularity": 3,
    "notes": "OECD descriptor ID: CPALTT01 OECD unit ID: GY OECD country ID: OECDE All OECD data should be cited as follows: OECD,\"Main Economic Indicators - complete database\"Main Economic Indicators(database)http://dx.doi.org/10.1787/data-00052-en(Accessed on date)Copyright, 2016, OECD. Reprinted with permission.",
    "path": "../Database/International Data/Institutions/OECD - Europe"
  },
  "OECDECPALTT01IXNBM": {
    "id": "OECDECPALTT01IXNBM",
    "realtime_start": "2022-04-06",
    "realtime_end": "2022-04-06",
    "title": "Consumer Price Index: All items: Total: Total for OECD - Europe",
    "observation_start": "1970-01-01",
    "observation_end": "2022-01-01",
    "frequency": "Monthly",
    "frequency_short": "M",
    "units": "Index source base",
    "units_short": "Index source base",
    "seasonal_adjustment": "Not Seasonally Adjusted",
    "seasonal_adjustment_short": "NSA",
    "last_updated": "2022-03-10 11:06:01-06",
    "popularity": 1,
    "group_popularity": 3,
    "notes": "OECD descriptor ID: CPALTT01 OECD unit ID: IXNB OECD country ID: OECDE All OECD data should be cited as follows: OECD,\"Main Economic Indicators - complete database\"Main Economic Indicators(database)http://dx.doi.org/10.1787/data-00052-en(Accessed on date)Copyright, 2016, OECD. Reprinted with permission.",
    "path": "../Database/International Data/Institutions/OECD - Europe"
  },
  "OECDECPALTT01IXNBQ": {
    "id": "OECDECPALTT01IXNBQ",
    "realtime_start": "2022-04-06",
    "realtime_end": "2022-04-06",
    "title": "Consumer Price Index: All items: Total: Total for OECD - Europe",
    "observation_start": "1970-01-01",
    "observation_end": "2021-10-01",
    "frequency": "Quarterly",
    "frequency_short": "Q",
    "units": "Index source base",
    "units_short": "Index source base",
    "seasonal_adjustment": "Not Seasonally Adjusted",
    "seasonal_adjustment_short": "NSA",
    "last_updated": "2022-03-10 10:35:40-06",
    "popularity": 1,
    "group_popularity": 3,
    "notes": "OECD descriptor ID: CPALTT01 OECD unit ID: IXNB OECD country ID: OECDE All OECD data should be cited as follows: OECD,\"Main Economic Indicators - complete database\"Main Economic Indicators(database)http://dx.doi.org/10.1787/data-00052-en(Accessed on date)Copyright, 2016, OECD. Reprinted with permission.",
    "path": "../Database/International Data/Institutions/OECD - Europe"
  },
  "OECDECPALTT01IXOBM": {
    "id": "OECDECPALTT01IXOBM",
    "realtime_start": "2022-04-06",
    "realtime_end": "2022-04-06",
    "title": "Consumer Price Index: All items: Total: Total for OECD - Europe",
    "observation_start": "1970-01-01",
    "observation_end": "2022-01-01",
    "frequency": "Monthly",
    "frequency_short": "M",
    "units": "Index 2015=100",
    "units_short": "Index 2015=100",
    "seasonal_adjustment": "Not Seasonally Adjusted",
    "seasonal_adjustment_short": "NSA",
    "last_updated": "2022-03-10 11:06:01-06",
    "popularity": 1,
    "group_popularity": 3,
    "notes": "OECD descriptor ID: CPALTT01 OECD unit ID: IXOB OECD country ID: OECDE All OECD data should be cited as follows: OECD,\"Main Economic Indicators - complete database\"Main Economic Indicators(database)http://dx.doi.org/10.1787/data-00052-en(Accessed on date)Copyright, 2016, OECD. Reprinted with permission.",
    "path": "../Database/International Data/Institutions/OECD - Europe"
  },
  "OECDECPALTT01IXOBQ": {
    "id": "OECDECPALTT01IXOBQ",
    "realtime_start": "2022-04-06",
    "realtime_end": "2022-04-06",
    "title": "Consumer Price Index: All items: Total: Total for OECD - Europe",
    "observation_start": "1970-01-01",
    "observation_end": "2021-10-01",
    "frequency": "Quarterly",
    "frequency_short": "Q",
    "units": "Index 2015=100",
    "units_short": "Index 2015=100",
    "seasonal_adjustment": "Not Seasonally Adjusted",
    "seasonal_adjustment_short": "NSA",
    "last_updated": "2022-03-10 10:35:40-06",
    "popularity": 1,
    "group_popularity": 3,
    "notes": "OECD descriptor ID: CPALTT01 OECD unit ID: IXOB OECD country ID: OECDE All OECD data should be cited as follows: OECD,\"Main Economic Indicators - complete database\"Main Economic Indicators(database)http://dx.doi.org/10.1787/data-00052-en(Accessed on date)Copyright, 2016, OECD. Reprinted with permission.",
    "path": "../Database/International Data/Institutions/OECD - Europe"
  },
  "OECDECPGREN01GPM": {
    "id": "OECDECPGREN01GPM",
    "realtime_start": "2022-04-06",
    "realtime_end": "2022-04-06",
    "title": "Consumer Price Index: OECD Groups: Energy (Fuel, electricity & gasoline): Total for OECD - Europe",
    "observation_start": "1970-02-01",
    "observation_end": "2022-01-01",
    "frequency": "Monthly",
    "frequency_short": "M",
    "units": "Growth rate previous period",
    "units_short": "Growth rate previous period",
    "seasonal_adjustment": "Not Seasonally Adjusted",
    "seasonal_adjustment_short": "NSA",
    "last_updated": "2022-03-10 11:06:00-06",
    "popularity": 1,
    "group_popularity": 7,
    "notes": "OECD descriptor ID: CPGREN01 OECD unit ID: GP OECD country ID: OECDE All OECD data should be cited as follows: OECD,\"Main Economic Indicators - complete database\"Main Economic Indicators(database)http://dx.doi.org/10.1787/data-00052-en(Accessed on date)Copyright, 2016, OECD. Reprinted with permission.",
    "path": "../Database/International Data/Institutions/OECD - Europe"
  },
  "OECDECPGREN01GPQ": {
    "id": "OECDECPGREN01GPQ",
    "realtime_start": "2022-04-06",
    "realtime_end": "2022-04-06",
    "title": "Consumer Price Index: OECD Groups: Energy (Fuel, electricity & gasoline): Total for OECD - Europe",
    "observation_start": "1970-04-01",
    "observation_end": "2021-10-01",
    "frequency": "Quarterly",
    "frequency_short": "Q",
    "units": "Growth rate previous period",
    "units_short": "Growth rate previous period",
    "seasonal_adjustment": "Not Seasonally Adjusted",
    "seasonal_adjustment_short": "NSA",
    "last_updated": "2022-03-10 10:35:40-06",
    "popularity": 1,
    "group_popularity": 7,
    "notes": "OECD descriptor ID: CPGREN01 OECD unit ID: GP OECD country ID: OECDE All OECD data should be cited as follows: OECD,\"Main Economic Indicators - complete database\"Main Economic Indicators(database)http://dx.doi.org/10.1787/data-00052-en(Accessed on date)Copyright, 2016, OECD. Reprinted with permission.",
    "path": "../Database/International Data/Institutions/OECD - Europe"
  },
  "OECDECPGREN01GYM": {
    "id": "OECDECPGREN01GYM",
    "realtime_start": "2022-04-06",
    "realtime_end": "2022-04-06",
    "title": "Consumer Price Index: OECD Groups: Energy (Fuel, electricity & gasoline): Total for OECD - Europe",
    "observation_start": "1971-01-01",
    "observation_end": "2022-01-01",
    "frequency": "Monthly",
    "frequency_short": "M",
    "units": "Growth rate same period previous year",
    "units_short": "Growth rate same period previous Yr.",
    "seasonal_adjustment": "Not Seasonally Adjusted",
    "seasonal_adjustment_short": "NSA",
    "last_updated": "2022-03-10 10:41:19-06",
    "popularity": 7,
    "group_popularity": 7,
    "notes": "OECD descriptor ID: CPGREN01 OECD unit ID: GY OECD country ID: OECDE All OECD data should be cited as follows: OECD,\"Main Economic Indicators - complete database\"Main Economic Indicators(database)http://dx.doi.org/10.1787/data-00052-en(Accessed on date)Copyright, 2016, OECD. Reprinted with permission.",
    "path": "../Database/International Data/Institutions/OECD - Europe"
  },
  "OECDECPGREN01GYQ": {
    "id": "OECDECPGREN01GYQ",
    "realtime_start": "2022-04-06",
    "realtime_end": "2022-04-06",
    "title": "Consumer Price Index: OECD Groups: Energy (Fuel, electricity & gasoline): Total for OECD - Europe",
    "observation_start": "1971-01-01",
    "observation_end": "2021-10-01",
    "frequency": "Quarterly",
    "frequency_short": "Q",
    "units": "Growth rate same period previous year",
    "units_short": "Growth rate same period previous Yr.",
    "seasonal_adjustment": "Not Seasonally Adjusted",
    "seasonal_adjustment_short": "NSA",
    "last_updated": "2022-03-10 10:35:39-06",
    "popularity": 1,
    "group_popularity": 7,
    "notes": "OECD descriptor ID: CPGREN01 OECD unit ID: GY OECD country ID: OECDE All OECD data should be cited as follows: OECD,\"Main Economic Indicators - complete database\"Main Economic Indicators(database)http://dx.doi.org/10.1787/data-00052-en(Accessed on date)Copyright, 2016, OECD. Reprinted with permission.",
    "path": "../Database/International Data/Institutions/OECD - Europe"
  },
  "OECDECPGREN01IXOBM": {
    "id": "OECDECPGREN01IXOBM",
    "realtime_start": "2022-04-06",
    "realtime_end": "2022-04-06",
    "title": "Consumer Price Index: OECD Groups: Energy (Fuel, electricity & gasoline): Total for OECD - Europe",
    "observation_start": "1970-01-01",
    "observation_end": "2022-01-01",
    "frequency": "Monthly",
    "frequency_short": "M",
    "units": "Index 2015=100",
    "units_short": "Index 2015=100",
    "seasonal_adjustment": "Not Seasonally Adjusted",
    "seasonal_adjustment_short": "NSA",
    "last_updated": "2022-03-10 11:06:00-06",
    "popularity": 1,
    "group_popularity": 7,
    "notes": "OECD descriptor ID: CPGREN01 OECD unit ID: IXOB OECD country ID: OECDE All OECD data should be cited as follows: OECD,\"Main Economic Indicators - complete database\"Main Economic Indicators(database)http://dx.doi.org/10.1787/data-00052-en(Accessed on date)Copyright, 2016, OECD. Reprinted with permission.",
    "path": "../Database/International Data/Institutions/OECD - Europe"
  },
  "OECDECPGREN01IXOBQ": {
    "id": "OECDECPGREN01IXOBQ",
    "realtime_start": "2022-04-06",
    "realtime_end": "2022-04-06",
    "title": "Consumer Price Index: OECD Groups: Energy (Fuel, electricity & gasoline): Total for OECD - Europe",
    "observation_start": "1970-01-01",
    "observation_end": "2021-10-01",
    "frequency": "Quarterly",
    "frequency_short": "Q",
    "units": "Index 2015=100",
    "units_short": "Index 2015=100",
    "seasonal_adjustment": "Not Seasonally Adjusted",
    "seasonal_adjustment_short": "NSA",
    "last_updated": "2022-03-10 10:35:39-06",
    "popularity": 0,
    "group_popularity": 7,
    "notes": "OECD descriptor ID: CPGREN01 OECD unit ID: IXOB OECD country ID: OECDE All OECD data should be cited as follows: OECD,\"Main Economic Indicators - complete database\"Main Economic Indicators(database)http://dx.doi.org/10.1787/data-00052-en(Accessed on date)Copyright, 2016, OECD. Reprinted with permission.",
    "path": "../Database/International Data/Institutions/OECD - Europe"
  },
  "OECDECPGRLE01GPM": {
    "id": "OECDECPGRLE01GPM",
    "realtime_start": "2022-04-06",
    "realtime_end": "2022-04-06",
    "title": "Consumer Price Index: OECD Groups: All items non-food non-energy: Total for OECD - Europe",
    "observation_start": "1970-02-01",
    "observation_end": "2022-01-01",
    "frequency": "Monthly",
    "frequency_short": "M",
    "units": "Growth rate previous period",
    "units_short": "Growth rate previous period",
    "seasonal_adjustment": "Not Seasonally Adjusted",
    "seasonal_adjustment_short": "NSA",
    "last_updated": "2022-03-10 11:05:59-06",
    "popularity": 1,
    "group_popularity": 1,
    "notes": "OECD descriptor ID: CPGRLE01 OECD unit ID: GP OECD country ID: OECDE All OECD data should be cited as follows: OECD,\"Main Economic Indicators - complete database\"Main Economic Indicators(database)http://dx.doi.org/10.1787/data-00052-en(Accessed on date)Copyright, 2016, OECD. Reprinted with permission.",
    "path": "../Database/International Data/Institutions/OECD - Europe"
  },
  "OECDECPGRLE01GPQ": {
    "id": "OECDECPGRLE01GPQ",
    "realtime_start": "2022-04-06",
    "realtime_end": "2022-04-06",
    "title": "Consumer Price Index: OECD Groups: All items non-food non-energy: Total for OECD - Europe",
    "observation_start": "1970-04-01",
    "observation_end": "2021-10-01",
    "frequency": "Quarterly",
    "frequency_short": "Q",
    "units": "Growth rate previous period",
    "units_short": "Growth rate previous period",
    "seasonal_adjustment": "Not Seasonally Adjusted",
    "seasonal_adjustment_short": "NSA",
    "last_updated": "2022-03-10 12:07:36-06",
    "popularity": 0,
    "group_popularity": 1,
    "notes": "OECD descriptor ID: CPGRLE01 OECD unit ID: GP OECD country ID: OECDE All OECD data should be cited as follows: OECD,\"Main Economic Indicators - complete database\"Main Economic Indicators(database)http://dx.doi.org/10.1787/data-00052-en(Accessed on date)Copyright, 2016, OECD. Reprinted with permission.",
    "path": "../Database/International Data/Institutions/OECD - Europe"
  },
  "OECDECPGRLE01GYM": {
    "id": "OECDECPGRLE01GYM",
    "realtime_start": "2022-04-06",
    "realtime_end": "2022-04-06",
    "title": "Consumer Price Index: OECD Groups: All items non-food non-energy: Total for OECD - Europe",
    "observation_start": "1971-01-01",
    "observation_end": "2022-01-01",
    "frequency": "Monthly",
    "frequency_short": "M",
    "units": "Growth rate same period previous year",
    "units_short": "Growth rate same period previous Yr.",
    "seasonal_adjustment": "Not Seasonally Adjusted",
    "seasonal_adjustment_short": "NSA",
    "last_updated": "2022-03-10 11:05:59-06",
    "popularity": 1,
    "group_popularity": 1,
    "notes": "OECD descriptor ID: CPGRLE01 OECD unit ID: GY OECD country ID: OECDE All OECD data should be cited as follows: OECD,\"Main Economic Indicators - complete database\"Main Economic Indicators(database)http://dx.doi.org/10.1787/data-00052-en(Accessed on date)Copyright, 2016, OECD. Reprinted with permission.",
    "path": "../Database/International Data/Institutions/OECD - Europe"
  },
  "OECDECPGRLE01GYQ": {
    "id": "OECDECPGRLE01GYQ",
    "realtime_start": "2022-04-06",
    "realtime_end": "2022-04-06",
    "title": "Consumer Price Index: OECD Groups: All items non-food non-energy: Total for OECD - Europe",
    "observation_start": "1971-01-01",
    "observation_end": "2021-10-01",
    "frequency": "Quarterly",
    "frequency_short": "Q",
    "units": "Growth rate same period previous year",
    "units_short": "Growth rate same period previous Yr.",
    "seasonal_adjustment": "Not Seasonally Adjusted",
    "seasonal_adjustment_short": "NSA",
    "last_updated": "2022-03-10 12:07:36-06",
    "popularity": 0,
    "group_popularity": 1,
    "notes": "OECD descriptor ID: CPGRLE01 OECD unit ID: GY OECD country ID: OECDE All OECD data should be cited as follows: OECD,\"Main Economic Indicators - complete database\"Main Economic Indicators(database)http://dx.doi.org/10.1787/data-00052-en(Accessed on date)Copyright, 2016, OECD. Reprinted with permission.",
    "path": "../Database/International Data/Institutions/OECD - Europe"
  },
  "OECDECPGRLE01IXOBM": {
    "id": "OECDECPGRLE01IXOBM",
    "realtime_start": "2022-04-06",
    "realtime_end": "2022-04-06",
    "title": "Consumer Price Index: OECD Groups: All items non-food non-energy: Total for OECD - Europe",
    "observation_start": "1970-01-01",
    "observation_end": "2022-01-01",
    "frequency": "Monthly",
    "frequency_short": "M",
    "units": "Index 2015=100",
    "units_short": "Index 2015=100",
    "seasonal_adjustment": "Not Seasonally Adjusted",
    "seasonal_adjustment_short": "NSA",
    "last_updated": "2022-03-10 11:05:59-06",
    "popularity": 1,
    "group_popularity": 1,
    "notes": "OECD descriptor ID: CPGRLE01 OECD unit ID: IXOB OECD country ID: OECDE All OECD data should be cited as follows: OECD,\"Main Economic Indicators - complete database\"Main Economic Indicators(database)http://dx.doi.org/10.1787/data-00052-en(Accessed on date)Copyright, 2016, OECD. Reprinted with permission.",
    "path": "../Database/International Data/Institutions/OECD - Europe"
  },
  "OECDECPGRLE01IXOBQ": {
    "id": "OECDECPGRLE01IXOBQ",
    "realtime_start": "2022-04-06",
    "realtime_end": "2022-04-06",
    "title": "Consumer Price Index: OECD Groups: All items non-food non-energy: Total for OECD - Europe",
    "observation_start": "1970-01-01",
    "observation_end": "2021-10-01",
    "frequency": "Quarterly",
    "frequency_short": "Q",
    "units": "Index 2015=100",
    "units_short": "Index 2015=100",
    "seasonal_adjustment": "Not Seasonally Adjusted",
    "seasonal_adjustment_short": "NSA",
    "last_updated": "2022-03-10 12:07:35-06",
    "popularity": 0,
    "group_popularity": 1,
    "notes": "OECD descriptor ID: CPGRLE01 OECD unit ID: IXOB OECD country ID: OECDE All OECD data should be cited as follows: OECD,\"Main Economic Indicators - complete database\"Main Economic Indicators(database)http://dx.doi.org/10.1787/data-00052-en(Accessed on date)Copyright, 2016, OECD. Reprinted with permission.",
    "path": "../Database/International Data/Institutions/OECD - Europe"
  },
  "OECDECSCICP03IXNSAM": {
    "id": "OECDECSCICP03IXNSAM",
    "realtime_start": "2022-04-06",
    "realtime_end": "2022-04-06",
    "title": "Consumer opinion surveys: Confidence indicators: Composite indicators: OECD Indicator for OECD - Europe",
    "observation_start": "1974-01-01",
    "observation_end": "2022-02-01",
    "frequency": "Monthly",
    "frequency_short": "M",
    "units": "Normalised, seasonally adjusted (normal = 100)",
    "units_short": "Normalised, seasonally adjusted (normal = 100)",
    "seasonal_adjustment": "Seasonally Adjusted",
    "seasonal_adjustment_short": "SA",
    "last_updated": "2022-03-10 11:05:58-06",
    "popularity": 1,
    "group_popularity": 1,
    "notes": "OECD descriptor ID: CSCICP03 OECD unit ID: IXNSA OECD country ID: OECDE All OECD data should be cited as follows: OECD,\"Main Economic Indicators - complete database\"Main Economic Indicators(database)http://dx.doi.org/10.1787/data-00052-en(Accessed on date)Copyright, 2016, OECD. Reprinted with permission.",
    "path": "../Database/International Data/Institutions/OECD - Europe"
  },
  "OECDELCEAMN01GPSAQ": {
    "id": "OECDELCEAMN01GPSAQ",
    "realtime_start": "2022-04-06",
    "realtime_end": "2022-04-06",
    "title": "Labour Compensation: Earnings: Manufacturing: Hourly for OECD - Europe",
    "observation_start": "1989-04-01",
    "observation_end": "2021-07-01",
    "frequency": "Quarterly",
    "frequency_short": "Q",
    "units": "Growth rate previous period",
    "units_short": "Growth rate previous period",
    "seasonal_adjustment": "Seasonally Adjusted",
    "seasonal_adjustment_short": "SA",
    "last_updated": "2022-03-10 10:35:39-06",
    "popularity": 1,
    "group_popularity": 1,
    "notes": "OECD descriptor ID: LCEAMN01 OECD unit ID: GPSA OECD country ID: OECDE All OECD data should be cited as follows: OECD,\"Main Economic Indicators - complete database\"Main Economic Indicators(database)http://dx.doi.org/10.1787/data-00052-en(Accessed on date)Copyright, 2016, OECD. Reprinted with permission.",
    "path": "../Database/International Data/Institutions/OECD - Europe"
  },
  "OECDELCEAMN01GYSAQ": {
    "id": "OECDELCEAMN01GYSAQ",
    "realtime_start": "2022-04-06",
    "realtime_end": "2022-04-06",
    "title": "Labour Compensation: Earnings: Manufacturing: Hourly for OECD - Europe",
    "observation_start": "1990-01-01",
    "observation_end": "2021-07-01",
    "frequency": "Quarterly",
    "frequency_short": "Q",
    "units": "Growth rate same period previous year",
    "units_short": "Growth rate same period previous Yr.",
    "seasonal_adjustment": "Seasonally Adjusted",
    "seasonal_adjustment_short": "SA",
    "last_updated": "2022-03-10 10:35:39-06",
    "popularity": 1,
    "group_popularity": 1,
    "notes": "OECD descriptor ID: LCEAMN01 OECD unit ID: GYSA OECD country ID: OECDE All OECD data should be cited as follows: OECD,\"Main Economic Indicators - complete database\"Main Economic Indicators(database)http://dx.doi.org/10.1787/data-00052-en(Accessed on date)Copyright, 2016, OECD. Reprinted with permission.",
    "path": "../Database/International Data/Institutions/OECD - Europe"
  },
  "OECDELCEAMN01IXOBSAQ": {
    "id": "OECDELCEAMN01IXOBSAQ",
    "realtime_start": "2022-04-06",
    "realtime_end": "2022-04-06",
    "title": "Labour Compensation: Earnings: Manufacturing: Hourly for OECD - Europe",
    "observation_start": "1989-01-01",
    "observation_end": "2021-07-01",
    "frequency": "Quarterly",
    "frequency_short": "Q",
    "units": "Index 2015=100",
    "units_short": "Index 2015=100",
    "seasonal_adjustment": "Seasonally Adjusted",
    "seasonal_adjustment_short": "SA",
    "last_updated": "2022-03-10 10:35:38-06",
    "popularity": 1,
    "group_popularity": 1,
    "notes": "OECD descriptor ID: LCEAMN01 OECD unit ID: IXOBSA OECD country ID: OECDE All OECD data should be cited as follows: OECD,\"Main Economic Indicators - complete database\"Main Economic Indicators(database)http://dx.doi.org/10.1787/data-00052-en(Accessed on date)Copyright, 2016, OECD. Reprinted with permission.",
    "path": "../Database/International Data/Institutions/OECD - Europe"
  },
  "OECDELOLITOAASTSAM": {
    "id": "OECDELOLITOAASTSAM",
    "realtime_start": "2022-04-06",
    "realtime_end": "2022-04-06",
    "title": "Leading Indicators OECD: Leading indicators: CLI: Amplitude adjusted for OECD - Europe",
    "observation_start": "1966-11-01",
    "observation_end": "2022-02-01",
    "frequency": "Monthly",
    "frequency_short": "M",
    "units": "Index",
    "units_short": "Index",
    "seasonal_adjustment": "Seasonally Adjusted",
    "seasonal_adjustment_short": "SA",
    "last_updated": "2022-03-10 10:41:19-06",
    "popularity": 1,
    "group_popularity": 1,
    "notes": "OECD descriptor ID: LOLITOAA OECD unit ID: STSA OECD country ID: OECDE All OECD data should be cited as follows: OECD,\"Main Economic Indicators - complete database\"Main Economic Indicators(database)http://dx.doi.org/10.1787/data-00052-en(Accessed on date)Copyright, 2016, OECD. Reprinted with permission.",
    "path": "../Database/International Data/Institutions/OECD - Europe"
  },
  "OECDELOLITONOSTSAM": {
    "id": "OECDELOLITONOSTSAM",
    "realtime_start": "2022-04-06",
    "realtime_end": "2022-04-06",
    "title": "Leading Indicators OECD: Leading indicators: CLI: Normalised for OECD - Europe",
    "observation_start": "1966-11-01",
    "observation_end": "2022-02-01",
    "frequency": "Monthly",
    "frequency_short": "M",
    "units": "Index",
    "units_short": "Index",
    "seasonal_adjustment": "Seasonally Adjusted",
    "seasonal_adjustment_short": "SA",
    "last_updated": "2022-03-10 11:05:58-06",
    "popularity": 1,
    "group_popularity": 1,
    "notes": "OECD descriptor ID: LOLITONO OECD unit ID: STSA OECD country ID: OECDE All OECD data should be cited as follows: OECD,\"Main Economic Indicators - complete database\"Main Economic Indicators(database)http://dx.doi.org/10.1787/data-00052-en(Accessed on date)Copyright, 2016, OECD. Reprinted with permission.",
    "path": "../Database/International Data/Institutions/OECD - Europe"
  },
  "OECDELOLITOTRGYSAM": {
    "id": "OECDELOLITOTRGYSAM",
    "realtime_start": "2022-04-06",
    "realtime_end": "2022-04-06",
    "title": "Leading Indicators OECD: Leading indicators: CLI: Trend restored for OECD - Europe",
    "observation_start": "1967-11-01",
    "observation_end": "2021-11-01",
    "frequency": "Monthly",
    "frequency_short": "M",
    "units": "Growth rate same period previous year",
    "units_short": "Growth rate same period previous Yr.",
    "seasonal_adjustment": "Seasonally Adjusted",
    "seasonal_adjustment_short": "SA",
    "last_updated": "2022-03-10 11:05:58-06",
    "popularity": 1,
    "group_popularity": 1,
    "notes": "OECD descriptor ID: LOLITOTR OECD unit ID: GYSA OECD country ID: OECDE All OECD data should be cited as follows: OECD,\"Main Economic Indicators - complete database\"Main Economic Indicators(database)http://dx.doi.org/10.1787/data-00052-en(Accessed on date)Copyright, 2016, OECD. Reprinted with permission.",
    "path": "../Database/International Data/Institutions/OECD - Europe"
  },
  "OECDELOLITOTRSTSAM": {
    "id": "OECDELOLITOTRSTSAM",
    "realtime_start": "2022-04-06",
    "realtime_end": "2022-04-06",
    "title": "Leading Indicators OECD: Leading indicators: CLI: Trend restored for OECD - Europe",
    "observation_start": "1966-11-01",
    "observation_end": "2021-11-01",
    "frequency": "Monthly",
    "frequency_short": "M",
    "units": "Index",
    "units_short": "Index",
    "seasonal_adjustment": "Seasonally Adjusted",
    "seasonal_adjustment_short": "SA",
    "last_updated": "2022-03-10 11:05:57-06",
    "popularity": 1,
    "group_popularity": 1,
    "notes": "OECD descriptor ID: LOLITOTR OECD unit ID: STSA OECD country ID: OECDE All OECD data should be cited as follows: OECD,\"Main Economic Indicators - complete database\"Main Economic Indicators(database)http://dx.doi.org/10.1787/data-00052-en(Accessed on date)Copyright, 2016, OECD. Reprinted with permission.",
    "path": "../Database/International Data/Institutions/OECD - Europe"
  },
  "OECDELORSGPNOSTSAM": {
    "id": "OECDELORSGPNOSTSAM",
    "realtime_start": "2022-04-06",
    "realtime_end": "2022-04-06",
    "title": "Leading Indicators OECD: Reference series: Gross Domestic Product (GDP): Normalised for OECD - Europe",
    "observation_start": "1960-02-01",
    "observation_end": "2021-11-01",
    "frequency": "Monthly",
    "frequency_short": "M",
    "units": "Index",
    "units_short": "Index",
    "seasonal_adjustment": "Seasonally Adjusted",
    "seasonal_adjustment_short": "SA",
    "last_updated": "2022-03-10 11:05:57-06",
    "popularity": 2,
    "group_popularity": 2,
    "notes": "OECD descriptor ID: LORSGPNO OECD unit ID: STSA OECD country ID: OECDE All OECD data should be cited as follows: OECD,\"Main Economic Indicators - complete database\"Main Economic Indicators(database)http://dx.doi.org/10.1787/data-00052-en(Accessed on date)Copyright, 2016, OECD. Reprinted with permission.",
    "path": "../Database/International Data/Institutions/OECD - Europe"
  },
  "OECDELORSGPORGYSAM": {
    "id": "OECDELORSGPORGYSAM",
    "realtime_start": "2022-04-06",
    "realtime_end": "2022-04-06",
    "title": "Leading Indicators OECD: Reference series: Gross Domestic Product (GDP): Original series for OECD - Europe",
    "observation_start": "1961-02-01",
    "observation_end": "2021-11-01",
    "frequency": "Monthly",
    "frequency_short": "M",
    "units": "Growth rate same period previous year",
    "units_short": "Growth rate same period previous Yr.",
    "seasonal_adjustment": "Seasonally Adjusted",
    "seasonal_adjustment_short": "SA",
    "last_updated": "2022-03-10 10:41:27-06",
    "popularity": 5,
    "group_popularity": 7,
    "notes": "OECD descriptor ID: LORSGPOR OECD unit ID: GYSA OECD country ID: OECDE All OECD data should be cited as follows: OECD,\"Main Economic Indicators - complete database\"Main Economic Indicators(database)http://dx.doi.org/10.1787/data-00052-en(Accessed on date)Copyright, 2016, OECD. Reprinted with permission.",
    "path": "../Database/International Data/Institutions/OECD - Europe"
  },
  "OECDELORSGPORIXOBSAM": {
    "id": "OECDELORSGPORIXOBSAM",
    "realtime_start": "2022-04-06",
    "realtime_end": "2022-04-06",
    "title": "Leading Indicators OECD: Reference series: Gross Domestic Product (GDP): Original series for OECD - Europe",
    "observation_start": "1960-02-01",
    "observation_end": "2021-11-01",
    "frequency": "Monthly",
    "frequency_short": "M",
    "units": "Index 2015=100",
    "units_short": "Index 2015=100",
    "seasonal_adjustment": "Seasonally Adjusted",
    "seasonal_adjustment_short": "SA",
    "last_updated": "2022-03-10 11:05:56-06",
    "popularity": 4,
    "group_popularity": 7,
    "notes": "OECD descriptor ID: LORSGPOR OECD unit ID: IXOBSA OECD country ID: OECDE All OECD data should be cited as follows: OECD,\"Main Economic Indicators - complete database\"Main Economic Indicators(database)http://dx.doi.org/10.1787/data-00052-en(Accessed on date)Copyright, 2016, OECD. Reprinted with permission.",
    "path": "../Database/International Data/Institutions/OECD - Europe"
  },
  "OECDELORSGPRTSTSAM": {
    "id": "OECDELORSGPRTSTSAM",
    "realtime_start": "2022-04-06",
    "realtime_end": "2022-04-06",
    "title": "Leading Indicators OECD: Reference series: Gross Domestic Product (GDP): Ratio to trend for OECD - Europe",
    "observation_start": "1960-02-01",
    "observation_end": "2021-11-01",
    "frequency": "Monthly",
    "frequency_short": "M",
    "units": "Index",
    "units_short": "Index",
    "seasonal_adjustment": "Seasonally Adjusted",
    "seasonal_adjustment_short": "SA",
    "last_updated": "2022-03-10 11:05:56-06",
    "popularity": 1,
    "group_popularity": 1,
    "notes": "OECD descriptor ID: LORSGPRT OECD unit ID: STSA OECD country ID: OECDE All OECD data should be cited as follows: OECD,\"Main Economic Indicators - complete database\"Main Economic Indicators(database)http://dx.doi.org/10.1787/data-00052-en(Accessed on date)Copyright, 2016, OECD. Reprinted with permission.",
    "path": "../Database/International Data/Institutions/OECD - Europe"
  },
  "OECDELORSGPTDSTSAM": {
    "id": "OECDELORSGPTDSTSAM",
    "realtime_start": "2022-04-06",
    "realtime_end": "2022-04-06",
    "title": "Leading Indicators OECD: Reference series: Gross Domestic Product (GDP): Trend for OECD - Europe",
    "observation_start": "1960-02-01",
    "observation_end": "2021-11-01",
    "frequency": "Monthly",
    "frequency_short": "M",
    "units": "Index",
    "units_short": "Index",
    "seasonal_adjustment": "Seasonally Adjusted",
    "seasonal_adjustment_short": "SA",
    "last_updated": "2022-03-10 11:05:55-06",
    "popularity": 2,
    "group_popularity": 2,
    "notes": "OECD descriptor ID: LORSGPTD OECD unit ID: STSA OECD country ID: OECDE All OECD data should be cited as follows: OECD,\"Main Economic Indicators - complete database\"Main Economic Indicators(database)http://dx.doi.org/10.1787/data-00052-en(Accessed on date)Copyright, 2016, OECD. Reprinted with permission.",
    "path": "../Database/International Data/Institutions/OECD - Europe"
  },
  "OECDEMABMM301GPSAM": {
    "id": "OECDEMABMM301GPSAM",
    "realtime_start": "2022-04-06",
    "realtime_end": "2022-04-06",
    "title": "Monetary aggregates and their components: Broad money and components: M3: M3 for OECD - Europe",
    "observation_start": "1980-02-01",
    "observation_end": "2018-12-01",
    "frequency": "Monthly",
    "frequency_short": "M",
    "units": "Growth rate previous period",
    "units_short": "Growth rate previous period",
    "seasonal_adjustment": "Seasonally Adjusted",
    "seasonal_adjustment_short": "SA",
    "last_updated": "2022-02-15 10:48:03-06",
    "popularity": 1,
    "group_popularity": 1,
    "notes": "OECD descriptor ID: MABMM301 OECD unit ID: GPSA OECD country ID: OECDE All OECD data should be cited as follows: OECD,\"Main Economic Indicators - complete database\"Main Economic Indicators(database)http://dx.doi.org/10.1787/data-00052-en(Accessed on date)Copyright, 2016, OECD. Reprinted with permission.",
    "path": "../Database/International Data/Institutions/OECD - Europe"
  },
  "OECDEMABMM301GPSAQ": {
    "id": "OECDEMABMM301GPSAQ",
    "realtime_start": "2022-04-06",
    "realtime_end": "2022-04-06",
    "title": "Monetary aggregates and their components: Broad money and components: M3: M3 for OECD - Europe",
    "observation_start": "1980-04-01",
    "observation_end": "2018-10-01",
    "frequency": "Quarterly",
    "frequency_short": "Q",
    "units": "Growth rate previous period",
    "units_short": "Growth rate previous period",
    "seasonal_adjustment": "Seasonally Adjusted",
    "seasonal_adjustment_short": "SA",
    "last_updated": "2022-02-15 10:17:29-06",
    "popularity": 1,
    "group_popularity": 1,
    "notes": "OECD descriptor ID: MABMM301 OECD unit ID: GPSA OECD country ID: OECDE All OECD data should be cited as follows: OECD,\"Main Economic Indicators - complete database\"Main Economic Indicators(database)http://dx.doi.org/10.1787/data-00052-en(Accessed on date)Copyright, 2016, OECD. Reprinted with permission.",
    "path": "../Database/International Data/Institutions/OECD - Europe"
  },
  "OECDEMABMM301GYSAM": {
    "id": "OECDEMABMM301GYSAM",
    "realtime_start": "2022-04-06",
    "realtime_end": "2022-04-06",
    "title": "Monetary aggregates and their components: Broad money and components: M3: M3 for OECD - Europe",
    "observation_start": "1981-01-01",
    "observation_end": "2018-12-01",
    "frequency": "Monthly",
    "frequency_short": "M",
    "units": "Growth rate same period previous year",
    "units_short": "Growth rate same period previous Yr.",
    "seasonal_adjustment": "Seasonally Adjusted",
    "seasonal_adjustment_short": "SA",
    "last_updated": "2022-02-15 10:48:02-06",
    "popularity": 1,
    "group_popularity": 1,
    "notes": "OECD descriptor ID: MABMM301 OECD unit ID: GYSA OECD country ID: OECDE All OECD data should be cited as follows: OECD,\"Main Economic Indicators - complete database\"Main Economic Indicators(database)http://dx.doi.org/10.1787/data-00052-en(Accessed on date)Copyright, 2016, OECD. Reprinted with permission.",
    "path": "../Database/International Data/Institutions/OECD - Europe"
  },
  "OECDEMABMM301GYSAQ": {
    "id": "OECDEMABMM301GYSAQ",
    "realtime_start": "2022-04-06",
    "realtime_end": "2022-04-06",
    "title": "Monetary aggregates and their components: Broad money and components: M3: M3 for OECD - Europe",
    "observation_start": "1981-01-01",
    "observation_end": "2018-10-01",
    "frequency": "Quarterly",
    "frequency_short": "Q",
    "units": "Growth rate same period previous year",
    "units_short": "Growth rate same period previous Yr.",
    "seasonal_adjustment": "Seasonally Adjusted",
    "seasonal_adjustment_short": "SA",
    "last_updated": "2022-02-15 10:17:28-06",
    "popularity": 0,
    "group_popularity": 1,
    "notes": "OECD descriptor ID: MABMM301 OECD unit ID: GYSA OECD country ID: OECDE All OECD data should be cited as follows: OECD,\"Main Economic Indicators - complete database\"Main Economic Indicators(database)http://dx.doi.org/10.1787/data-00052-en(Accessed on date)Copyright, 2016, OECD. Reprinted with permission.",
    "path": "../Database/International Data/Institutions/OECD - Europe"
  },
  "OECDEMABMM301IXOBSAM": {
    "id": "OECDEMABMM301IXOBSAM",
    "realtime_start": "2022-04-06",
    "realtime_end": "2022-04-06",
    "title": "Monetary aggregates and their components: Broad money and components: M3: M3 for OECD - Europe",
    "observation_start": "1980-01-01",
    "observation_end": "2018-12-01",
    "frequency": "Monthly",
    "frequency_short": "M",
    "units": "Index 2015=100",
    "units_short": "Index 2015=100",
    "seasonal_adjustment": "Seasonally Adjusted",
    "seasonal_adjustment_short": "SA",
    "last_updated": "2022-02-15 10:48:02-06",
    "popularity": 1,
    "group_popularity": 1,
    "notes": "OECD descriptor ID: MABMM301 OECD unit ID: IXOBSA OECD country ID: OECDE All OECD data should be cited as follows: OECD,\"Main Economic Indicators - complete database\"Main Economic Indicators(database)http://dx.doi.org/10.1787/data-00052-en(Accessed on date)Copyright, 2016, OECD. Reprinted with permission.",
    "path": "../Database/International Data/Institutions/OECD - Europe"
  },
  "OECDEMABMM301IXOBSAQ": {
    "id": "OECDEMABMM301IXOBSAQ",
    "realtime_start": "2022-04-06",
    "realtime_end": "2022-04-06",
    "title": "Monetary aggregates and their components: Broad money and components: M3: M3 for OECD - Europe",
    "observation_start": "1980-01-01",
    "observation_end": "2018-10-01",
    "frequency": "Quarterly",
    "frequency_short": "Q",
    "units": "Index 2015=100",
    "units_short": "Index 2015=100",
    "seasonal_adjustment": "Seasonally Adjusted",
    "seasonal_adjustment_short": "SA",
    "last_updated": "2022-02-15 10:17:28-06",
    "popularity": 1,
    "group_popularity": 1,
    "notes": "OECD descriptor ID: MABMM301 OECD unit ID: IXOBSA OECD country ID: OECDE All OECD data should be cited as follows: OECD,\"Main Economic Indicators - complete database\"Main Economic Indicators(database)http://dx.doi.org/10.1787/data-00052-en(Accessed on date)Copyright, 2016, OECD. Reprinted with permission.",
    "path": "../Database/International Data/Institutions/OECD - Europe"
  },
  "OECDEMANMM101GPSAM": {
    "id": "OECDEMANMM101GPSAM",
    "realtime_start": "2022-04-06",
    "realtime_end": "2022-04-06",
    "title": "Monetary aggregates and their components: Narrow money and components: M1 and components: M1 for OECD - Europe",
    "observation_start": "1980-02-01",
    "observation_end": "2018-12-01",
    "frequency": "Monthly",
    "frequency_short": "M",
    "units": "Growth rate previous period",
    "units_short": "Growth rate previous period",
    "seasonal_adjustment": "Seasonally Adjusted",
    "seasonal_adjustment_short": "SA",
    "last_updated": "2022-02-15 10:48:02-06",
    "popularity": 1,
    "group_popularity": 1,
    "notes": "OECD descriptor ID: MANMM101 OECD unit ID: GPSA OECD country ID: OECDE All OECD data should be cited as follows: OECD,\"Main Economic Indicators - complete database\"Main Economic Indicators(database)http://dx.doi.org/10.1787/data-00052-en(Accessed on date)Copyright, 2016, OECD. Reprinted with permission.",
    "path": "../Database/International Data/Institutions/OECD - Europe"
  },
  "OECDEMANMM101GPSAQ": {
    "id": "OECDEMANMM101GPSAQ",
    "realtime_start": "2022-04-06",
    "realtime_end": "2022-04-06",
    "title": "Monetary aggregates and their components: Narrow money and components: M1 and components: M1 for OECD - Europe",
    "observation_start": "1980-04-01",
    "observation_end": "2018-10-01",
    "frequency": "Quarterly",
    "frequency_short": "Q",
    "units": "Growth rate previous period",
    "units_short": "Growth rate previous period",
    "seasonal_adjustment": "Seasonally Adjusted",
    "seasonal_adjustment_short": "SA",
    "last_updated": "2022-02-15 10:17:28-06",
    "popularity": 0,
    "group_popularity": 1,
    "notes": "OECD descriptor ID: MANMM101 OECD unit ID: GPSA OECD country ID: OECDE All OECD data should be cited as follows: OECD,\"Main Economic Indicators - complete database\"Main Economic Indicators(database)http://dx.doi.org/10.1787/data-00052-en(Accessed on date)Copyright, 2016, OECD. Reprinted with permission.",
    "path": "../Database/International Data/Institutions/OECD - Europe"
  },
  "OECDEMANMM101IXOBSAM": {
    "id": "OECDEMANMM101IXOBSAM",
    "realtime_start": "2022-04-06",
    "realtime_end": "2022-04-06",
    "title": "Monetary aggregates and their components: Narrow money and components: M1 and components: M1 for OECD - Europe",
    "observation_start": "1980-01-01",
    "observation_end": "2018-12-01",
    "frequency": "Monthly",
    "frequency_short": "M",
    "units": "Index 2015=100",
    "units_short": "Index 2015=100",
    "seasonal_adjustment": "Seasonally Adjusted",
    "seasonal_adjustment_short": "SA",
    "last_updated": "2022-02-15 10:48:01-06",
    "popularity": 1,
    "group_popularity": 1,
    "notes": "OECD descriptor ID: MANMM101 OECD unit ID: IXOBSA OECD country ID: OECDE All OECD data should be cited as follows: OECD,\"Main Economic Indicators - complete database\"Main Economic Indicators(database)http://dx.doi.org/10.1787/data-00052-en(Accessed on date)Copyright, 2016, OECD. Reprinted with permission.",
    "path": "../Database/International Data/Institutions/OECD - Europe"
  },
  "OECDEMANMM101IXOBSAQ": {
    "id": "OECDEMANMM101IXOBSAQ",
    "realtime_start": "2022-04-06",
    "realtime_end": "2022-04-06",
    "title": "Monetary aggregates and their components: Narrow money and components: M1 and components: M1 for OECD - Europe",
    "observation_start": "1980-01-01",
    "observation_end": "2018-10-01",
    "frequency": "Quarterly",
    "frequency_short": "Q",
    "units": "Index 2015=100",
    "units_short": "Index 2015=100",
    "seasonal_adjustment": "Seasonally Adjusted",
    "seasonal_adjustment_short": "SA",
    "last_updated": "2022-02-15 10:17:28-06",
    "popularity": 0,
    "group_popularity": 1,
    "notes": "OECD descriptor ID: MANMM101 OECD unit ID: IXOBSA OECD country ID: OECDE All OECD data should be cited as follows: OECD,\"Main Economic Indicators - complete database\"Main Economic Indicators(database)http://dx.doi.org/10.1787/data-00052-en(Accessed on date)Copyright, 2016, OECD. Reprinted with permission.",
    "path": "../Database/International Data/Institutions/OECD - Europe"
  },
  "OECDEPIEAMP02GPM": {
    "id": "OECDEPIEAMP02GPM",
    "realtime_start": "2022-04-06",
    "realtime_end": "2022-04-06",
    "title": "Producer Prices Index: Economic activities: Manufacturing: Domestic for OECD - Europe",
    "observation_start": "1982-02-01",
    "observation_end": "2022-01-01",
    "frequency": "Monthly",
    "frequency_short": "M",
    "units": "Growth rate previous period",
    "units_short": "Growth rate previous period",
    "seasonal_adjustment": "Not Seasonally Adjusted",
    "seasonal_adjustment_short": "NSA",
    "last_updated": "2022-03-10 11:05:55-06",
    "popularity": 1,
    "group_popularity": 1,
    "notes": "OECD descriptor ID: PIEAMP02 OECD unit ID: GP OECD country ID: OECDE All OECD data should be cited as follows: OECD,\"Main Economic Indicators - complete database\"Main Economic Indicators(database)http://dx.doi.org/10.1787/data-00052-en(Accessed on date)Copyright, 2016, OECD. Reprinted with permission.",
    "path": "../Database/International Data/Institutions/OECD - Europe"
  },
  "OECDEPIEAMP02GPQ": {
    "id": "OECDEPIEAMP02GPQ",
    "realtime_start": "2022-04-06",
    "realtime_end": "2022-04-06",
    "title": "Producer Prices Index: Economic activities: Manufacturing: Domestic for OECD - Europe",
    "observation_start": "1982-04-01",
    "observation_end": "2021-10-01",
    "frequency": "Quarterly",
    "frequency_short": "Q",
    "units": "Growth rate previous period",
    "units_short": "Growth rate previous period",
    "seasonal_adjustment": "Not Seasonally Adjusted",
    "seasonal_adjustment_short": "NSA",
    "last_updated": "2022-03-10 12:07:35-06",
    "popularity": 0,
    "group_popularity": 1,
    "notes": "OECD descriptor ID: PIEAMP02 OECD unit ID: GP OECD country ID: OECDE All OECD data should be cited as follows: OECD,\"Main Economic Indicators - complete database\"Main Economic Indicators(database)http://dx.doi.org/10.1787/data-00052-en(Accessed on date)Copyright, 2016, OECD. Reprinted with permission.",
    "path": "../Database/International Data/Institutions/OECD - Europe"
  },
  "OECDEPIEAMP02GYM": {
    "id": "OECDEPIEAMP02GYM",
    "realtime_start": "2022-04-06",
    "realtime_end": "2022-04-06",
    "title": "Producer Prices Index: Economic activities: Manufacturing: Domestic for OECD - Europe",
    "observation_start": "1983-01-01",
    "observation_end": "2022-01-01",
    "frequency": "Monthly",
    "frequency_short": "M",
    "units": "Growth rate same period previous year",
    "units_short": "Growth rate same period previous Yr.",
    "seasonal_adjustment": "Not Seasonally Adjusted",
    "seasonal_adjustment_short": "NSA",
    "last_updated": "2022-03-10 11:05:54-06",
    "popularity": 1,
    "group_popularity": 1,
    "notes": "OECD descriptor ID: PIEAMP02 OECD unit ID: GY OECD country ID: OECDE All OECD data should be cited as follows: OECD,\"Main Economic Indicators - complete database\"Main Economic Indicators(database)http://dx.doi.org/10.1787/data-00052-en(Accessed on date)Copyright, 2016, OECD. Reprinted with permission.",
    "path": "../Database/International Data/Institutions/OECD - Europe"
  },
  "OECDEPIEAMP02GYQ": {
    "id": "OECDEPIEAMP02GYQ",
    "realtime_start": "2022-04-06",
    "realtime_end": "2022-04-06",
    "title": "Producer Prices Index: Economic activities: Manufacturing: Domestic for OECD - Europe",
    "observation_start": "1983-01-01",
    "observation_end": "2021-10-01",
    "frequency": "Quarterly",
    "frequency_short": "Q",
    "units": "Growth rate same period previous year",
    "units_short": "Growth rate same period previous Yr.",
    "seasonal_adjustment": "Not Seasonally Adjusted",
    "seasonal_adjustment_short": "NSA",
    "last_updated": "2022-03-10 12:07:35-06",
    "popularity": 0,
    "group_popularity": 1,
    "notes": "OECD descriptor ID: PIEAMP02 OECD unit ID: GY OECD country ID: OECDE All OECD data should be cited as follows: OECD,\"Main Economic Indicators - complete database\"Main Economic Indicators(database)http://dx.doi.org/10.1787/data-00052-en(Accessed on date)Copyright, 2016, OECD. Reprinted with permission.",
    "path": "../Database/International Data/Institutions/OECD - Europe"
  },
  "OECDEPIEAMP02IXOBM": {
    "id": "OECDEPIEAMP02IXOBM",
    "realtime_start": "2022-04-06",
    "realtime_end": "2022-04-06",
    "title": "Producer Prices Index: Economic activities: Manufacturing: Domestic for OECD - Europe",
    "observation_start": "1982-01-01",
    "observation_end": "2022-01-01",
    "frequency": "Monthly",
    "frequency_short": "M",
    "units": "Index 2015=100",
    "units_short": "Index 2015=100",
    "seasonal_adjustment": "Not Seasonally Adjusted",
    "seasonal_adjustment_short": "NSA",
    "last_updated": "2022-03-10 11:05:54-06",
    "popularity": 1,
    "group_popularity": 1,
    "notes": "OECD descriptor ID: PIEAMP02 OECD unit ID: IXOB OECD country ID: OECDE All OECD data should be cited as follows: OECD,\"Main Economic Indicators - complete database\"Main Economic Indicators(database)http://dx.doi.org/10.1787/data-00052-en(Accessed on date)Copyright, 2016, OECD. Reprinted with permission.",
    "path": "../Database/International Data/Institutions/OECD - Europe"
  },
  "OECDEPIEAMP02IXOBQ": {
    "id": "OECDEPIEAMP02IXOBQ",
    "realtime_start": "2022-04-06",
    "realtime_end": "2022-04-06",
    "title": "Producer Prices Index: Economic activities: Manufacturing: Domestic for OECD - Europe",
    "observation_start": "1982-01-01",
    "observation_end": "2021-10-01",
    "frequency": "Quarterly",
    "frequency_short": "Q",
    "units": "Index 2015=100",
    "units_short": "Index 2015=100",
    "seasonal_adjustment": "Not Seasonally Adjusted",
    "seasonal_adjustment_short": "NSA",
    "last_updated": "2022-03-10 10:31:11-06",
    "popularity": 1,
    "group_popularity": 1,
    "notes": "OECD descriptor ID: PIEAMP02 OECD unit ID: IXOB OECD country ID: OECDE All OECD data should be cited as follows: OECD,\"Main Economic Indicators - complete database\"Main Economic Indicators(database)http://dx.doi.org/10.1787/data-00052-en(Accessed on date)Copyright, 2016, OECD. Reprinted with permission.",
    "path": "../Database/International Data/Institutions/OECD - Europe"
  },
  "OECDEPRCNTO01GPSAM": {
    "id": "OECDEPRCNTO01GPSAM",
    "realtime_start": "2022-04-06",
    "realtime_end": "2022-04-06",
    "title": "Production: Construction: Total construction: Total for OECD - Europe",
    "observation_start": "1990-02-01",
    "observation_end": "2021-11-01",
    "frequency": "Monthly",
    "frequency_short": "M",
    "units": "Growth rate previous period",
    "units_short": "Growth rate previous period",
    "seasonal_adjustment": "Seasonally Adjusted",
    "seasonal_adjustment_short": "SA",
    "last_updated": "2022-02-15 10:48:01-06",
    "popularity": 1,
    "group_popularity": 4,
    "notes": "OECD descriptor ID: PRCNTO01 OECD unit ID: GPSA OECD country ID: OECDE All OECD data should be cited as follows: OECD,\"Main Economic Indicators - complete database\"Main Economic Indicators(database)http://dx.doi.org/10.1787/data-00052-en(Accessed on date)Copyright, 2016, OECD. Reprinted with permission.",
    "path": "../Database/International Data/Institutions/OECD - Europe"
  },
  "OECDEPRCNTO01GPSAQ": {
    "id": "OECDEPRCNTO01GPSAQ",
    "realtime_start": "2022-04-06",
    "realtime_end": "2022-04-06",
    "title": "Production: Construction: Total construction: Total for OECD - Europe",
    "observation_start": "1990-04-01",
    "observation_end": "2021-07-01",
    "frequency": "Quarterly",
    "frequency_short": "Q",
    "units": "Growth rate previous period",
    "units_short": "Growth rate previous period",
    "seasonal_adjustment": "Seasonally Adjusted",
    "seasonal_adjustment_short": "SA",
    "last_updated": "2022-02-15 11:20:02-06",
    "popularity": 0,
    "group_popularity": 4,
    "notes": "OECD descriptor ID: PRCNTO01 OECD unit ID: GPSA OECD country ID: OECDE All OECD data should be cited as follows: OECD,\"Main Economic Indicators - complete database\"Main Economic Indicators(database)http://dx.doi.org/10.1787/data-00052-en(Accessed on date)Copyright, 2016, OECD. Reprinted with permission.",
    "path": "../Database/International Data/Institutions/OECD - Europe"
  },
  "OECDEPRCNTO01GYSAM": {
    "id": "OECDEPRCNTO01GYSAM",
    "realtime_start": "2022-04-06",
    "realtime_end": "2022-04-06",
    "title": "Production: Construction: Total construction: Total for OECD - Europe",
    "observation_start": "1991-01-01",
    "observation_end": "2021-11-01",
    "frequency": "Monthly",
    "frequency_short": "M",
    "units": "Growth rate same period previous year",
    "units_short": "Growth rate same period previous Yr.",
    "seasonal_adjustment": "Seasonally Adjusted",
    "seasonal_adjustment_short": "SA",
    "last_updated": "2022-02-15 10:48:01-06",
    "popularity": 1,
    "group_popularity": 4,
    "notes": "OECD descriptor ID: PRCNTO01 OECD unit ID: GYSA OECD country ID: OECDE All OECD data should be cited as follows: OECD,\"Main Economic Indicators - complete database\"Main Economic Indicators(database)http://dx.doi.org/10.1787/data-00052-en(Accessed on date)Copyright, 2016, OECD. Reprinted with permission.",
    "path": "../Database/International Data/Institutions/OECD - Europe"
  },
  "OECDEPRCNTO01GYSAQ": {
    "id": "OECDEPRCNTO01GYSAQ",
    "realtime_start": "2022-04-06",
    "realtime_end": "2022-04-06",
    "title": "Production: Construction: Total construction: Total for OECD - Europe",
    "observation_start": "1991-01-01",
    "observation_end": "2021-07-01",
    "frequency": "Quarterly",
    "frequency_short": "Q",
    "units": "Growth rate same period previous year",
    "units_short": "Growth rate same period previous Yr.",
    "seasonal_adjustment": "Seasonally Adjusted",
    "seasonal_adjustment_short": "SA",
    "last_updated": "2022-02-15 10:17:27-06",
    "popularity": 1,
    "group_popularity": 4,
    "notes": "OECD descriptor ID: PRCNTO01 OECD unit ID: GYSA OECD country ID: OECDE All OECD data should be cited as follows: OECD,\"Main Economic Indicators - complete database\"Main Economic Indicators(database)http://dx.doi.org/10.1787/data-00052-en(Accessed on date)Copyright, 2016, OECD. Reprinted with permission.",
    "path": "../Database/International Data/Institutions/OECD - Europe"
  },
  "OECDEPRCNTO01IXOBSAM": {
    "id": "OECDEPRCNTO01IXOBSAM",
    "realtime_start": "2022-04-06",
    "realtime_end": "2022-04-06",
    "title": "Production: Construction: Total construction: Total for OECD - Europe",
    "observation_start": "1990-01-01",
    "observation_end": "2021-11-01",
    "frequency": "Monthly",
    "frequency_short": "M",
    "units": "Index 2015=100",
    "units_short": "Index 2015=100",
    "seasonal_adjustment": "Seasonally Adjusted",
    "seasonal_adjustment_short": "SA",
    "last_updated": "2022-02-15 10:48:00-06",
    "popularity": 1,
    "group_popularity": 4,
    "notes": "OECD descriptor ID: PRCNTO01 OECD unit ID: IXOBSA OECD country ID: OECDE All OECD data should be cited as follows: OECD,\"Main Economic Indicators - complete database\"Main Economic Indicators(database)http://dx.doi.org/10.1787/data-00052-en(Accessed on date)Copyright, 2016, OECD. Reprinted with permission.",
    "path": "../Database/International Data/Institutions/OECD - Europe"
  },
  "OECDEPRCNTO01IXOBSAQ": {
    "id": "OECDEPRCNTO01IXOBSAQ",
    "realtime_start": "2022-04-06",
    "realtime_end": "2022-04-06",
    "title": "Production: Construction: Total construction: Total for OECD - Europe",
    "observation_start": "1990-01-01",
    "observation_end": "2021-07-01",
    "frequency": "Quarterly",
    "frequency_short": "Q",
    "units": "Index 2015=100",
    "units_short": "Index 2015=100",
    "seasonal_adjustment": "Seasonally Adjusted",
    "seasonal_adjustment_short": "SA",
    "last_updated": "2022-02-15 10:17:27-06",
    "popularity": 2,
    "group_popularity": 4,
    "notes": "OECD descriptor ID: PRCNTO01 OECD unit ID: IXOBSA OECD country ID: OECDE All OECD data should be cited as follows: OECD,\"Main Economic Indicators - complete database\"Main Economic Indicators(database)http://dx.doi.org/10.1787/data-00052-en(Accessed on date)Copyright, 2016, OECD. Reprinted with permission.",
    "path": "../Database/International Data/Institutions/OECD - Europe"
  },
  "OECDEPRINTO01GPSAM": {
    "id": "OECDEPRINTO01GPSAM",
    "realtime_start": "2022-04-06",
    "realtime_end": "2022-04-06",
    "title": "Production: Industry: Total industry: Total industry excluding construction for OECD - Europe",
    "observation_start": "1960-02-01",
    "observation_end": "2021-11-01",
    "frequency": "Monthly",
    "frequency_short": "M",
    "units": "Growth rate previous period",
    "units_short": "Growth rate previous period",
    "seasonal_adjustment": "Seasonally Adjusted",
    "seasonal_adjustment_short": "SA",
    "last_updated": "2022-02-15 10:48:00-06",
    "popularity": 2,
    "group_popularity": 3,
    "notes": "OECD descriptor ID: PRINTO01 OECD unit ID: GPSA OECD country ID: OECDE All OECD data should be cited as follows: OECD,\"Main Economic Indicators - complete database\"Main Economic Indicators(database)http://dx.doi.org/10.1787/data-00052-en(Accessed on date)Copyright, 2016, OECD. Reprinted with permission.",
    "path": "../Database/International Data/Institutions/OECD - Europe"
  },
  "OECDEPRINTO01GPSAQ": {
    "id": "OECDEPRINTO01GPSAQ",
    "realtime_start": "2022-04-06",
    "realtime_end": "2022-04-06",
    "title": "Production: Industry: Total industry: Total industry excluding construction for OECD - Europe",
    "observation_start": "1960-04-01",
    "observation_end": "2021-07-01",
    "frequency": "Quarterly",
    "frequency_short": "Q",
    "units": "Growth rate previous period",
    "units_short": "Growth rate previous period",
    "seasonal_adjustment": "Seasonally Adjusted",
    "seasonal_adjustment_short": "SA",
    "last_updated": "2022-02-15 10:17:27-06",
    "popularity": 1,
    "group_popularity": 3,
    "notes": "OECD descriptor ID: PRINTO01 OECD unit ID: GPSA OECD country ID: OECDE All OECD data should be cited as follows: OECD,\"Main Economic Indicators - complete database\"Main Economic Indicators(database)http://dx.doi.org/10.1787/data-00052-en(Accessed on date)Copyright, 2016, OECD. Reprinted with permission.",
    "path": "../Database/International Data/Institutions/OECD - Europe"
  },
  "OECDEPRINTO01GYSAM": {
    "id": "OECDEPRINTO01GYSAM",
    "realtime_start": "2022-04-06",
    "realtime_end": "2022-04-06",
    "title": "Production: Industry: Total industry: Total industry excluding construction for OECD - Europe",
    "observation_start": "1961-01-01",
    "observation_end": "2021-11-01",
    "frequency": "Monthly",
    "frequency_short": "M",
    "units": "Growth rate same period previous year",
    "units_short": "Growth rate same period previous Yr.",
    "seasonal_adjustment": "Seasonally Adjusted",
    "seasonal_adjustment_short": "SA",
    "last_updated": "2022-02-15 10:25:10-06",
    "popularity": 2,
    "group_popularity": 3,
    "notes": "OECD descriptor ID: PRINTO01 OECD unit ID: GYSA OECD country ID: OECDE All OECD data should be cited as follows: OECD,\"Main Economic Indicators - complete database\"Main Economic Indicators(database)http://dx.doi.org/10.1787/data-00052-en(Accessed on date)Copyright, 2016, OECD. Reprinted with permission.",
    "path": "../Database/International Data/Institutions/OECD - Europe"
  },
  "OECDEPRINTO01GYSAQ": {
    "id": "OECDEPRINTO01GYSAQ",
    "realtime_start": "2022-04-06",
    "realtime_end": "2022-04-06",
    "title": "Production: Industry: Total industry: Total industry excluding construction for OECD - Europe",
    "observation_start": "1961-01-01",
    "observation_end": "2021-07-01",
    "frequency": "Quarterly",
    "frequency_short": "Q",
    "units": "Growth rate same period previous year",
    "units_short": "Growth rate same period previous Yr.",
    "seasonal_adjustment": "Seasonally Adjusted",
    "seasonal_adjustment_short": "SA",
    "last_updated": "2022-02-15 10:17:27-06",
    "popularity": 1,
    "group_popularity": 3,
    "notes": "OECD descriptor ID: PRINTO01 OECD unit ID: GYSA OECD country ID: OECDE All OECD data should be cited as follows: OECD,\"Main Economic Indicators - complete database\"Main Economic Indicators(database)http://dx.doi.org/10.1787/data-00052-en(Accessed on date)Copyright, 2016, OECD. Reprinted with permission.",
    "path": "../Database/International Data/Institutions/OECD - Europe"
  },
  "OECDEPRINTO01IXOBSAM": {
    "id": "OECDEPRINTO01IXOBSAM",
    "realtime_start": "2022-04-06",
    "realtime_end": "2022-04-06",
    "title": "Production: Industry: Total industry: Total industry excluding construction for OECD - Europe",
    "observation_start": "1960-01-01",
    "observation_end": "2021-11-01",
    "frequency": "Monthly",
    "frequency_short": "M",
    "units": "Index 2015=100",
    "units_short": "Index 2015=100",
    "seasonal_adjustment": "Seasonally Adjusted",
    "seasonal_adjustment_short": "SA",
    "last_updated": "2022-02-15 10:48:00-06",
    "popularity": 1,
    "group_popularity": 3,
    "notes": "OECD descriptor ID: PRINTO01 OECD unit ID: IXOBSA OECD country ID: OECDE All OECD data should be cited as follows: OECD,\"Main Economic Indicators - complete database\"Main Economic Indicators(database)http://dx.doi.org/10.1787/data-00052-en(Accessed on date)Copyright, 2016, OECD. Reprinted with permission.",
    "path": "../Database/International Data/Institutions/OECD - Europe"
  },
  "OECDEPRINTO01IXOBSAQ": {
    "id": "OECDEPRINTO01IXOBSAQ",
    "realtime_start": "2022-04-06",
    "realtime_end": "2022-04-06",
    "title": "Production: Industry: Total industry: Total industry excluding construction for OECD - Europe",
    "observation_start": "1960-01-01",
    "observation_end": "2021-07-01",
    "frequency": "Quarterly",
    "frequency_short": "Q",
    "units": "Index 2015=100",
    "units_short": "Index 2015=100",
    "seasonal_adjustment": "Seasonally Adjusted",
    "seasonal_adjustment_short": "SA",
    "last_updated": "2022-02-15 10:14:10-06",
    "popularity": 1,
    "group_popularity": 3,
    "notes": "OECD descriptor ID: PRINTO01 OECD unit ID: IXOBSA OECD country ID: OECDE All OECD data should be cited as follows: OECD,\"Main Economic Indicators - complete database\"Main Economic Indicators(database)http://dx.doi.org/10.1787/data-00052-en(Accessed on date)Copyright, 2016, OECD. Reprinted with permission.",
    "path": "../Database/International Data/Institutions/OECD - Europe"
  },
  "OECDEPRMNTO01GPSAM": {
    "id": "OECDEPRMNTO01GPSAM",
    "realtime_start": "2022-04-06",
    "realtime_end": "2022-04-06",
    "title": "Production: Manufacturing: Total manufacturing: Total manufacturing for OECD - Europe",
    "observation_start": "1990-02-01",
    "observation_end": "2021-11-01",
    "frequency": "Monthly",
    "frequency_short": "M",
    "units": "Growth rate previous period",
    "units_short": "Growth rate previous period",
    "seasonal_adjustment": "Seasonally Adjusted",
    "seasonal_adjustment_short": "SA",
    "last_updated": "2022-02-15 10:48:00-06",
    "popularity": 1,
    "group_popularity": 1,
    "notes": "OECD descriptor ID: PRMNTO01 OECD unit ID: GPSA OECD country ID: OECDE All OECD data should be cited as follows: OECD,\"Main Economic Indicators - complete database\"Main Economic Indicators(database)http://dx.doi.org/10.1787/data-00052-en(Accessed on date)Copyright, 2016, OECD. Reprinted with permission.",
    "path": "../Database/International Data/Institutions/OECD - Europe"
  },
  "OECDEPRMNTO01GPSAQ": {
    "id": "OECDEPRMNTO01GPSAQ",
    "realtime_start": "2022-04-06",
    "realtime_end": "2022-04-06",
    "title": "Production: Manufacturing: Total manufacturing: Total manufacturing for OECD - Europe",
    "observation_start": "1990-04-01",
    "observation_end": "2021-07-01",
    "frequency": "Quarterly",
    "frequency_short": "Q",
    "units": "Growth rate previous period",
    "units_short": "Growth rate previous period",
    "seasonal_adjustment": "Seasonally Adjusted",
    "seasonal_adjustment_short": "SA",
    "last_updated": "2022-02-15 10:17:26-06",
    "popularity": 1,
    "group_popularity": 1,
    "notes": "OECD descriptor ID: PRMNTO01 OECD unit ID: GPSA OECD country ID: OECDE All OECD data should be cited as follows: OECD,\"Main Economic Indicators - complete database\"Main Economic Indicators(database)http://dx.doi.org/10.1787/data-00052-en(Accessed on date)Copyright, 2016, OECD. Reprinted with permission.",
    "path": "../Database/International Data/Institutions/OECD - Europe"
  },
  "OECDEPRMNTO01GYSAM": {
    "id": "OECDEPRMNTO01GYSAM",
    "realtime_start": "2022-04-06",
    "realtime_end": "2022-04-06",
    "title": "Production: Manufacturing: Total manufacturing: Total manufacturing for OECD - Europe",
    "observation_start": "1991-01-01",
    "observation_end": "2021-11-01",
    "frequency": "Monthly",
    "frequency_short": "M",
    "units": "Growth rate same period previous year",
    "units_short": "Growth rate same period previous Yr.",
    "seasonal_adjustment": "Seasonally Adjusted",
    "seasonal_adjustment_short": "SA",
    "last_updated": "2022-02-15 10:47:59-06",
    "popularity": 1,
    "group_popularity": 1,
    "notes": "OECD descriptor ID: PRMNTO01 OECD unit ID: GYSA OECD country ID: OECDE All OECD data should be cited as follows: OECD,\"Main Economic Indicators - complete database\"Main Economic Indicators(database)http://dx.doi.org/10.1787/data-00052-en(Accessed on date)Copyright, 2016, OECD. Reprinted with permission.",
    "path": "../Database/International Data/Institutions/OECD - Europe"
  },
  "OECDEPRMNTO01GYSAQ": {
    "id": "OECDEPRMNTO01GYSAQ",
    "realtime_start": "2022-04-06",
    "realtime_end": "2022-04-06",
    "title": "Production: Manufacturing: Total manufacturing: Total manufacturing for OECD - Europe",
    "observation_start": "1991-01-01",
    "observation_end": "2021-07-01",
    "frequency": "Quarterly",
    "frequency_short": "Q",
    "units": "Growth rate same period previous year",
    "units_short": "Growth rate same period previous Yr.",
    "seasonal_adjustment": "Seasonally Adjusted",
    "seasonal_adjustment_short": "SA",
    "last_updated": "2022-02-15 10:17:26-06",
    "popularity": 0,
    "group_popularity": 1,
    "notes": "OECD descriptor ID: PRMNTO01 OECD unit ID: GYSA OECD country ID: OECDE All OECD data should be cited as follows: OECD,\"Main Economic Indicators - complete database\"Main Economic Indicators(database)http://dx.doi.org/10.1787/data-00052-en(Accessed on date)Copyright, 2016, OECD. Reprinted with permission.",
    "path": "../Database/International Data/Institutions/OECD - Europe"
  },
  "OECDEPRMNTO01IXOBSAM": {
    "id": "OECDEPRMNTO01IXOBSAM",
    "realtime_start": "2022-04-06",
    "realtime_end": "2022-04-06",
    "title": "Production: Manufacturing: Total manufacturing: Total manufacturing for OECD - Europe",
    "observation_start": "1990-01-01",
    "observation_end": "2021-11-01",
    "frequency": "Monthly",
    "frequency_short": "M",
    "units": "Index 2015=100",
    "units_short": "Index 2015=100",
    "seasonal_adjustment": "Seasonally Adjusted",
    "seasonal_adjustment_short": "SA",
    "last_updated": "2022-02-15 10:47:59-06",
    "popularity": 1,
    "group_popularity": 1,
    "notes": "OECD descriptor ID: PRMNTO01 OECD unit ID: IXOBSA OECD country ID: OECDE All OECD data should be cited as follows: OECD,\"Main Economic Indicators - complete database\"Main Economic Indicators(database)http://dx.doi.org/10.1787/data-00052-en(Accessed on date)Copyright, 2016, OECD. Reprinted with permission.",
    "path": "../Database/International Data/Institutions/OECD - Europe"
  },
  "OECDEPRMNTO01IXOBSAQ": {
    "id": "OECDEPRMNTO01IXOBSAQ",
    "realtime_start": "2022-04-06",
    "realtime_end": "2022-04-06",
    "title": "Production: Manufacturing: Total manufacturing: Total manufacturing for OECD - Europe",
    "observation_start": "1990-01-01",
    "observation_end": "2021-07-01",
    "frequency": "Quarterly",
    "frequency_short": "Q",
    "units": "Index 2015=100",
    "units_short": "Index 2015=100",
    "seasonal_adjustment": "Seasonally Adjusted",
    "seasonal_adjustment_short": "SA",
    "last_updated": "2022-02-15 10:17:26-06",
    "popularity": 1,
    "group_popularity": 1,
    "notes": "OECD descriptor ID: PRMNTO01 OECD unit ID: IXOBSA OECD country ID: OECDE All OECD data should be cited as follows: OECD,\"Main Economic Indicators - complete database\"Main Economic Indicators(database)http://dx.doi.org/10.1787/data-00052-en(Accessed on date)Copyright, 2016, OECD. Reprinted with permission.",
    "path": "../Database/International Data/Institutions/OECD - Europe"
  },
  "OECDESLRTCR03GPSAM": {
    "id": "OECDESLRTCR03GPSAM",
    "realtime_start": "2022-04-06",
    "realtime_end": "2022-04-06",
    "title": "Sales: Retail trade: Car registration: Passenger cars for OECD - Europe",
    "observation_start": "1973-02-01",
    "observation_end": "2018-12-01",
    "frequency": "Monthly",
    "frequency_short": "M",
    "units": "Growth rate previous period",
    "units_short": "Growth rate previous period",
    "seasonal_adjustment": "Seasonally Adjusted",
    "seasonal_adjustment_short": "SA",
    "last_updated": "2022-01-18 12:05:23-06",
    "popularity": 1,
    "group_popularity": 1,
    "notes": "OECD descriptor ID: SLRTCR03 OECD unit ID: GPSA OECD country ID: OECDE All OECD data should be cited as follows: OECD,\"Main Economic Indicators - complete database\"Main Economic Indicators(database)http://dx.doi.org/10.1787/data-00052-en(Accessed on date)Copyright, 2016, OECD. Reprinted with permission.",
    "path": "../Database/International Data/Institutions/OECD - Europe"
  },
  "OECDESLRTCR03GPSAQ": {
    "id": "OECDESLRTCR03GPSAQ",
    "realtime_start": "2022-04-06",
    "realtime_end": "2022-04-06",
    "title": "Sales: Retail trade: Car registration: Passenger cars for OECD - Europe",
    "observation_start": "1973-04-01",
    "observation_end": "2018-10-01",
    "frequency": "Quarterly",
    "frequency_short": "Q",
    "units": "Growth rate previous period",
    "units_short": "Growth rate previous period",
    "seasonal_adjustment": "Seasonally Adjusted",
    "seasonal_adjustment_short": "SA",
    "last_updated": "2022-03-10 10:35:39-06",
    "popularity": 1,
    "group_popularity": 1,
    "notes": "OECD descriptor ID: SLRTCR03 OECD unit ID: GPSA OECD country ID: OECDE All OECD data should be cited as follows: OECD,\"Main Economic Indicators - complete database\"Main Economic Indicators(database)http://dx.doi.org/10.1787/data-00052-en(Accessed on date)Copyright, 2016, OECD. Reprinted with permission.",
    "path": "../Database/International Data/Institutions/OECD - Europe"
  },
  "OECDESLRTCR03GYSAM": {
    "id": "OECDESLRTCR03GYSAM",
    "realtime_start": "2022-04-06",
    "realtime_end": "2022-04-06",
    "title": "Sales: Retail trade: Car registration: Passenger cars for OECD - Europe",
    "observation_start": "1974-01-01",
    "observation_end": "2018-12-01",
    "frequency": "Monthly",
    "frequency_short": "M",
    "units": "Growth rate same period previous year",
    "units_short": "Growth rate same period previous Yr.",
    "seasonal_adjustment": "Seasonally Adjusted",
    "seasonal_adjustment_short": "SA",
    "last_updated": "2022-01-18 12:05:22-06",
    "popularity": 1,
    "group_popularity": 1,
    "notes": "OECD descriptor ID: SLRTCR03 OECD unit ID: GYSA OECD country ID: OECDE All OECD data should be cited as follows: OECD,\"Main Economic Indicators - complete database\"Main Economic Indicators(database)http://dx.doi.org/10.1787/data-00052-en(Accessed on date)Copyright, 2016, OECD. Reprinted with permission.",
    "path": "../Database/International Data/Institutions/OECD - Europe"
  },
  "OECDESLRTCR03GYSAQ": {
    "id": "OECDESLRTCR03GYSAQ",
    "realtime_start": "2022-04-06",
    "realtime_end": "2022-04-06",
    "title": "Sales: Retail trade: Car registration: Passenger cars for OECD - Europe",
    "observation_start": "1974-01-01",
    "observation_end": "2018-10-01",
    "frequency": "Quarterly",
    "frequency_short": "Q",
    "units": "Growth rate same period previous year",
    "units_short": "Growth rate same period previous Yr.",
    "seasonal_adjustment": "Seasonally Adjusted",
    "seasonal_adjustment_short": "SA",
    "last_updated": "2021-10-13 14:40:47-05",
    "popularity": 1,
    "group_popularity": 1,
    "notes": "OECD descriptor ID: SLRTCR03 OECD unit ID: GYSA OECD country ID: OECDE All OECD data should be cited as follows: OECD,\"Main Economic Indicators - complete database\"Main Economic Indicators(database)http://dx.doi.org/10.1787/data-00052-en(Accessed on date)Copyright, 2016, OECD. Reprinted with permission.",
    "path": "../Database/International Data/Institutions/OECD - Europe"
  },
  "OECDESLRTCR03IXOBSAM": {
    "id": "OECDESLRTCR03IXOBSAM",
    "realtime_start": "2022-04-06",
    "realtime_end": "2022-04-06",
    "title": "Sales: Retail trade: Car registration: Passenger cars for OECD - Europe",
    "observation_start": "1973-01-01",
    "observation_end": "2018-12-01",
    "frequency": "Monthly",
    "frequency_short": "M",
    "units": "Index 2015=100",
    "units_short": "Index 2015=100",
    "seasonal_adjustment": "Seasonally Adjusted",
    "seasonal_adjustment_short": "SA",
    "last_updated": "2022-03-10 11:05:54-06",
    "popularity": 1,
    "group_popularity": 1,
    "notes": "OECD descriptor ID: SLRTCR03 OECD unit ID: IXOBSA OECD country ID: OECDE All OECD data should be cited as follows: OECD,\"Main Economic Indicators - complete database\"Main Economic Indicators(database)http://dx.doi.org/10.1787/data-00052-en(Accessed on date)Copyright, 2016, OECD. Reprinted with permission.",
    "path": "../Database/International Data/Institutions/OECD - Europe"
  },
  "OECDESLRTCR03IXOBSAQ": {
    "id": "OECDESLRTCR03IXOBSAQ",
    "realtime_start": "2022-04-06",
    "realtime_end": "2022-04-06",
    "title": "Sales: Retail trade: Car registration: Passenger cars for OECD - Europe",
    "observation_start": "1973-01-01",
    "observation_end": "2018-10-01",
    "frequency": "Quarterly",
    "frequency_short": "Q",
    "units": "Index 2015=100",
    "units_short": "Index 2015=100",
    "seasonal_adjustment": "Seasonally Adjusted",
    "seasonal_adjustment_short": "SA",
    "last_updated": "2021-12-14 15:55:34-06",
    "popularity": 1,
    "group_popularity": 1,
    "notes": "OECD descriptor ID: SLRTCR03 OECD unit ID: IXOBSA OECD country ID: OECDE All OECD data should be cited as follows: OECD,\"Main Economic Indicators - complete database\"Main Economic Indicators(database)http://dx.doi.org/10.1787/data-00052-en(Accessed on date)Copyright, 2016, OECD. Reprinted with permission.",
    "path": "../Database/International Data/Institutions/OECD - Europe"
  },
  "OECDESLRTTO01GPSAM": {
    "id": "OECDESLRTTO01GPSAM",
    "realtime_start": "2022-04-06",
    "realtime_end": "2022-04-06",
    "title": "Sales: Retail trade: Total retail trade: Volume for OECD - Europe",
    "observation_start": "1990-02-01",
    "observation_end": "2021-11-01",
    "frequency": "Monthly",
    "frequency_short": "M",
    "units": "Growth rate previous period",
    "units_short": "Growth rate previous period",
    "seasonal_adjustment": "Seasonally Adjusted",
    "seasonal_adjustment_short": "SA",
    "last_updated": "2022-02-15 10:47:59-06",
    "popularity": 1,
    "group_popularity": 2,
    "notes": "OECD descriptor ID: SLRTTO01 OECD unit ID: GPSA OECD country ID: OECDE All OECD data should be cited as follows: OECD,\"Main Economic Indicators - complete database\"Main Economic Indicators(database)http://dx.doi.org/10.1787/data-00052-en(Accessed on date)Copyright, 2016, OECD. Reprinted with permission.",
    "path": "../Database/International Data/Institutions/OECD - Europe"
  },
  "OECDESLRTTO01GPSAQ": {
    "id": "OECDESLRTTO01GPSAQ",
    "realtime_start": "2022-04-06",
    "realtime_end": "2022-04-06",
    "title": "Sales: Retail trade: Total retail trade: Volume for OECD - Europe",
    "observation_start": "1990-04-01",
    "observation_end": "2021-07-01",
    "frequency": "Quarterly",
    "frequency_short": "Q",
    "units": "Growth rate previous period",
    "units_short": "Growth rate previous period",
    "seasonal_adjustment": "Seasonally Adjusted",
    "seasonal_adjustment_short": "SA",
    "last_updated": "2022-02-15 10:17:25-06",
    "popularity": 1,
    "group_popularity": 2,
    "notes": "OECD descriptor ID: SLRTTO01 OECD unit ID: GPSA OECD country ID: OECDE All OECD data should be cited as follows: OECD,\"Main Economic Indicators - complete database\"Main Economic Indicators(database)http://dx.doi.org/10.1787/data-00052-en(Accessed on date)Copyright, 2016, OECD. Reprinted with permission.",
    "path": "../Database/International Data/Institutions/OECD - Europe"
  },
  "OECDESLRTTO01GYSAM": {
    "id": "OECDESLRTTO01GYSAM",
    "realtime_start": "2022-04-06",
    "realtime_end": "2022-04-06",
    "title": "Sales: Retail trade: Total retail trade: Volume for OECD - Europe",
    "observation_start": "1991-01-01",
    "observation_end": "2021-11-01",
    "frequency": "Monthly",
    "frequency_short": "M",
    "units": "Growth rate same period previous year",
    "units_short": "Growth rate same period previous Yr.",
    "seasonal_adjustment": "Seasonally Adjusted",
    "seasonal_adjustment_short": "SA",
    "last_updated": "2022-02-15 10:47:58-06",
    "popularity": 1,
    "group_popularity": 2,
    "notes": "OECD descriptor ID: SLRTTO01 OECD unit ID: GYSA OECD country ID: OECDE All OECD data should be cited as follows: OECD,\"Main Economic Indicators - complete database\"Main Economic Indicators(database)http://dx.doi.org/10.1787/data-00052-en(Accessed on date)Copyright, 2016, OECD. Reprinted with permission.",
    "path": "../Database/International Data/Institutions/OECD - Europe"
  },
  "OECDESLRTTO01GYSAQ": {
    "id": "OECDESLRTTO01GYSAQ",
    "realtime_start": "2022-04-06",
    "realtime_end": "2022-04-06",
    "title": "Sales: Retail trade: Total retail trade: Volume for OECD - Europe",
    "observation_start": "1991-01-01",
    "observation_end": "2021-07-01",
    "frequency": "Quarterly",
    "frequency_short": "Q",
    "units": "Growth rate same period previous year",
    "units_short": "Growth rate same period previous Yr.",
    "seasonal_adjustment": "Seasonally Adjusted",
    "seasonal_adjustment_short": "SA",
    "last_updated": "2022-02-15 10:17:25-06",
    "popularity": 1,
    "group_popularity": 2,
    "notes": "OECD descriptor ID: SLRTTO01 OECD unit ID: GYSA OECD country ID: OECDE All OECD data should be cited as follows: OECD,\"Main Economic Indicators - complete database\"Main Economic Indicators(database)http://dx.doi.org/10.1787/data-00052-en(Accessed on date)Copyright, 2016, OECD. Reprinted with permission.",
    "path": "../Database/International Data/Institutions/OECD - Europe"
  },
  "OECDESLRTTO01IXOBSAM": {
    "id": "OECDESLRTTO01IXOBSAM",
    "realtime_start": "2022-04-06",
    "realtime_end": "2022-04-06",
    "title": "Sales: Retail trade: Total retail trade: Volume for OECD - Europe",
    "observation_start": "1990-01-01",
    "observation_end": "2021-11-01",
    "frequency": "Monthly",
    "frequency_short": "M",
    "units": "Index 2015=100",
    "units_short": "Index 2015=100",
    "seasonal_adjustment": "Seasonally Adjusted",
    "seasonal_adjustment_short": "SA",
    "last_updated": "2022-02-15 10:47:58-06",
    "popularity": 1,
    "group_popularity": 2,
    "notes": "OECD descriptor ID: SLRTTO01 OECD unit ID: IXOBSA OECD country ID: OECDE All OECD data should be cited as follows: OECD,\"Main Economic Indicators - complete database\"Main Economic Indicators(database)http://dx.doi.org/10.1787/data-00052-en(Accessed on date)Copyright, 2016, OECD. Reprinted with permission.",
    "path": "../Database/International Data/Institutions/OECD - Europe"
  },
  "OECDESLRTTO01IXOBSAQ": {
    "id": "OECDESLRTTO01IXOBSAQ",
    "realtime_start": "2022-04-06",
    "realtime_end": "2022-04-06",
    "title": "Sales: Retail trade: Total retail trade: Volume for OECD - Europe",
    "observation_start": "1990-01-01",
    "observation_end": "2021-07-01",
    "frequency": "Quarterly",
    "frequency_short": "Q",
    "units": "Index 2015=100",
    "units_short": "Index 2015=100",
    "seasonal_adjustment": "Seasonally Adjusted",
    "seasonal_adjustment_short": "SA",
    "last_updated": "2022-02-15 10:17:25-06",
    "popularity": 1,
    "group_popularity": 2,
    "notes": "OECD descriptor ID: SLRTTO01 OECD unit ID: IXOBSA OECD country ID: OECDE All OECD data should be cited as follows: OECD,\"Main Economic Indicators - complete database\"Main Economic Indicators(database)http://dx.doi.org/10.1787/data-00052-en(Accessed on date)Copyright, 2016, OECD. Reprinted with permission.",
    "path": "../Database/International Data/Institutions/OECD - Europe"
  }
}